Workbook
Name Gross_margin: 'Break-Even'!$G$19
Name Sales_price_unit: 'Break-Even'!$F$5
Name Sales_volume_units: 'Break-Even'!$F$6
Name SalesCycle: Projections!$C$117
Name Total_fixed: 'Break-Even'!$G$29
Name Total_Sales: 'Break-Even'!$G$7
Name Total_variable: 'Break-Even'!$G$16
Name Unit_contrib_margin: 'Break-Even'!$F$18
Name Variable_costs_unit: 'Break-Even'!$F$10:$F$11
Name Variable_Unit_Cost: 'Break-Even'!$F$15

Sheet Welcome
F4: Subscription Financial Model Template
F5: version 2.04
G7: To Edit in Google Sheets Go to File > Make a Copy | J7: To Edit in Excel Go to File > Download
B10: Legal Disclaimer | F10: Help & Resources | M10: More Templates
B12: This document is provided as a reference and template, and the financial information included should not be considered an certified business valuation, or projection. The information provided by Slidebean Incorporated (“we,” “us” or “our”) on https://slidebean.com (the “Site”) is for general informational purposes only. All information on the Site is provided in good faith, however we make no representation or warranty of any kind, express or implied, regarding the accuracy, adequacy, validity, reliability, availability or completeness of any information on the Site. UNDER NO CIRCUMSTANCE SHALL WE HAVE ANY LIABILITY TO YOU FOR ANY LOSS OR DAMAGE OF ANY KIND INCURRED AS A RESULT OF THE USE OF THE SITE OR RELIANCE ON ANY INFORMATION PROVIDED ON THE SITE. YOUR USE OF THE SITE AND YOUR RELIANCE ON ANY INFORMATION ON THE SITE IS SOLELY AT YOUR OWN RISK. The Site cannot and does not contain financial advice. The financial information is provided for general informational and educational purposes only and is not a substitute for professional advice. Accordingly, before taking any actions based upon such information, we encourage you to consult with the appropriate professionals. We do not provide any kind of financial advice. THE USE OR RELIANCE OF ANY INFORMATION CONTAINED ON THIS SITE IS SOLELY AT YOUR OWN RISK. | F12: =HYPERLINK("https://www.youtube.com/watch?v=rwUxqjnksAc","Watch the Tutorial") -> Watch the Tutorial | M12: =HYPERLINK("https://slidebean.com/pitch-deck-template","Pitch Deck Template for Startups") -> Pitch Deck Template for Startups
F14: =HYPERLINK("https://calendly.com/slidebean-strategy-team/financial-model","Book a Call with our Experts") -> Book a Call with our Experts | M14: =HYPERLINK("https://checkout.slidebean.com/product/financial-model-template-saas","Subscription Business Financial Model") -> Subscription Business Financial Model
F15: Book a call with our financial modeling experts. They can walk you through specific questions in our formulas, or help you customize the model to your business.
M16: =HYPERLINK("https://checkout.slidebean.com/product/financial-model-template-ecommerce","eCommerce Platform Financial Model") -> eCommerce Platform Financial Model
F17: =HYPERLINK("https://slidebean.com/youtube#discord","Get Help from the Community") -> Get Help from the Community
F18: Join our Discord community and get your questions answered by fellow startup founders. | M18: =HYPERLINK("https://checkout.slidebean.com/product/marketplace-financial-model","Marketplace Financial Model") -> Marketplace Financial Model
F20: =HYPERLINK("https://app.hubspot.com/meetings/derek54/fin-model-call","Get a Custom Financial Model") -> Get a Custom Financial Model | M20: =HYPERLINK("https://checkout.slidebean.com/product/social-media-platform-financial-model-template","Social Media Platform Financial Model") -> Social Media Platform Financial Model
F21: Our team can build a custom financial model for your based on your specific business requirements. This service starts at $649.
M22: =HYPERLINK("https://checkout.slidebean.com/product/blog-news-site-financial-model-template","Blog/News Site Financial Model") -> Blog/News Site Financial Model

Sheet Change Log
B3: The Ultimate Financial Model for Startups | H3: 2.01 | I3: Fixed an issue with Organic Traffic driving paid customers revenue models not yet enabled. Revenue rows 63 and 122.
I4: Fixed the count of total active customers (Revenue row 37). It cause the support agents needed to be 0.
I5: Added Freeze Row/Column to some sheets that didn't have it.
B7: version 2.04 | H7: 2.02 | I7: New welcome page Removed hidden 'Slides' sheet
H9: 2.03 | I9: Fixed an issue with the Teams & Salaries formula that caused errors on the quarterly and annually hiring cycles
I10: Fixed formula error on SG&A row 77
I11: Changed the design of this (Change Log) Sheet
H13: 2.031 | I13: Fixed Revenue Rows 15/16 - Total Sales Team Budget and Total Marketing Budget was sourcing the wrong column from SG&A.
H14: 2.032 | I14: Fixed issue with Monthly Billing MRR not being reported. Revenue rows 105, 169 and 220.
H15: 2.033 | I15: Fixed issue with Inbound sales agents not being added to the Headcount.
I16: Removed VP of Sales as an option for Inbound Sales scaling
I17: Customer count was not including annual subscribers.
H19: 2.034 | I19: Formatting changes in the Revenue sheet
I20: Added SaaS Quick Ratio
I21: Fixed an error on the Outbound Sales delay for 2 months
H23: 2.04 | I23: Fixed an issue with the Marketing Team salaries not being referenced correctly.
I24: Fixed an issue with the annual salary increase referring the CEO cell.
I25: FS-Month Row 44 (D&A) was refererencing an incorrect cell in CAPEX.
I26: Typo on FS Rows 109 and 115
I27: Valuation Section on FS-Month was missing references.
I28: Fixed formatting issue in CAPEX Sheet
I29: Fixed typos and reference errors in Revenue KPIs

Sheet Intro
A1: =Settings!C5 -> VReeMind
A2: Financial Model Guide
A3: =+TODAY() -> 44143
A9: COLOR CODING
A11: Inputs/assumptions | B11: BLUE | C11: Inputs, or any hard-coded data, such as historical values, assumptions, and drivers.
A12: Formulas/results | B12: BLACK | C12: Formulas, calculations, or references deriving from inputs
A15: CONTENTS
A18: Settings | C18: General settings
A19: Salaries | C19: A summary of salaries and team members
A20: Projections | C20: Use this sheet to summarize the variables that directly affect the business projections
A21: Charts & KPIs | C21: A summary of P&L charts, capital requirements and other KPIs relevant to the business
A22: CapTable | C22: Capitalization table including estimated Round A clossing
A23: FS-Annual | C23: Projected annual financial statements
A24: FS-Month | C24: Projected monthly financial statements
A25: Revenue | C25: Detailed monthly revenue assumptions & projections
A26: COGS | C26: Detailed monthly cost of goods sold (COGS) assumptions & projections
A27: SG&A | C27: Detailed monthly selling, general & administrative expenses (SG&A) assumptions & projections
A28: WK+CAPEX | C28: Detailed monthly working capital (WK) & capital expenditures (CAPEX) assumptions & projections
A29: Funding - Equity Round Estimation | C29: A simple calculator to estimate the stock that needs to be issued on a (priced) round of funding
A30: Funding - Convertible Note Estimation | C30: A simple calculator to estimate the stock that needs to be issued on a convertible note funding round

Sheet Settings
A1: Item | B1: Format | C1: Input | D1: Notes
A4: GENERAL
A5: Company Name | C5: VReeMind
A6: Currency | C6: USD
A7: Model Start Date | C7: 43466
A10: FS-MONTH
A11: Initial Cash Balance | B11: =Settings!$C$6 -> USD | C11: 50000
A13: FS-ANNUAL
A15: Taxes & Inflation
A16: Income tax rate | B16: % | C16: 0 | D16: Will be used to estimate the the annual tax payment, that will be added to FS-Month
A17: Inflation | B17: % | C17: 0.03 | D17: Used for buiness valuation calculations
A19: Valuation
A20: Business terminal value | C20: xEBITDA | D20: This model will estimate your current business valuation based on a Discounted Cash Flow Model:
A21: Discount rate - Today | B21: % | C21: 0.15 | D21: https://www.investopedia.com/terms/d/dcf.asp#:~:text=Discounted%20cash%20flow%20(DCF)%20is,will%20generate%20in%20the%20future.
A22: xEBITDA | B22: Multiplier | C22: 10
A23: Debt/Capital Ratio | B23: % | C23: 0.05
A24: Debt interest rate | B24: % | C24: 0.1
A26: CAPEX
A28: OPERATING CASH
A29: Balance | B29: =Settings!$C$6 -> USD | C29: 0
A30: Percentage of revenues | B30: % | C30: 0.1
A32: Accounts Receivable
A33: Pending Income/Total Income | B33: % | C33: 0
A35: Pre-paid expenses
A36: Pre-paid Days Outstanding | B36: days | C36: 30
A38: Accounts Payable
A39: A/P as % of total COGS | B39: % | C39: 0
A41: CAPITAL EXPENDITURES
A42: Automatically estimate new computer purchases for new employees | B42: Dropdown | C42: YES
A43: Price per computer | B43: =$C$6 -> USD | C43: 1000
A45: TIME FOR ASSETS TO DEPRECIATE
A46: Apartment/office fixings | B46: Years | C46: 10
A47: Office furniture | B47: Years | C47: 5
A48: Computers | B48: Years | C48: 3
A49: Telecom equipment | B49: Years | C49: 5
A50: Servers & other tech infrastructure | B50: Years | C50: 5
A51: Other | B51: Years | C51: 5

Sheet Team & Salaries
A1: Salaries | B1: Expense Category | C1: Currency | D1: Monthly Cost to Company | E1: Monthly Salary | F1: Year 2 | G1: Year 3 | H1: Year 4 | I1: Year 5 | J1: Year 6 | K1: Annual Salary | L1: Payroll Taxes + Benefits | M1: First Hire | N1: How many hires added per period? | O1: How often are new hires added? | P1: Maximum Team | Q1: Annual Increase | R1: Notes
A2: If you need additional roles, just unhide rows. | N2: Set to 0 if you would like to disable the position
A5: Operations
A6: CEO | B6: Ops | C6: USD | D6: =E6*(1+L6) -> 2291.6667 | E6: =K6/12 -> 2083.3333 | F6: =D6*(1+$Q6) -> 2360.4167 | G6: =F6*(1+$Q6) -> 2431.2292 | H6: =G6*(1+$Q6) -> 2504.166 | I6: =H6*(1+$Q6) -> 2579.291 | J6: =I6*(1+$Q6) -> 2656.6698 | K6: 25000 | L6: 0.1 | M6: 43466 | N6: =IF(M6>0,1,0) -> 1 | O6: Never | P6: 1 | Q6: 0.03
A7: UX Research | B7: Ops | C7: USD | D7: =E7*(1+L7) -> 2291.6667 | E7: =K7/12 -> 2083.3333 | F7: =D7*(1+$Q7) -> 2360.4167 | G7: =F7*(1+$Q7) -> 2431.2292 | H7: =G7*(1+$Q7) -> 2504.166 | I7: =H7*(1+$Q7) -> 2579.291 | J7: =I7*(1+$Q7) -> 2656.6698 | K7: 25000 | L7: 0.1 | M7: 43466 | N7: =IF(M7>0,1,0) -> 1 | O7: Never | P7: 1 | Q7: 0.03
A8: CFO | B8: Ops | C8: USD | D8: =E8*(1+L8) -> 2291.6667 | E8: =K8/12 -> 2083.3333 | F8: =D8*(1+$Q8) -> 2360.4167 | G8: =F8*(1+$Q8) -> 2431.2292 | H8: =G8*(1+$Q8) -> 2504.166 | I8: =H8*(1+$Q8) -> 2579.291 | J8: =I8*(1+$Q8) -> 2656.6698 | K8: 25000 | L8: 0.1 | M8: 44197 | N8: =IF(M8>0,1,0) -> 1 | O8: Never | P8: 1 | Q8: 0.03
A9: Intern | B9: Ops | C9: USD | D9: =E9*(1+L9) -> 2291.6667 | E9: =K9/12 -> 2083.3333 | F9: =D9*(1+$Q9) -> 2360.4167 | G9: =F9*(1+$Q9) -> 2431.2292 | H9: =G9*(1+$Q9) -> 2504.166 | I9: =H9*(1+$Q9) -> 2579.291 | J9: =I9*(1+$Q9) -> 2656.6698 | K9: 25000 | L9: 0.1 | M9: 44197 | N9: =IF(M9>0,1,0) -> 1 | O9: Never | P9: 1 | Q9: 0.03
A10: CEO 2 | B10: Ops | C10: USD | D10: =E10*(1+L10) -> 4583.3333 | E10: =K10/12 -> 4166.6667 | F10: =D10*(1+$Q10) -> 4812.5 | G10: =F10*(1+$Q10) -> 5053.125 | H10: =G10*(1+$Q10) -> 5305.7813 | I10: =H10*(1+$Q10) -> 5571.0703 | J10: =I10*(1+$Q10) -> 5849.6238 | K10: 50000 | L10: 0.1 | M10: 44562 | N10: =IF(M10>0,1,0) -> 1 | O10: Never | P10: 1 | Q10: 0.05
A11: CFO 2 | B11: Ops | C11: USD | D11: =E11*(1+L11) -> 4583.3333 | E11: =K11/12 -> 4166.6667 | F11: =D11*(1+$Q11) -> 4812.5 | G11: =F11*(1+$Q11) -> 5053.125 | H11: =G11*(1+$Q11) -> 5305.7813 | I11: =H11*(1+$Q11) -> 5571.0703 | J11: =I11*(1+$Q11) -> 5849.6238 | K11: 50000 | L11: 0.1 | M11: 44562 | N11: =IF(M11>0,1,0) -> 1 | O11: Never | P11: 1 | Q11: 0.05
A12: CTO 2 | B12: Ops | C12: USD | D12: =E12*(1+L12) -> 4583.3333 | E12: =K12/12 -> 4166.6667 | F12: =D12*(1+$Q12) -> 4812.5 | G12: =F12*(1+$Q12) -> 5053.125 | H12: =G12*(1+$Q12) -> 5305.7813 | I12: =H12*(1+$Q12) -> 5571.0703 | J12: =I12*(1+$Q12) -> 5849.6238 | K12: 50000 | L12: 0.1 | M12: 44562 | N12: =IF(M12>0,1,0) -> 1 | O12: Never | P12: 1 | Q12: 0.05
A13: CMO 2 | B13: Ops | C13: USD | D13: =E13*(1+L13) -> 4583.3333 | E13: =K13/12 -> 4166.6667 | F13: =D13*(1+$Q13) -> 4812.5 | G13: =F13*(1+$Q13) -> 5053.125 | H13: =G13*(1+$Q13) -> 5305.7813 | I13: =H13*(1+$Q13) -> 5571.0703 | J13: =I13*(1+$Q13) -> 5849.6238 | K13: 50000 | L13: 0.1 | M13: 44562 | N13: =IF(M13>0,1,0) -> 1 | O13: Never | P13: 1 | Q13: 0.05
Q14: 0.03
Q15: 0.03
A16: Product | Q16: 0.03
A17: CTO | B17: Prod | C17: USD | D17: =E17*(1+L17) -> 2291.6667 | E17: =K17/12 -> 2083.3333 | F17: =D17*(1+$Q17) -> 2360.4167 | G17: =F17*(1+$Q17) -> 2431.2292 | H17: =G17*(1+$Q17) -> 2504.166 | I17: =H17*(1+$Q17) -> 2579.291 | J17: =I17*(1+$Q17) -> 2656.6698 | K17: 25000 | L17: 0.1 | M17: 43466 | N17: =IF(M17>0,1,0) -> 1 | O17: Never | P17: =IF(N17=1,1,0) -> 1 | Q17: 0.03
A18: 3D Design | B18: Prod | C18: USD | D18: =E18*(1+L18) -> 2291.6667 | E18: =K18/12 -> 2083.3333 | F18: =D18*(1+$Q18) -> 2360.4167 | G18: =F18*(1+$Q18) -> 2431.2292 | H18: =G18*(1+$Q18) -> 2504.166 | I18: =H18*(1+$Q18) -> 2579.291 | J18: =I18*(1+$Q18) -> 2656.6698 | K18: 25000 | L18: 0.1 | M18: 43647 | N18: =IF(M18>0,1,0) -> 1 | O18: Never | P18: =IF(N18=1,1,0) -> 1 | Q18: 0.03
A19: 3D Design | B19: Prod | C19: USD | D19: =E19*(1+L19) -> 2291.6667 | E19: =K19/12 -> 2083.3333 | F19: =D19*(1+$Q19) -> 2360.4167 | G19: =F19*(1+$Q19) -> 2431.2292 | H19: =G19*(1+$Q19) -> 2504.166 | I19: =H19*(1+$Q19) -> 2579.291 | J19: =I19*(1+$Q19) -> 2656.6698 | K19: 25000 | L19: 0.1 | M19: 44378 | N19: =IF(M19>0,1,0) -> 1 | O19: Never | P19: 1 | Q19: 0.03
A20: 3D Design | B20: Prod | C20: USD | D20: =E20*(1+L20) -> 2291.6667 | E20: =K20/12 -> 2083.3333 | F20: =D20*(1+$Q20) -> 2360.4167 | G20: =F20*(1+$Q20) -> 2431.2292 | H20: =G20*(1+$Q20) -> 2504.166 | I20: =H20*(1+$Q20) -> 2579.291 | J20: =I20*(1+$Q20) -> 2656.6698 | K20: 25000 | L20: 0.1 | M20: 44378 | N20: =IF(M20>0,1,0) -> 1 | O20: Never | P20: 1 | Q20: 0.03
A21: 3D Design | B21: Prod | C21: USD | D21: =E21*(1+L21) -> 6875 | E21: =K21/12 -> 6250 | F21: =D21*(1+$Q21) -> 7081.25 | G21: =F21*(1+$Q21) -> 7293.6875 | H21: =G21*(1+$Q21) -> 7512.4981 | I21: =H21*(1+$Q21) -> 7737.8731 | J21: =I21*(1+$Q21) -> 7970.0093 | K21: 75000 | L21: 0.1 | M21: 45292 | N21: =IF(M21>0,1,0) -> 1 | O21: Never | P21: 1 | Q21: 0.03
A22: 3D Design | B22: Prod | C22: USD | D22: =E22*(1+L22) -> 6875 | E22: =K22/12 -> 6250 | F22: =D22*(1+$Q22) -> 7081.25 | G22: =F22*(1+$Q22) -> 7293.6875 | H22: =G22*(1+$Q22) -> 7512.4981 | I22: =H22*(1+$Q22) -> 7737.8731 | J22: =I22*(1+$Q22) -> 7970.0093 | K22: 75000 | L22: 0.1 | M22: 45292 | N22: =IF(M22>0,1,0) -> 1 | O22: Never | P22: 1 | Q22: 0.03
A23: Mobile Dev | B23: Prod | C23: USD | D23: =E23*(1+L23) -> 6875 | E23: =K23/12 -> 6250 | F23: =D23*(1+$Q23) -> 7081.25 | G23: =F23*(1+$Q23) -> 7293.6875 | H23: =G23*(1+$Q23) -> 7512.4981 | I23: =H23*(1+$Q23) -> 7737.8731 | J23: =I23*(1+$Q23) -> 7970.0093 | K23: 75000 | L23: 0.1 | M23: 44927 | N23: =IF(M23>0,1,0) -> 1 | O23: Never | P23: 1 | Q23: 0.03
A24: Mobile Dev | B24: Prod | C24: USD | D24: =E24*(1+L24) -> 2291.6667 | E24: =K24/12 -> 2083.3333 | F24: =D24*(1+$Q24) -> 2360.4167 | G24: =F24*(1+$Q24) -> 2431.2292 | H24: =G24*(1+$Q24) -> 2504.166 | I24: =H24*(1+$Q24) -> 2579.291 | J24: =I24*(1+$Q24) -> 2656.6698 | K24: 25000 | L24: 0.1 | M24: 43556 | N24: =IF(M24>0,1,0) -> 1 | O24: Never | P24: 1 | Q24: 0.03
A25: Mobile Dev | B25: Prod | C25: USD | D25: =E25*(1+L25) -> 2291.6667 | E25: =K25/12 -> 2083.3333 | F25: =D25*(1+$Q25) -> 2360.4167 | G25: =F25*(1+$Q25) -> 2431.2292 | H25: =G25*(1+$Q25) -> 2504.166 | I25: =H25*(1+$Q25) -> 2579.291 | J25: =I25*(1+$Q25) -> 2656.6698 | K25: 25000 | L25: 0.1 | M25: 43556 | N25: =IF(M25>0,1,0) -> 1 | O25: Never | P25: 1 | Q25: 0.03
A26: Mobile Dev | B26: Prod | C26: USD | D26: =E26*(1+L26) -> 2291.6667 | E26: =K26/12 -> 2083.3333 | F26: =D26*(1+$Q26) -> 2360.4167 | G26: =F26*(1+$Q26) -> 2431.2292 | H26: =G26*(1+$Q26) -> 2504.166 | I26: =H26*(1+$Q26) -> 2579.291 | J26: =I26*(1+$Q26) -> 2656.6698 | K26: 25000 | L26: 0.1 | M26: 44378 | N26: =IF(M26>0,1,0) -> 1 | O26: Never | P26: 1 | Q26: 0.03
A27: Mobile Dev | B27: Prod | C27: USD | D27: =E27*(1+L27) -> 2291.6667 | E27: =K27/12 -> 2083.3333 | F27: =D27*(1+$Q27) -> 2360.4167 | G27: =F27*(1+$Q27) -> 2431.2292 | H27: =G27*(1+$Q27) -> 2504.166 | I27: =H27*(1+$Q27) -> 2579.291 | J27: =I27*(1+$Q27) -> 2656.6698 | K27: 25000 | L27: 0.1 | M27: 44378 | N27: =IF(M27>0,1,0) -> 1 | O27: Never | P27: 1 | Q27: 0.03
A28: Mobile Dev | B28: Prod | C28: USD | D28: =E28*(1+L28) -> 2291.6667 | E28: =K28/12 -> 2083.3333 | F28: =D28*(1+$Q28) -> 2360.4167 | G28: =F28*(1+$Q28) -> 2431.2292 | H28: =G28*(1+$Q28) -> 2504.166 | I28: =H28*(1+$Q28) -> 2579.291 | J28: =I28*(1+$Q28) -> 2656.6698 | K28: 25000 | L28: 0.1 | M28: 44378 | N28: =IF(M28>0,1,0) -> 1 | O28: Never | P28: 1 | Q28: 0.03
A29: Mobile Dev | B29: Prod | C29: USD | D29: =E29*(1+L29) -> 6875 | E29: =K29/12 -> 6250 | F29: =D29*(1+$Q29) -> 7081.25 | G29: =F29*(1+$Q29) -> 7293.6875 | H29: =G29*(1+$Q29) -> 7512.4981 | I29: =H29*(1+$Q29) -> 7737.8731 | J29: =I29*(1+$Q29) -> 7970.0093 | K29: 75000 | L29: 0.1 | M29: 45108 | N29: =IF(M29>0,1,0) -> 1 | O29: Never | P29: 1 | Q29: 0.03
A30: Scrum Master | B30: Prod | C30: USD | D30: =E30*(1+L30) -> 4583.3333 | E30: =K30/12 -> 4166.6667 | F30: =D30*(1+$Q30) -> 4720.8333 | G30: =F30*(1+$Q30) -> 4862.4583 | H30: =G30*(1+$Q30) -> 5008.3321 | I30: =H30*(1+$Q30) -> 5158.582 | J30: =I30*(1+$Q30) -> 5313.3395 | K30: 50000 | L30: 0.1 | M30: 45658 | N30: =IF(M30>0,1,0) -> 1 | O30: Never | P30: 1 | Q30: 0.03
... A42: VR Dev 4 | B42: Prod | C42: USD | D42: =E42*(1+L42) -> 5500 | E42: =K42/12 -> 5000 | F42: =D42*(1+$Q42) -> 5665 | G42: =F42*(1+$Q42) -> 5834.95 | H42: =G42*(1+$Q42) -> 6009.9985 | I42: =H42*(1+$Q42) -> 6190.2985 | J42: =I42*(1+$Q42) -> 6376.0074 | K42: 60000 | L42: 0.1 | M42: 44835 | N42: =IF(M42>0,1,0) -> 1 | O42: Never | P42: 1 | Q42: 0.03
Q43: 0.03
Q44: 0.03
A45: Marketing & Sales | Q45: 0.03
A46: CMO | B46: Growth | C46: USD | D46: =E46*(1+L46) -> 2291.6667 | E46: =K46/12 -> 2083.3333 | F46: =D46*(1+$Q46) -> 2360.4167 | G46: =F46*(1+$Q46) -> 2431.2292 | H46: =G46*(1+$Q46) -> 2504.166 | I46: =H46*(1+$Q46) -> 2579.291 | J46: =I46*(1+$Q46) -> 2656.6698 | K46: 25000 | L46: 0.1 | M46: 44197 | N46: =IF(M46>0,1,0) -> 1 | O46: Never | P46: 1 | Q46: 0.03
A47: Digital Marketer | B47: Growth | C47: USD | D47: =E47*(1+L47) -> 2291.6667 | E47: =K47/12 -> 2083.3333 | F47: =D47*(1+$Q47) -> 2360.4167 | G47: =F47*(1+$Q47) -> 2431.2292 | H47: =G47*(1+$Q47) -> 2504.166 | I47: =H47*(1+$Q47) -> 2579.291 | J47: =I47*(1+$Q47) -> 2656.6698 | K47: 25000 | L47: 0.1 | M47: 44197 | N47: =IF(M47>0,1,0) -> 1 | O47: Never | P47: 1 | Q47: 0.03
A48: Digital Marketer | B48: Growth | C48: USD | D48: =E48*(1+L48) -> 2291.6667 | E48: =K48/12 -> 2083.3333 | F48: =D48*(1+$Q48) -> 2360.4167 | G48: =F48*(1+$Q48) -> 2431.2292 | H48: =G48*(1+$Q48) -> 2504.166 | I48: =H48*(1+$Q48) -> 2579.291 | J48: =I48*(1+$Q48) -> 2656.6698 | K48: 25000 | L48: 0.1 | M48: 44197 | N48: =IF(M48>0,1,0) -> 1 | O48: Never | P48: =IF(N48=1,1,0) -> 1 | Q48: 0.03
A49: Digital Marketer | B49: Growth | C49: USD | D49: =E49*(1+L49) -> 2291.6667 | E49: =K49/12 -> 2083.3333 | F49: =D49*(1+$Q49) -> 2360.4167 | G49: =F49*(1+$Q49) -> 2431.2292 | H49: =G49*(1+$Q49) -> 2504.166 | I49: =H49*(1+$Q49) -> 2579.291 | J49: =I49*(1+$Q49) -> 2656.6698 | K49: 25000 | L49: 0.1 | M49: 44197 | N49: =IF(M49>0,1,0) -> 1 | O49: Never | P49: =IF(N49=1,1,0) -> 1 | Q49: 0.03
A50: Digital Marketer | B50: Growth | C50: USD | D50: =E50*(1+L50) -> 3208.3333 | E50: =K50/12 -> 2916.6667 | F50: =D50*(1+$Q50) -> 3304.5833 | G50: =F50*(1+$Q50) -> 3403.7208 | H50: =G50*(1+$Q50) -> 3505.8325 | I50: =H50*(1+$Q50) -> 3611.0074 | J50: =I50*(1+$Q50) -> 3719.3377 | K50: 35000 | L50: 0.1 | M50: 45292 | N50: =IF(M50>0,1,0) -> 1 | O50: Never | P50: =IF(N50=1,1,0) -> 1 | Q50: 0.03
A51: Sales & Maketing | B51: Growth | C51: USD | D51: =E51*(1+L51) -> 3208.3333 | E51: =K51/12 -> 2916.6667 | F51: =D51*(1+$Q51) -> 3304.5833 | G51: =F51*(1+$Q51) -> 3403.7208 | H51: =G51*(1+$Q51) -> 3505.8325 | I51: =H51*(1+$Q51) -> 3611.0074 | J51: =I51*(1+$Q51) -> 3719.3377 | K51: 35000 | L51: 0.1 | M51: 44562 | N51: =IF(M51>0,1,0) -> 1 | O51: Never | P51: =IF(N51=1,1,0) -> 1 | Q51: 0.03
A52: Sales & Maketing | B52: Growth | C52: USD | D52: =E52*(1+L52) -> 3208.3333 | E52: =K52/12 -> 2916.6667 | F52: =D52*(1+$Q52) -> 3304.5833 | G52: =F52*(1+$Q52) -> 3403.7208 | H52: =G52*(1+$Q52) -> 3505.8325 | I52: =H52*(1+$Q52) -> 3611.0074 | J52: =I52*(1+$Q52) -> 3719.3377 | K52: 35000 | L52: 0.1 | M52: 44562 | N52: =IF(M52>0,1,0) -> 1 | O52: Never | P52: =IF(N52=1,1,0) -> 1 | Q52: 0.03
A53: Sales & Maketing | B53: Growth | C53: USD | D53: =E53*(1+L53) -> 3208.3333 | E53: =K53/12 -> 2916.6667 | F53: =D53*(1+$Q53) -> 3304.5833 | G53: =F53*(1+$Q53) -> 3403.7208 | H53: =G53*(1+$Q53) -> 3505.8325 | I53: =H53*(1+$Q53) -> 3611.0074 | J53: =I53*(1+$Q53) -> 3719.3377 | K53: 35000 | L53: 0.1 | M53: 44927 | N53: =IF(M53>0,1,0) -> 1 | O53: Never | P53: =IF(N53=1,1,0) -> 1 | Q53: 0.03
A54: Sales & Maketing | B54: Growth | C54: USD | D54: =E54*(1+L54) -> 3208.3333 | E54: =K54/12 -> 2916.6667 | F54: =D54*(1+$Q54) -> 3304.5833 | G54: =F54*(1+$Q54) -> 3403.7208 | H54: =G54*(1+$Q54) -> 3505.8325 | I54: =H54*(1+$Q54) -> 3611.0074 | J54: =I54*(1+$Q54) -> 3719.3377 | K54: 35000 | L54: 0.1 | M54: 44927 | N54: =IF(M54>0,1,0) -> 1 | O54: Never | P54: =IF(N54=1,1,0) -> 1 | Q54: 0.03
A55: Sales & Maketing | B55: Growth | C55: USD | D55: =E55*(1+L55) -> 3208.3333 | E55: =K55/12 -> 2916.6667 | F55: =D55*(1+$Q55) -> 3304.5833 | G55: =F55*(1+$Q55) -> 3403.7208 | H55: =G55*(1+$Q55) -> 3505.8325 | I55: =H55*(1+$Q55) -> 3611.0074 | J55: =I55*(1+$Q55) -> 3719.3377 | K55: 35000 | L55: 0.1 | M55: 45292 | N55: =IF(M55>0,1,0) -> 1 | O55: Never | P55: =IF(N55=1,1,0) -> 1 | Q55: 0.03
Q56: 0.03
Q57: 0.03
A58: Customer Support | Q58: 0.03
A59: Head of Customer | B59: Ops | C59: USD | D59: =E59*(1+L59) -> 2291.6667 | E59: =K59/12 -> 2083.3333 | F59: =D59*(1+$Q59) -> 2360.4167 | G59: =F59*(1+$Q59) -> 2431.2292 | H59: =G59*(1+$Q59) -> 2504.166 | I59: =H59*(1+$Q59) -> 2579.291 | J59: =I59*(1+$Q59) -> 2656.6698 | K59: 25000 | L59: 0.1 | M59: 44197 | N59: =IF(M59>0,1,0) -> 1 | O59: Never | P59: 1 | Q59: 0.03
A60: Senior Customer Support | B60: Ops | C60: USD | D60: =E60*(1+L60) -> 2291.6667 | E60: =K60/12 -> 2083.3333 | F60: =D60*(1+$Q60) -> 2360.4167 | G60: =F60*(1+$Q60) -> 2431.2292 | H60: =G60*(1+$Q60) -> 2504.166 | I60: =H60*(1+$Q60) -> 2579.291 | J60: =I60*(1+$Q60) -> 2656.6698 | K60: 25000 | L60: 0.1 | M60: 44197 | N60: =IF(M60>0,1,0) -> 1 | O60: Never | P60: =IF(N60=1,1,0) -> 1 | Q60: 0.03
A61: Junior Customer Support | B61: Ops | C61: USD | D61: =E61*(1+L61) -> 2291.6667 | E61: =K61/12 -> 2083.3333 | F61: =D61*(1+$Q61) -> 2360.4167 | G61: =F61*(1+$Q61) -> 2431.2292 | H61: =G61*(1+$Q61) -> 2504.166 | I61: =H61*(1+$Q61) -> 2579.291 | J61: =I61*(1+$Q61) -> 2656.6698 | K61: 25000 | L61: 0.1 | M61: 44197 | N61: =IF(M61>0,1,0) -> 1 | O61: Never | P61: =IF(N61=1,1,0) -> 1 | Q61: 0.03
A62: Customer Rep 1 | B62: Ops | C62: USD | D62: =E62*(1+L62) -> 2291.6667 | E62: =K62/12 -> 2083.3333 | F62: =D62*(1+$Q62) -> 2360.4167 | G62: =F62*(1+$Q62) -> 2431.2292 | H62: =G62*(1+$Q62) -> 2504.166 | I62: =H62*(1+$Q62) -> 2579.291 | J62: =I62*(1+$Q62) -> 2656.6698 | K62: 25000 | L62: 0.1 | M62: 44562 | N62: =IF(M62>0,1,0) -> 1 | O62: Never | P62: =IF(N62=1,1,0) -> 1 | Q62: 0.03
A63: Customer Rep 2 | B63: Ops | C63: USD | D63: =E63*(1+L63) -> 2750 | E63: =K63/12 -> 2500 | F63: =D63*(1+$Q63) -> 2832.5 | G63: =F63*(1+$Q63) -> 2917.475 | H63: =G63*(1+$Q63) -> 3004.9992 | I63: =H63*(1+$Q63) -> 3095.1492 | J63: =I63*(1+$Q63) -> 3188.0037 | K63: 30000 | L63: 0.1 | M63: 45108 | N63: =IF(M63>0,1,0) -> 1 | O63: Never | P63: =IF(N63=1,1,0) -> 1 | Q63: 0.03
A64: Customer Rep 3 | B64: Ops | C64: USD | D64: =E64*(1+L64) -> 2750 | E64: =K64/12 -> 2500 | F64: =D64*(1+$Q64) -> 2832.5 | G64: =F64*(1+$Q64) -> 2917.475 | H64: =G64*(1+$Q64) -> 3004.9992 | I64: =H64*(1+$Q64) -> 3095.1492 | J64: =I64*(1+$Q64) -> 3188.0037 | K64: 30000 | L64: 0.1 | M64: 45658 | N64: =IF(M64>0,1,0) -> 1 | O64: Never | P64: =IF(N64=1,1,0) -> 1 | Q64: 0.03
A65: Other 4 | B65: Ops | C65: USD | D65: =E65*(1+L65) -> 2750 | E65: =K65/12 -> 2500 | F65: =D65*(1+$Q65) -> 2832.5 | G65: =F65*(1+$Q65) -> 2917.475 | H65: =G65*(1+$Q65) -> 3004.9992 | I65: =H65*(1+$Q65) -> 3095.1492 | J65: =I65*(1+$Q65) -> 3188.0037 | K65: 30000 | L65: 0.1 | M65: 45658 | N65: =IF(M65>0,1,0) -> 1 | O65: Never | P65: =IF(N65=1,1,0) -> 1 | Q65: 0.03
A66: Other 5 | B66: Ops | C66: USD | D66: =E66*(1+L66) -> 2750 | E66: =K66/12 -> 2500 | F66: =D66*(1+$Q66) -> 2832.5 | G66: =F66*(1+$Q66) -> 2917.475 | H66: =G66*(1+$Q66) -> 3004.9992 | I66: =H66*(1+$Q66) -> 3095.1492 | J66: =I66*(1+$Q66) -> 3188.0037 | K66: 30000 | L66: 0.1 | M66: 45658 | N66: =IF(M66>0,1,0) -> 1 | O66: Never | P66: =IF(N66=1,1,0) -> 1 | Q66: 0.03

Sheet Projections
A1: Item | B1: Format | C1: Input | D1: Scenario A | E1: Scenario B | F1: Scenario C | G1: Notes
A2: General Settings
A4: Fundraising Close Date | B4: Date | C4: 43739 | D4: 44197 | E4: 44197 | F4: 44197
A5: Investment Amount | B5: =Settings!$C$6 -> USD | C5: 100000 | D5: 0 | E5: 0 | F5: 0
A10: REVENUE
A12: Organic Website Traffic
A13: Use this section to estimate the success of your SEO, Brand Awareness and customer referral efforts. Your total estimated traffic will be visible on the KPI section of the Revenue Sheet.
A14: Organic traffic is disonnected from the budget: that means that you can project organic traffic regardless of how much you are spending. Still, it is recommended to use realistic expectations.
A16: Brand Awareness Budget
A17: Starting Budget | B17: =Settings!$C$6 -> USD | C17: 0 | G17: Expenses automatically added to the SG&A Sheet
A18: Monthly Marketing Budget Increase | B18: =Settings!$C$6 -> USD | C18: 0 | G18: Expenses automatically added to the SG&A Sheet
A19: Maximum Marketing Budget | B19: =Settings!$C$6 -> USD | C19: 0 | G19: Expenses automatically added to the SG&A Sheet
A21: Website Traffic
A22: Organic Traffic Efforts Kick-Off | B22: Date | C22: 44287 | D22: 44197 | E22: 44197 | F22: 44197
A23: Website Traffic at launch | B23: # | C23: 0
A24: Monthly Traffic Increase | B24: % | C24: 0
A25: Maximum Possible Organic Website Traffic | B25: # | C25: 0
A30: SOURCE #1: Self-Service Subscriptions | C30: Enabled
A31: Enable this section if you expect to close deals without a sales team. Your customers go to your website and convert without any sales efforts required.
A32: Customers convert directly from organic or paid traffic, into paid accounts.
A34: Business Model
A35: Expected Launch | B35: Date | C35: 44287 | D35: 44197 | E35: 44197 | F35: 44197
A36: ARPU | B36: =Settings!$C$6 -> USD | C36: 276 | G36: The average account revenue per account, per month. If you have multiple plans, provide an average of the plan price.
A37: How will you primarily bill your customers | B37: =Settings!$C$6 -> USD | C37: Yearly
A38: ="Expected "&C37&" Churn Rate" -> Expected Yearly Churn Rate | B38: % | C38: 0.7 | G38: Most B2C companies try to stay near 5% monthly churn. Most B2B companies aim for 0-2% monthly churn
A39: Expected Lifetime Value | B39: =Settings!$C$6 -> USD | C39: =IF(C37="Monthly",C36/C38,C36/(C38/12)) -> 4731.4286
A41: Organic Traffic
A42: Organic Traffic Conversion to Paid | B42: % | C42: 0.01
A44: Paid Traffic | G44: Use this section to estimate the success of your paid ads (Google Ads, Facebook, etc...)
A45: Paid Traffic Marketing Budget
A46: Starting Marketing Budget | B46: =Settings!$C$6 -> USD | C46: 0 | G46: Expenses automatically added to the SG&A Sheet
A47: Monthly Marketing Budget Increase | B47: =Settings!$C$6 -> USD | C47: 0 | G47: Expenses automatically added to the SG&A Sheet
A48: Maximum Paid Ads Marketing Budget | B48: =Settings!$C$6 -> USD | C48: 0 | G48: Expenses automatically added to the SG&A Sheet
A50: Cost of acqusition
A51: Expected CAC, first month | B51: =Settings!$C$6 -> USD | C51: 15 | G51: Cost of acquisition per account
A52: Monthly CAC change | B52: =Settings!$C$6 -> USD | C52: -2 | G52: Use positive numbers if you assume your CAC will go up. Use negative numbers if you expect it to go down. Most SaaS companies see this number increase as they scale.
A53: Minimum CAC possible | B53: =Settings!$C$6 -> USD | C53: 30 | G53: The minimum possible CAC you expect
A60: SOURCE #2: Inbound Sales | C60: Disabled
A61: Enable this section if you expect to close deals using lead generation, lead nurturing and a team to close sales.
A62: Traffic converts to leads, which are then handled by your sales team.
A64: Business Model
A65: Expected Launch | B65: Date | D65: 44197 | E65: 44197 | F65: 44197
A66: ARPU | B66: =Settings!$C$6 -> USD | G66: The average account revenue per account, per month. If you have multiple plans, provide an average of the plan price.
A67: How will you primarily bill your customers | B67: =Settings!$C$6 -> USD
A68: ="Expected "&C67&" Churn Rate" -> Expected Churn Rate | B68: % | G68: Most B2B companies aim for 0-2% monthly churn
A69: Expected Lifetime Value | B69: =Settings!$C$6 -> USD | C69: =IF(C67="Monthly",C66/C68,C66/(C68/12)) -> #DIV/0!
A71: Organic Traffic
A72: Organic Traffic Conversion to Lead | B72: %
A74: Paid Traffic
A75: Paid Traffic Marketing Budget
A76: Starting Marketing Budget | B76: =Settings!$C$6 -> USD | G76: Expenses automatically added to the SG&A Sheet
A77: Monthly Marketing Budget Increase | B77: =Settings!$C$6 -> USD | G77: Expenses automatically added to the SG&A Sheet
A78: Maximum Paid Ads Marketing Budget | B78: =Settings!$C$6 -> USD | G78: Expenses automatically added to the SG&A Sheet
A80: Cost of acqusition per Lead
A81: Expected Lead cost, first month | B81: =Settings!$C$6 -> USD | G81: Cost of acquisition per lead
A82: Monthly Lead cost change | B82: =Settings!$C$6 -> USD | G82: Use positive numbers if you assume your CAC will go up. Use negative numbers if you expect it to go down.
A83: Minimum Lead cost possible | B83: =Settings!$C$6 -> USD | G83: The minimum possible CAC you expect
A85: Agents & Lead Nurturing
A86: Leads a single sales agent can handle per month | B86: #
A87: Position in charge of lead handling and conversion | B87: dropdown | C87: Inbound Sales Agent
A89: Conversions
A90: Lead to sale conversion rate | B90: %
A101: SOURCE #3: Outbound Sales | C101: Disabled
A102: Enable this section if you expect to close deals using with sales representatives handling the outreach, nurturing and deal closing.
A104: Business Model
A105: Expected Launch | B105: Date
A106: ARPU | B106: =Settings!$C$6 -> USD | G106: The average account revenue per account, per month. If you have multiple plans, provide an average of the plan price.
A107: How will you primarily bill your customers | B107: =Settings!$C$6 -> USD
A108: ="Expected "&C107&" Churn Rate" -> Expected Churn Rate | B108: % | G108: Most B2B companies aim for 0-2% monthly churn
A109: Expected Lifetime Value | B109: =Settings!$C$6 -> USD | C109: =IF(C107="Monthly",C106/C108,C106/(C108/12)) -> #DIV/0!
A111: Outbound Reachout
A112: Position in Charge | C112: ='Team & Salaries'!A48 -> Digital Marketer
A113: New agents added per month | B113: # | C113: 0 | G113: ="Employees will be added to the '"&C$112&"' row on the SG&A sheet" -> Employees will be added to the 'Digital Marketer' row on the SG&A sheet
A114: Maximum Agents for Outbound Sales | B114: # | C114: 0 | G114: ="Employees will be added to the '"&C$112&"' row on the SG&A sheet" -> Employees will be added to the 'Digital Marketer' row on the SG&A sheet
A116: Deals closed per agent per month | B116: #
A117: Sales cycle expected time | B117: months
A121: SG&A
A123: Office > Per Desk Cost | B123: =Settings!$C$6 -> USD | C123: 0
A125: Tech Support/Customer Success
A126: Customers an agent can handle | B126: #
A127: Position in charge of support/success | B127: dropdown | C127: Junior Customer Support
A130: COGS
A134: CAPEX

Sheet Data for Charts
A1: =Settings!C5 -> VReeMind
A2: Data for Charts
A3: =+TODAY() -> 44143
D6: ='FS-Month'!D6 -> 43466 | E6: ='FS-Month'!E6 -> 43497 | F6: ='FS-Month'!F6 -> 43525 | G6: ='FS-Month'!G6 -> 43556 | H6: ='FS-Month'!H6 -> 43586 | I6: ='FS-Month'!I6 -> 43617 | J6: ='FS-Month'!J6 -> 43647 | K6: ='FS-Month'!K6 -> 43678 | ... BK6: ='FS-Month'!BK6 -> 45261 | BL6: ='FS-Month'!#REF! -> #REF! | BM6: ='FS-Month'!#REF! -> #REF! | BN6: ='FS-Month'!#REF! -> #REF! | BO6: ='FS-Month'!#REF! -> #REF! | BP6: ='FS-Month'!#REF! -> #REF! | BQ6: ='FS-Month'!#REF! -> #REF! | BR6: ='FS-Month'!#REF! -> #REF! | BS6: ='FS-Month'!#REF! -> #REF! | ... CI6: ='FS-Month'!#REF! -> #REF!
D7: ='FS-Month'!D7 -> 1 | E7: ='FS-Month'!E7 -> 2 | F7: ='FS-Month'!F7 -> 3 | G7: ='FS-Month'!G7 -> 4 | H7: ='FS-Month'!H7 -> 5 | I7: ='FS-Month'!I7 -> 6 | J7: ='FS-Month'!J7 -> 7 | K7: ='FS-Month'!K7 -> 8 | ... BK7: ='FS-Month'!BK7 -> 60 | BL7: ='FS-Month'!#REF! -> #REF! | BM7: ='FS-Month'!#REF! -> #REF! | BN7: ='FS-Month'!#REF! -> #REF! | BO7: ='FS-Month'!#REF! -> #REF! | BP7: ='FS-Month'!#REF! -> #REF! | BQ7: ='FS-Month'!#REF! -> #REF! | BR7: ='FS-Month'!#REF! -> #REF! | BS7: ='FS-Month'!#REF! -> #REF! | ... CI7: ='FS-Month'!#REF! -> #REF!
A11: P&L Bar Chart
A13: ='FS-Month'!A12 -> Revenue | D13: ='FS-Month'!D12 -> 0 | E13: ='FS-Month'!E12 -> 0 | F13: ='FS-Month'!F12 -> 0 | G13: ='FS-Month'!G12 -> 0 | H13: ='FS-Month'!H12 -> 0 | I13: ='FS-Month'!I12 -> 0 | J13: ='FS-Month'!J12 -> 0 | K13: ='FS-Month'!K12 -> 0 | ... BK13: ='FS-Month'!BK12 -> 915792.66 | BL13: ='FS-Month'!#REF! -> #REF! | BM13: ='FS-Month'!#REF! -> #REF! | BN13: ='FS-Month'!#REF! -> #REF! | BO13: ='FS-Month'!#REF! -> #REF! | BP13: ='FS-Month'!#REF! -> #REF! | BQ13: ='FS-Month'!#REF! -> #REF! | BR13: ='FS-Month'!#REF! -> #REF! | BS13: ='FS-Month'!#REF! -> #REF! | ... CI13: ='FS-Month'!#REF! -> #REF!
A14: ='FS-Month'!A18 -> COGS | D14: ='FS-Month'!D18*-1 -> 0 | E14: ='FS-Month'!E18*-1 -> 0 | F14: ='FS-Month'!F18*-1 -> 0 | G14: ='FS-Month'!G18*-1 -> 0 | H14: ='FS-Month'!H18*-1 -> 0 | I14: ='FS-Month'!I18*-1 -> 0 | J14: ='FS-Month'!J18*-1 -> 0 | K14: ='FS-Month'!K18*-1 -> 0 | ... BK14: ='FS-Month'!BK18*-1 -> -325382.93 | BL14: ='FS-Month'!#REF!*-1 -> #REF! | BM14: ='FS-Month'!#REF!*-1 -> #REF! | BN14: ='FS-Month'!#REF!*-1 -> #REF! | BO14: ='FS-Month'!#REF!*-1 -> #REF! | BP14: ='FS-Month'!#REF!*-1 -> #REF! | BQ14: ='FS-Month'!#REF!*-1 -> #REF! | BR14: ='FS-Month'!#REF!*-1 -> #REF! | BS14: ='FS-Month'!#REF!*-1 -> #REF! | ... CI14: ='FS-Month'!#REF!*-1 -> #REF!
A15: ='FS-Month'!A25 -> SG&A | D15: ='FS-Month'!D25*-1 -> -20458.333 | E15: ='FS-Month'!E25*-1 -> -6875 | F15: ='FS-Month'!F25*-1 -> -9875 | G15: ='FS-Month'!G25*-1 -> -21958.333 | H15: ='FS-Month'!H25*-1 -> -15958.333 | I15: ='FS-Month'!I25*-1 -> -16179.583 | J15: ='FS-Month'!J25*-1 -> -21500.5 | K15: ='FS-Month'!K25*-1 -> -18500.5 | ... BK15: ='FS-Month'!BK25*-1 -> -194521.06 | BL15: ='FS-Month'!#REF!*-1 -> #REF! | BM15: ='FS-Month'!#REF!*-1 -> #REF! | BN15: ='FS-Month'!#REF!*-1 -> #REF! | BO15: ='FS-Month'!#REF!*-1 -> #REF! | BP15: ='FS-Month'!#REF!*-1 -> #REF! | BQ15: ='FS-Month'!#REF!*-1 -> #REF! | BR15: ='FS-Month'!#REF!*-1 -> #REF! | BS15: ='FS-Month'!#REF!*-1 -> #REF! | ... CI15: ='FS-Month'!#REF!*-1 -> #REF!
A16: CAPEX | D16: ='FS-Month'!D86*-1 -> 0 | E16: ='FS-Month'!E86*-1 -> 0 | F16: ='FS-Month'!F86*-1 -> 0 | G16: ='FS-Month'!G86*-1 -> 0 | H16: ='FS-Month'!H86*-1 -> 0 | I16: ='FS-Month'!I86*-1 -> 0 | J16: ='FS-Month'!J86*-1 -> 0 | K16: ='FS-Month'!K86*-1 -> 0 | ... BK16: ='FS-Month'!BK86*-1 -> 0 | BL16: ='FS-Month'!#REF!*-1 -> #REF! | BM16: ='FS-Month'!#REF!*-1 -> #REF! | BN16: ='FS-Month'!#REF!*-1 -> #REF! | BO16: ='FS-Month'!#REF!*-1 -> #REF! | BP16: ='FS-Month'!#REF!*-1 -> #REF! | BQ16: ='FS-Month'!#REF!*-1 -> #REF! | BR16: ='FS-Month'!#REF!*-1 -> #REF! | BS16: ='FS-Month'!#REF!*-1 -> #REF! | ... CI16: ='FS-Month'!#REF!*-1 -> #REF!
A19: Cash in the Bank
A20: Cash in the Bank | D20: ='FS-Month'!D89 -> 79541.667 | E20: ='FS-Month'!E89 -> 72666.667 | F20: ='FS-Month'!F89 -> 62791.667 | G20: ='FS-Month'!G89 -> 40833.333 | H20: ='FS-Month'!H89 -> 24875 | I20: ='FS-Month'!I89 -> 8695.4167 | J20: ='FS-Month'!J89 -> 287194.92 | K20: ='FS-Month'!K89 -> 268694.42 | ... BK20: ='FS-Month'!BK89 -> 5813323.3 | BL20: ='FS-Month'!#REF! -> #REF! | BM20: ='FS-Month'!#REF! -> #REF! | BN20: ='FS-Month'!#REF! -> #REF! | BO20: ='FS-Month'!#REF! -> #REF! | BP20: ='FS-Month'!#REF! -> #REF! | BQ20: ='FS-Month'!#REF! -> #REF! | BR20: ='FS-Month'!#REF! -> #REF! | BS20: ='FS-Month'!#REF! -> #REF! | ... CI20: ='FS-Month'!#REF! -> #REF!
A24: Use of Funds - first 18 months
A26: SG&A
A27: Ops | D27: =SUMIF('SG&A'!$D:$D,$A27,'SG&A'!F:F) -> 18166.667 | E27: =SUMIF('SG&A'!$D:$D,$A27,'SG&A'!G:G) -> 4583.3333 | F27: =SUMIF('SG&A'!$D:$D,$A27,'SG&A'!H:H) -> 4583.3333 | G27: =SUMIF('SG&A'!$D:$D,$A27,'SG&A'!I:I) -> 12083.333 | H27: =SUMIF('SG&A'!$D:$D,$A27,'SG&A'!J:J) -> 6083.3333 | I27: =SUMIF('SG&A'!$D:$D,$A27,'SG&A'!K:K) -> 6304.5833 | J27: =SUMIF('SG&A'!$D:$D,$A27,'SG&A'!L:L) -> 9333.8333 | K27: =SUMIF('SG&A'!$D:$D,$A27,'SG&A'!M:M) -> 6333.8333 | L27: =SUMIF('SG&A'!$D:$D,$A27,'SG&A'!N:N) -> 6333.8333 | M27: =SUMIF('SG&A'!$D:$D,$A27,'SG&A'!O:O) -> 9363.0833 | N27: =SUMIF('SG&A'!$D:$D,$A27,'SG&A'!P:P) -> 6363.0833 | O27: =SUMIF('SG&A'!$D:$D,$A27,'SG&A'!Q:Q) -> 11863.083 | P27: =SUMIF('SG&A'!$D:$D,$A27,'SG&A'!R:R) -> 12421.583 | Q27: =SUMIF('SG&A'!$D:$D,$A27,'SG&A'!S:S) -> 18676.083 | R27: =SUMIF('SG&A'!$D:$D,$A27,'SG&A'!T:T) -> 6676.0833 | S27: =SUMIF('SG&A'!$D:$D,$A27,'SG&A'!U:U) -> 9705.3333 | T27: =SUMIF('SG&A'!$D:$D,$A27,'SG&A'!V:V) -> 6705.3333 | U27: =SUMIF('SG&A'!$D:$D,$A27,'SG&A'!W:W) -> 56705.333
A28: R&D | D28: =SUMIF('SG&A'!$D:$D,$A28,'SG&A'!F:F) -> 0 | E28: =SUMIF('SG&A'!$D:$D,$A28,'SG&A'!G:G) -> 0 | F28: =SUMIF('SG&A'!$D:$D,$A28,'SG&A'!H:H) -> 0 | G28: =SUMIF('SG&A'!$D:$D,$A28,'SG&A'!I:I) -> 0 | H28: =SUMIF('SG&A'!$D:$D,$A28,'SG&A'!J:J) -> 0 | I28: =SUMIF('SG&A'!$D:$D,$A28,'SG&A'!K:K) -> 0 | J28: =SUMIF('SG&A'!$D:$D,$A28,'SG&A'!L:L) -> 0 | K28: =SUMIF('SG&A'!$D:$D,$A28,'SG&A'!M:M) -> 0 | L28: =SUMIF('SG&A'!$D:$D,$A28,'SG&A'!N:N) -> 0 | M28: =SUMIF('SG&A'!$D:$D,$A28,'SG&A'!O:O) -> 0 | N28: =SUMIF('SG&A'!$D:$D,$A28,'SG&A'!P:P) -> 0 | O28: =SUMIF('SG&A'!$D:$D,$A28,'SG&A'!Q:Q) -> 0 | P28: =SUMIF('SG&A'!$D:$D,$A28,'SG&A'!R:R) -> 0 | Q28: =SUMIF('SG&A'!$D:$D,$A28,'SG&A'!S:S) -> 0 | R28: =SUMIF('SG&A'!$D:$D,$A28,'SG&A'!T:T) -> 0 | S28: =SUMIF('SG&A'!$D:$D,$A28,'SG&A'!U:U) -> 0 | T28: =SUMIF('SG&A'!$D:$D,$A28,'SG&A'!V:V) -> 0 | U28: =SUMIF('SG&A'!$D:$D,$A28,'SG&A'!W:W) -> 0
A29: Growth | D29: =SUMIF('SG&A'!$D:$D,$A29,'SG&A'!F:F) -> 0 | E29: =SUMIF('SG&A'!$D:$D,$A29,'SG&A'!G:G) -> 0 | F29: =SUMIF('SG&A'!$D:$D,$A29,'SG&A'!H:H) -> 3000 | G29: =SUMIF('SG&A'!$D:$D,$A29,'SG&A'!I:I) -> 3000 | H29: =SUMIF('SG&A'!$D:$D,$A29,'SG&A'!J:J) -> 3000 | I29: =SUMIF('SG&A'!$D:$D,$A29,'SG&A'!K:K) -> 3000 | J29: =SUMIF('SG&A'!$D:$D,$A29,'SG&A'!L:L) -> 3000 | K29: =SUMIF('SG&A'!$D:$D,$A29,'SG&A'!M:M) -> 3000 | L29: =SUMIF('SG&A'!$D:$D,$A29,'SG&A'!N:N) -> 3000 | M29: =SUMIF('SG&A'!$D:$D,$A29,'SG&A'!O:O) -> 3000 | N29: =SUMIF('SG&A'!$D:$D,$A29,'SG&A'!P:P) -> 3000 | O29: =SUMIF('SG&A'!$D:$D,$A29,'SG&A'!Q:Q) -> 3000 | P29: =SUMIF('SG&A'!$D:$D,$A29,'SG&A'!R:R) -> 7500 | Q29: =SUMIF('SG&A'!$D:$D,$A29,'SG&A'!S:S) -> 7500 | R29: =SUMIF('SG&A'!$D:$D,$A29,'SG&A'!T:T) -> 7500 | S29: =SUMIF('SG&A'!$D:$D,$A29,'SG&A'!U:U) -> 7500 | T29: =SUMIF('SG&A'!$D:$D,$A29,'SG&A'!V:V) -> 7500 | U29: =SUMIF('SG&A'!$D:$D,$A29,'SG&A'!W:W) -> 7500
A31: COGS
A32: Ops | D32: =SUMIF(COGS!$C:$C,$A32,COGS!E:E) -> 0 | E32: =SUMIF(COGS!$C:$C,$A32,COGS!F:F) -> 0 | F32: =SUMIF(COGS!$C:$C,$A32,COGS!G:G) -> 0 | G32: =SUMIF(COGS!$C:$C,$A32,COGS!H:H) -> 0 | H32: =SUMIF(COGS!$C:$C,$A32,COGS!I:I) -> 0 | I32: =SUMIF(COGS!$C:$C,$A32,COGS!J:J) -> 0 | J32: =SUMIF(COGS!$C:$C,$A32,COGS!K:K) -> 0 | K32: =SUMIF(COGS!$C:$C,$A32,COGS!L:L) -> 0 | L32: =SUMIF(COGS!$C:$C,$A32,COGS!M:M) -> 0 | M32: =SUMIF(COGS!$C:$C,$A32,COGS!N:N) -> 0 | N32: =SUMIF(COGS!$C:$C,$A32,COGS!O:O) -> 0 | O32: =SUMIF(COGS!$C:$C,$A32,COGS!P:P) -> 0 | P32: =SUMIF(COGS!$C:$C,$A32,COGS!Q:Q) -> 0 | Q32: =SUMIF(COGS!$C:$C,$A32,COGS!R:R) -> 0 | R32: =SUMIF(COGS!$C:$C,$A32,COGS!S:S) -> 0 | S32: =SUMIF(COGS!$C:$C,$A32,COGS!T:T) -> 0 | T32: =SUMIF(COGS!$C:$C,$A32,COGS!U:U) -> 0 | U32: =SUMIF(COGS!$C:$C,$A32,COGS!V:V) -> 0
A33: R&D | D33: =SUMIF(COGS!$C:$C,$A33,COGS!E:E) -> 0 | E33: =SUMIF(COGS!$C:$C,$A33,COGS!F:F) -> 0 | F33: =SUMIF(COGS!$C:$C,$A33,COGS!G:G) -> 0 | G33: =SUMIF(COGS!$C:$C,$A33,COGS!H:H) -> 0 | H33: =SUMIF(COGS!$C:$C,$A33,COGS!I:I) -> 0 | I33: =SUMIF(COGS!$C:$C,$A33,COGS!J:J) -> 0 | J33: =SUMIF(COGS!$C:$C,$A33,COGS!K:K) -> 0 | K33: =SUMIF(COGS!$C:$C,$A33,COGS!L:L) -> 0 | L33: =SUMIF(COGS!$C:$C,$A33,COGS!M:M) -> 0 | M33: =SUMIF(COGS!$C:$C,$A33,COGS!N:N) -> 0 | N33: =SUMIF(COGS!$C:$C,$A33,COGS!O:O) -> 0 | O33: =SUMIF(COGS!$C:$C,$A33,COGS!P:P) -> 0 | P33: =SUMIF(COGS!$C:$C,$A33,COGS!Q:Q) -> 0 | Q33: =SUMIF(COGS!$C:$C,$A33,COGS!R:R) -> 0 | R33: =SUMIF(COGS!$C:$C,$A33,COGS!S:S) -> 0 | S33: =SUMIF(COGS!$C:$C,$A33,COGS!T:T) -> 0 | T33: =SUMIF(COGS!$C:$C,$A33,COGS!U:U) -> 0 | U33: =SUMIF(COGS!$C:$C,$A33,COGS!V:V) -> 0
A34: Growth | D34: =SUMIF(COGS!$C:$C,$A34,COGS!E:E) -> 0 | E34: =SUMIF(COGS!$C:$C,$A34,COGS!F:F) -> 0 | F34: =SUMIF(COGS!$C:$C,$A34,COGS!G:G) -> 0 | G34: =SUMIF(COGS!$C:$C,$A34,COGS!H:H) -> 0 | H34: =SUMIF(COGS!$C:$C,$A34,COGS!I:I) -> 0 | I34: =SUMIF(COGS!$C:$C,$A34,COGS!J:J) -> 0 | J34: =SUMIF(COGS!$C:$C,$A34,COGS!K:K) -> 0 | K34: =SUMIF(COGS!$C:$C,$A34,COGS!L:L) -> 0 | L34: =SUMIF(COGS!$C:$C,$A34,COGS!M:M) -> 0 | M34: =SUMIF(COGS!$C:$C,$A34,COGS!N:N) -> 0 | N34: =SUMIF(COGS!$C:$C,$A34,COGS!O:O) -> 0 | O34: =SUMIF(COGS!$C:$C,$A34,COGS!P:P) -> 0 | P34: =SUMIF(COGS!$C:$C,$A34,COGS!Q:Q) -> 0 | Q34: =SUMIF(COGS!$C:$C,$A34,COGS!R:R) -> 0 | R34: =SUMIF(COGS!$C:$C,$A34,COGS!S:S) -> 0 | S34: =SUMIF(COGS!$C:$C,$A34,COGS!T:T) -> 0 | T34: =SUMIF(COGS!$C:$C,$A34,COGS!U:U) -> 0 | U34: =SUMIF(COGS!$C:$C,$A34,COGS!V:V) -> 0
A37: Total
A38: Ops | D38: =D27+D32 -> 18166.667 | E38: =E27+E32 -> 4583.3333 | F38: =F27+F32 -> 4583.3333 | G38: =G27+G32 -> 12083.333 | H38: =H27+H32 -> 6083.3333 | I38: =I27+I32 -> 6304.5833 | J38: =J27+J32 -> 9333.8333 | K38: =K27+K32 -> 6333.8333 | ... U38: =U27+U32 -> 56705.333
A39: R&D | D39: =D28+D33 -> 0 | E39: =E28+E33 -> 0 | F39: =F28+F33 -> 0 | G39: =G28+G33 -> 0 | H39: =H28+H33 -> 0 | I39: =I28+I33 -> 0 | J39: =J28+J33 -> 0 | K39: =K28+K33 -> 0 | ... U39: =U28+U33 -> 0
A40: Growth | D40: =D29+D34 -> 0 | E40: =E29+E34 -> 0 | F40: =F29+F34 -> 3000 | G40: =G29+G34 -> 3000 | H40: =H29+H34 -> 3000 | I40: =I29+I34 -> 3000 | J40: =J29+J34 -> 3000 | K40: =K29+K34 -> 3000 | ... U40: =U29+U34 -> 7500
A41: Other | D41: =D42-D38-D39-D40 -> 2291.6667 | E41: =E42-E38-E39-E40 -> 2291.6667 | F41: =F42-F38-F39-F40 -> 2291.6667 | G41: =G42-G38-G39-G40 -> 6875 | H41: =H42-H38-H39-H40 -> 6875 | I41: =I42-I38-I39-I40 -> 6875 | J41: =J42-J38-J39-J40 -> 9166.6667 | K41: =K42-K38-K39-K40 -> 9166.6667 | ... U41: =U42-U38-U39-U40 -> 30250
A42: Total Expenses | D42: ='FS-Month'!D25+'FS-Month'!D18 -> 20458.333 | E42: ='FS-Month'!E25+'FS-Month'!E18 -> 6875 | F42: ='FS-Month'!F25+'FS-Month'!F18 -> 9875 | G42: ='FS-Month'!G25+'FS-Month'!G18 -> 21958.333 | H42: ='FS-Month'!H25+'FS-Month'!H18 -> 15958.333 | I42: ='FS-Month'!I25+'FS-Month'!I18 -> 16179.583 | J42: ='FS-Month'!J25+'FS-Month'!J18 -> 21500.5 | K42: ='FS-Month'!K25+'FS-Month'!K18 -> 18500.5 | ... U42: ='FS-Month'!U25+'FS-Month'!U18 -> 94455.333
A45: Pie Chart
A46: Ops | C46: =D46/D$50 -> 0.39203631 | D46: =SUM(38:38) -> 212285.08
A47: R&D | C47: =D47/D$50 -> 0 | D47: =SUM(39:39) -> 0
A48: Growth | C48: =D48/D$50 -> 0.13850584 | D48: =SUM(40:40) -> 75000
A49: Other | C49: =D49/D$50 -> 0.46945785 | D49: =SUM(41:41) -> 254208.33
A50: Total Expenses | D50: =SUM(42:42) -> 541493.42

Sheet FS-Annual
A1: =Settings!C5 -> VReeMind
A2: Financial Statement (Annual)
A3: =+TODAY() -> 44143
C4: D-O | D4: P-AA | E4: AB-AM | F4: AN-AY | G4: AZ-BK | H4: BL-BW | I4: BX-CI
A6: Net Present Value | B6: =NPV(Settings!C21,C111:I111) -> 51678189 | C6: =Settings!C7 -> 43466 | D6: =EDATE(C6,12) -> 43831 | E6: =EDATE(D6,12) -> 44197 | F6: =EDATE(E6,12) -> 44562 | G6: =EDATE(F6,12) -> 44927 | H6: =EDATE(G6,12) -> 45292 | I6: =EDATE(H6,12) -> 45658 | J6: CAGR
B7: Unit | C7: 1 | D7: =C7+1 -> 2 | E7: =D7+1 -> 3 | F7: =E7+1 -> 4 | G7: =F7+1 -> 5 | H7: =G7+1 -> 6 | I7: =H7+1 -> 7 | J7: Y3-Y7
A9: KEY INDICATORS
A17: INCOME STATEMENT
A19: Revenue | B19: =Settings!$C$6 -> USD | C19: =SUM(C20:C23) -> 0 | D19: =SUM(D20:D23) -> 208701.37 | E19: =SUM(E20:E23) -> 3766395.6 | F19: =SUM(F20:F23) -> 7386963.3 | G19: =SUM(G20:G23) -> 11444990 | H19: =SUM(H20:H23) -> 20542725 | I19: =SUM(I20:I23) -> 36015130 | J19: =IF(IFERROR((I19/E19)^(1/5)-1,"-")<0,"-",IFERROR((I19/E19)^(1/5)-1,"-")) -> 0.57076715
A20: ='FS-Month'!A13 -> SOURCE #1: Self-Service Subscriptions | B20: =Settings!$C$6 -> USD | C20: =SUM('FS-Month'!D13:O13) -> 0 | D20: =SUM('FS-Month'!P13:AA13) -> 208701.37 | E20: =SUM('FS-Month'!AB13:AM13) -> 3485595.6 | F20: =SUM('FS-Month'!AN13:AY13) -> 5889363.3 | G20: =SUM('FS-Month'!AZ13:BK13) -> 8956669.8 | H20: =SUM('FS-Month'!BL13:BW13) -> 15970845 | I20: =SUM('FS-Month'!BX13:CI13) -> 28464922 | J20: =IF(IFERROR((I20/E20)^(1/5)-1,"-")<0,"-",IFERROR((I20/E20)^(1/5)-1,"-")) -> 0.52197178
A21: ='FS-Month'!A14 -> SOURCE #2: Inbound Sales | B21: =Settings!$C$6 -> USD | C21: =SUM('FS-Month'!D14:O14) -> 0 | D21: =SUM('FS-Month'!P14:AA14) -> 0 | E21: =SUM('FS-Month'!AB14:AM14) -> 0 | F21: =SUM('FS-Month'!AN14:AY14) -> 0 | G21: =SUM('FS-Month'!AZ14:BK14) -> 0 | H21: =SUM('FS-Month'!BL14:BW14) -> 0 | I21: =SUM('FS-Month'!BX14:CI14) -> 0 | J21: =IF(IFERROR((I21/E21)^(1/5)-1,"-")<0,"-",IFERROR((I21/E21)^(1/5)-1,"-")) -> -
A22: ='FS-Month'!A15 -> SOURCE #3: Outbound Sales | B22: =Settings!$C$6 -> USD | C22: =SUM('FS-Month'!D15:O15) -> 0 | D22: =SUM('FS-Month'!P15:AA15) -> 0 | E22: =SUM('FS-Month'!AB15:AM15) -> 0 | F22: =SUM('FS-Month'!AN15:AY15) -> 0 | G22: =SUM('FS-Month'!AZ15:BK15) -> 0 | H22: =SUM('FS-Month'!BL15:BW15) -> 0 | I22: =SUM('FS-Month'!BX15:CI15) -> 0 | J22: =IF(IFERROR((I22/E22)^(1/5)-1,"-")<0,"-",IFERROR((I22/E22)^(1/5)-1,"-")) -> -
A23: ='FS-Month'!A16 -> Renewals | B23: =Settings!$C$6 -> USD | C23: =SUM('FS-Month'!D16:O16) -> 0 | D23: =SUM('FS-Month'!P16:AA16) -> 0 | E23: =SUM('FS-Month'!AB16:AM16) -> 280800 | F23: =SUM('FS-Month'!AN16:AY16) -> 1497600 | G23: =SUM('FS-Month'!AZ16:BK16) -> 2488320 | H23: =SUM('FS-Month'!BL16:BW16) -> 4571880 | I23: =SUM('FS-Month'!BX16:CI16) -> 7550208 | J23: =IF(IFERROR((I23/E23)^(1/5)-1,"-")<0,"-",IFERROR((I23/E23)^(1/5)-1,"-")) -> 0.9315785
J24: =IF(IFERROR((I24/E24)^(1/5)-1,"-")<0,"-",IFERROR((I24/E24)^(1/5)-1,"-")) -> -
A25: COGS | B25: =Settings!$C$6 -> USD | C25: =SUM(C26:C28) -> 0 | D25: =SUM(D26:D28) -> 381439.48 | E25: =SUM(E26:E28) -> 2955395.2 | F25: =SUM(F26:F28) -> 5162194.7 | G25: =SUM(G26:G28) -> 8131569.5 | H25: =SUM(H26:H28) -> 12968149 | I25: =SUM(I26:I28) -> 21692893 | J25: =IF(IFERROR((I25/E25)^(1/5)-1,"-")<0,"-",IFERROR((I25/E25)^(1/5)-1,"-")) -> 0.48984259
A26: ='FS-Month'!A19 -> CATEGORY #1: Hosting/Customer Service | B26: =Settings!$C$6 -> USD | C26: =SUM('FS-Month'!D19:O19) -> 0 | D26: =SUM('FS-Month'!P19:AA19) -> 594 | E26: =SUM('FS-Month'!AB19:AM19) -> 9596.7234 | F26: =SUM('FS-Month'!AN19:AY19) -> 25077.577 | G26: =SUM('FS-Month'!AZ19:BK19) -> 47743.097 | H26: =SUM('FS-Month'!BL19:BW19) -> 80927.685 | I26: =SUM('FS-Month'!BX19:CI19) -> 129513.24 | J26: =IF(IFERROR((I26/E26)^(1/5)-1,"-")<0,"-",IFERROR((I26/E26)^(1/5)-1,"-")) -> 0.68282222
A27: ='FS-Month'!A20 -> CATEGORY #2: Partnership Commissions | B27: =Settings!$C$6 -> USD | C27: =SUM('FS-Month'!D20:O20) -> 0 | D27: =SUM('FS-Month'!P20:AA20) -> 318235.07 | E27: =SUM('FS-Month'!AB20:AM20) -> 1815879.8 | F27: =SUM('FS-Month'!AN20:AY20) -> 2921028.2 | G27: =SUM('FS-Month'!AZ20:BK20) -> 4650329.5 | H27: =SUM('FS-Month'!BL20:BW20) -> 6724404 | I27: =SUM('FS-Month'!BX20:CI20) -> 10758841 | J27: =IF(IFERROR((I27/E27)^(1/5)-1,"-")<0,"-",IFERROR((I27/E27)^(1/5)-1,"-")) -> 0.4273671
A28: ='FS-Month'!A21 -> CATEGORY #3: App Store Fees | B28: =Settings!$C$6 -> USD | C28: =SUM('FS-Month'!D21:O21) -> 0 | D28: =SUM('FS-Month'!P21:AA21) -> 62610.411 | E28: =SUM('FS-Month'!AB21:AM21) -> 1129918.7 | F28: =SUM('FS-Month'!AN21:AY21) -> 2216089 | G28: =SUM('FS-Month'!AZ21:BK21) -> 3433496.9 | H28: =SUM('FS-Month'!BL21:BW21) -> 6162817.4 | I28: =SUM('FS-Month'!BX21:CI21) -> 10804539 | J28: =IF(IFERROR((I28/E28)^(1/5)-1,"-")<0,"-",IFERROR((I28/E28)^(1/5)-1,"-")) -> 0.57076715
A29: Gross Profit | B29: =Settings!$C$6 -> USD | C29: =C19-C25 -> 0 | D29: =D19-D25 -> -172738.11 | E29: =E19-E25 -> 811000.43 | F29: =F19-F25 -> 2224768.6 | G29: =G19-G25 -> 3313420.3 | H29: =H19-H25 -> 7574575.6 | I29: =I19-I25 -> 14322237 | J29: =IF(IFERROR((I29/E29)^(1/5)-1,"-")<0,"-",IFERROR((I29/E29)^(1/5)-1,"-")) -> 0.77581595
A30: Gross margin | B30: % | C30: =IFERROR(C29/C$19,"-") -> - | D30: =IFERROR(D29/D$19,"-") -> -0.82768077 | E30: =IFERROR(E29/E$19,"-") -> 0.21532534 | F30: =IFERROR(F29/F$19,"-") -> 0.30117499 | G30: =IFERROR(G29/G$19,"-") -> 0.28950836 | H30: =IFERROR(H29/H$19,"-") -> 0.36872303 | I30: =IFERROR(I29/I$19,"-") -> 0.39767277 | J30: =IF(IFERROR((I30/E30)^(1/5)-1,"-")<0,"-",IFERROR((I30/E30)^(1/5)-1,"-")) -> 0.13054054
D31: =(D28)=D19*0.3 -> TRUE | E31: =(E28)=E19*0.3 -> TRUE | F31: =(F28)=F19*0.3 -> TRUE | G31: =(G28)=G19*0.3 -> TRUE | H31: =(H28)=H19*0.3 -> TRUE | I31: =(I28)=I19*0.3 -> TRUE
A32: SG&A | B32: =Settings!$C$6 -> USD | C32: =SUM(C33:C40) -> 220770.33 | D32: =SUM(D33:D40) -> 594955.08 | E32: =SUM(E33:E40) -> 985808.37 | F32: =SUM(F33:F40) -> 1517992.1 | G32: =SUM(G33:G40) -> 1964791.9 | H32: =SUM(H33:H40) -> 2421328 | I32: =SUM(I33:I40) -> 2518233.2 | J32: =IF(IFERROR((I32/E32)^(1/5)-1,"-")<0,"-",IFERROR((I32/E32)^(1/5)-1,"-")) -> 0.20631489
A33: ='FS-Month'!A26 -> PAYROLL | B33: =Settings!$C$6 -> USD | C33: =SUM('FS-Month'!D26:O26) -> 148958.33 | D33: =SUM('FS-Month'!P26:AA26) -> 399345.83 | E33: =SUM('FS-Month'!AB26:AM26) -> 742957.87 | F33: =SUM('FS-Month'!AN26:AY26) -> 1183631.6 | G33: =SUM('FS-Month'!AZ26:BK26) -> 1511676.4 | H33: =SUM('FS-Month'!BL26:BW26) -> 1870311.3 | I33: =SUM('FS-Month'!BX26:CI26) -> 1965783.2 | J33: =IF(IFERROR((I33/E33)^(1/5)-1,"-")<0,"-",IFERROR((I33/E33)^(1/5)-1,"-")) -> 0.21482658
A34: ='FS-Month'!A27 -> MARKETING & GROWTH | B34: =Settings!$C$6 -> USD | C34: =SUM('FS-Month'!D27:O27) -> 30000 | D34: =SUM('FS-Month'!P27:AA27) -> 90000 | E34: =SUM('FS-Month'!AB27:AM27) -> 150000 | F34: =SUM('FS-Month'!AN27:AY27) -> 240000 | G34: =SUM('FS-Month'!AZ27:BK27) -> 360000 | H34: =SUM('FS-Month'!BL27:BW27) -> 480000 | I34: =SUM('FS-Month'!BX27:CI27) -> 480000 | J34: =IF(IFERROR((I34/E34)^(1/5)-1,"-")<0,"-",IFERROR((I34/E34)^(1/5)-1,"-")) -> 0.26191469
A35: ='FS-Month'!A28 -> LEGAL, ADVISORY, PROF. SERVICES | B35: =Settings!$C$6 -> USD | C35: =SUM('FS-Month'!D28:O28) -> 16000 | D35: =SUM('FS-Month'!P28:AA28) -> 74000 | E35: =SUM('FS-Month'!AB28:AM28) -> 31000 | F35: =SUM('FS-Month'!AN28:AY28) -> 40000 | G35: =SUM('FS-Month'!AZ28:BK28) -> 40000 | H35: =SUM('FS-Month'!BL28:BW28) -> 40000 | I35: =SUM('FS-Month'!BX28:CI28) -> 40000 | J35: =IF(IFERROR((I35/E35)^(1/5)-1,"-")<0,"-",IFERROR((I35/E35)^(1/5)-1,"-")) -> 0.052300216
A36: ='FS-Month'!A29 -> WFA Stipend | B36: =Settings!$C$6 -> USD | C36: =SUM('FS-Month'!D29:O29) -> 21000 | D36: =SUM('FS-Month'!P29:AA29) -> 21000 | E36: =SUM('FS-Month'!AB29:AM29) -> 42000 | F36: =SUM('FS-Month'!AN29:AY29) -> 27000 | G36: =SUM('FS-Month'!AZ29:BK29) -> 15000 | H36: =SUM('FS-Month'!BL29:BW29) -> 12000 | I36: =SUM('FS-Month'!BX29:CI29) -> 12000 | J36: =IF(IFERROR((I36/E36)^(1/5)-1,"-")<0,"-",IFERROR((I36/E36)^(1/5)-1,"-")) -> -
A37: ='FS-Month'!A30 -> TECH SUPPORT & SERVICES | B37: =Settings!$C$6 -> USD | C37: =SUM('FS-Month'!D30:O30) -> 1812 | D37: =SUM('FS-Month'!P30:AA30) -> 5609.25 | E37: =SUM('FS-Month'!AB30:AM30) -> 9850.5 | F37: =SUM('FS-Month'!AN30:AY30) -> 13360.5 | G37: =SUM('FS-Month'!AZ30:BK30) -> 15115.5 | H37: =SUM('FS-Month'!BL30:BW30) -> 17016.75 | I37: =SUM('FS-Month'!BX30:CI30) -> 18450 | J37: =IF(IFERROR((I37/E37)^(1/5)-1,"-")<0,"-",IFERROR((I37/E37)^(1/5)-1,"-")) -> 0.13372473
A38: ='FS-Month'!A31 -> INSURANCE | B38: =Settings!$C$6 -> USD | C38: =SUM('FS-Month'!D31:O31) -> 1000 | D38: =SUM('FS-Month'!P31:AA31) -> 1000 | E38: =SUM('FS-Month'!AB31:AM31) -> 2000 | F38: =SUM('FS-Month'!AN31:AY31) -> 4000 | G38: =SUM('FS-Month'!AZ31:BK31) -> 8000 | H38: =SUM('FS-Month'!BL31:BW31) -> 2000 | I38: =SUM('FS-Month'!BX31:CI31) -> 2000 | J38: =IF(IFERROR((I38/E38)^(1/5)-1,"-")<0,"-",IFERROR((I38/E38)^(1/5)-1,"-")) -> 0
A39: ='FS-Month'!A32 -> 0 | B39: =Settings!$C$6 -> USD | C39: =SUM('FS-Month'!D32:O32) -> 0 | D39: =SUM('FS-Month'!P32:AA32) -> 0 | E39: =SUM('FS-Month'!AB32:AM32) -> 0 | F39: =SUM('FS-Month'!AN32:AY32) -> 0 | G39: =SUM('FS-Month'!AZ32:BK32) -> 0 | H39: =SUM('FS-Month'!BL32:BW32) -> 0 | I39: =SUM('FS-Month'!BX32:CI32) -> 0 | J39: =IF(IFERROR((I39/E39)^(1/5)-1,"-")<0,"-",IFERROR((I39/E39)^(1/5)-1,"-")) -> -
A40: ='FS-Month'!A33 -> OTHER EXPENSES | B40: =Settings!$C$6 -> USD | C40: =SUM('FS-Month'!D33:O33) -> 2000 | D40: =SUM('FS-Month'!P33:AA33) -> 4000 | E40: =SUM('FS-Month'!AB33:AM33) -> 8000 | F40: =SUM('FS-Month'!AN33:AY33) -> 10000 | G40: =SUM('FS-Month'!AZ33:BK33) -> 15000 | H40: =SUM('FS-Month'!BL33:BW33) -> 0 | I40: =SUM('FS-Month'!BX33:CI33) -> 0 | J40: =IF(IFERROR((I40/E40)^(1/5)-1,"-")<0,"-",IFERROR((I40/E40)^(1/5)-1,"-")) -> -
A41: EBITDA | B41: =Settings!$C$6 -> USD | C41: =C29-C32 -> -220770.33 | D41: =D29-D32 -> -767693.19 | E41: =E29-E32 -> -174807.95 | F41: =F29-F32 -> 706776.45 | G41: =G29-G32 -> 1348628.4 | H41: =H29-H32 -> 5153247.6 | I41: =I29-I32 -> 11804004 | J41: =IF(IFERROR((I41/E41)^(1/5)-1,"-")<0,"-",IFERROR((I41/E41)^(1/5)-1,"-")) -> -
A42: EBITDA margin | C42: =IFERROR(MAX((C41/C$19),0),"-") -> - | D42: =IFERROR(MAX((D41/D$19),0),"-") -> 0 | E42: =IFERROR(MAX((E41/E$19),0),"-") -> 0 | F42: =IFERROR(MAX((F41/F$19),0),"-") -> 0.09567889 | G42: =IFERROR(MAX((G41/G$19),0),"-") -> 0.1178357 | H42: =IFERROR(MAX((H41/H$19),0),"-") -> 0.25085512 | I42: =IFERROR(MAX((I41/I$19),0),"-") -> 0.32775124
A44: D&A | B44: =Settings!$C$6 -> USD | C44: =SUM('FS-Month'!D37:O37) -> 0 | D44: =SUM('FS-Month'!P37:AA37) -> 0 | E44: =SUM('FS-Month'!AB37:AM37) -> 0 | F44: =SUM('FS-Month'!AN37:AY37) -> 0 | G44: =SUM('FS-Month'!AZ37:BK37) -> 0 | H44: =SUM('FS-Month'!BL37:BW37) -> 0 | I44: =SUM('FS-Month'!BX37:CI37) -> 0 | J44: =IF(IFERROR((I44/E44)^(1/5)-1,"-")<0,"-",IFERROR((I44/E44)^(1/5)-1,"-")) -> -
A45: EBIT | B45: =Settings!$C$6 -> USD | C45: =C41-C44 -> -220770.33 | D45: =D41-D44 -> -767693.19 | E45: =E41-E44 -> -174807.95 | F45: =F41-F44 -> 706776.45 | G45: =G41-G44 -> 1348628.4 | H45: =H41-H44 -> 5153247.6 | I45: =I41-I44 -> 11804004 | J45: =IF(IFERROR((I45/E45)^(1/5)-1,"-")<0,"-",IFERROR((I45/E45)^(1/5)-1,"-")) -> -
A46: EBIT margin | C46: =IFERROR(MAX((C45/C$19),0),"-") -> - | D46: =IFERROR(MAX((D45/D$19),0),"-") -> 0 | E46: =IFERROR(MAX((E45/E$19),0),"-") -> 0 | F46: =IFERROR(MAX((F45/F$19),0),"-") -> 0.09567889 | G46: =IFERROR(MAX((G45/G$19),0),"-") -> 0.1178357 | H46: =IFERROR(MAX((H45/H$19),0),"-") -> 0.25085512
A48: Interest expense | B48: =Settings!$C$6 -> USD | C48: =SUM('FS-Month'!D41:O41) -> 0 | D48: =SUM('FS-Month'!P41:AA41) -> 0 | E48: =SUM('FS-Month'!AB41:AM41) -> 0 | F48: =SUM('FS-Month'!AN41:AY41) -> 0 | G48: =SUM('FS-Month'!AZ41:BK41) -> 0 | H48: =SUM('FS-Month'!BL41:BW41) -> 0 | I48: =SUM('FS-Month'!BB41:BM41) -> 0
A49: Income taxes | B49: =Settings!$C$6 -> USD | C49: =IF(C45>0,C45*Settings!$C$16,"0") -> 0 | D49: =IF(D45>0,D45*Settings!$C$16,"0") -> 0 | E49: =IF(E45>0,E45*Settings!$C$16,"0") -> 0 | F49: =IF(F45>0,F45*Settings!$C$16,"0") -> 0 | G49: =IF(G45>0,G45*Settings!$C$16,"0") -> 0 | H49: =IF(H45>0,H45*Settings!$C$16,"0") -> 0 | I49: =IF(I45>0,I45*Settings!$C$16,"0") -> 0 | J49: =IF(IFERROR((I49/E49)^(1/5)-1,"-")<0,"-",IFERROR((I49/E49)^(1/5)-1,"-")) -> -
A50: Net income | B50: =Settings!$C$6 -> USD | C50: =C45-C48-C49 -> -220770.33 | D50: =D45-D48-D49 -> -767693.19 | E50: =E45-E48-E49 -> -174807.95 | F50: =F45-F48-F49 -> 706776.45 | G50: =G45-G48-G49 -> 1348628.4 | H50: =H45-H48-H49 -> 5153247.6 | I50: =I45-I48-I49 -> 11804004 | J50: =IF(IFERROR((I50/E50)^(1/5)-1,"-")<0,"-",IFERROR((I50/E50)^(1/5)-1,"-")) -> -
A51: Net margin | C51: =IFERROR(C50/C19,"-") -> - | D51: =IFERROR(D50/D19,"-") -> -3.6784291 | E51: =IFERROR(E50/E19,"-") -> -0.04641253 | F51: =IFERROR(F50/F19,"-") -> 0.09567889 | G51: =IFERROR(G50/G19,"-") -> 0.1178357 | H51: =IFERROR(H50/H19,"-") -> 0.25085512 | I51: =IFERROR(I50/I19,"-") -> 0.32775124
A54: BALANCE SHEET
A56: Operating cash | B56: =Settings!$C$6 -> USD | C56: ='FS-Month'!O49 -> 179229.67 | D56: ='FS-Month'!AA49 -> 280835.1 | E56: ='FS-Month'!AM49 -> 1331631.5 | F56: ='FS-Month'!AY49 -> 2638644.7 | G56: ='FS-Month'!BK49 -> 5813323.3 | H56: ='FS-Month'!BW49 -> 14804726 | I56: ='FS-Month'!CI49 -> 30860607 | J56: =IF(IFERROR((I56/E56)^(1/5)-1,"-")<0,"-",IFERROR((I56/E56)^(1/5)-1,"-")) -> 0.87501212
A57: Excess cash | B57: =Settings!$C$6 -> USD | C57: ='FS-Month'!O57 -> 0 | D57: 0 | E57: 0 | F57: 0 | G57: 0 | H57: 0 | I57: 0 | J57: =IF(IFERROR((I57/E57)^(1/5)-1,"-")<0,"-",IFERROR((I57/E57)^(1/5)-1,"-")) -> -
A58: Accounts receivable | B58: =Settings!$C$6 -> USD | C58: ='FS-Month'!O58 -> 0 | D58: ='FS-Month'!P58 -> 0 | E58: ='FS-Month'!Q58 -> 0 | F58: ='FS-Month'!R58 -> 0 | G58: ='FS-Month'!S58 -> 0 | H58: ='FS-Month'!T58 -> 0 | I58: ='FS-Month'!U58 -> 0 | J58: =IF(IFERROR((I58/E58)^(1/5)-1,"-")<0,"-",IFERROR((I58/E58)^(1/5)-1,"-")) -> -
A59: Current Assets | B59: =Settings!$C$6 -> USD | C59: =SUM(C56:C58) -> 179229.67 | D59: =SUM(D56:D58) -> 280835.1 | E59: =SUM(E56:E58) -> 1331631.5 | F59: =SUM(F56:F58) -> 2638644.7 | G59: =SUM(G56:G58) -> 5813323.3 | H59: =SUM(H56:H58) -> 14804726 | I59: =SUM(I56:I58) -> 30860607 | J59: =IF(IFERROR((I59/E59)^(1/5)-1,"-")<0,"-",IFERROR((I59/E59)^(1/5)-1,"-")) -> 0.87501212
B60: =Settings!$C$6 -> USD | J60: =IF(IFERROR((I60/E60)^(1/5)-1,"-")<0,"-",IFERROR((I60/E60)^(1/5)-1,"-")) -> -
A61: Intangible assets | B61: =Settings!$C$6 -> USD | C61: ='FS-Month'!O58 -> 0 | D61: 50000 | E61: 50000 | F61: 50000 | G61: 50000 | H61: 50000 | I61: 50000 | J61: =IF(IFERROR((I61/E61)^(1/5)-1,"-")<0,"-",IFERROR((I61/E61)^(1/5)-1,"-")) -> 0
A62: Investments | B62: =Settings!$C$6 -> USD | C62: 0 | D62: 0 | E62: 0 | F62: 0 | G62: 0 | H62: 0 | I62: 0 | J62: =IF(IFERROR((I62/E62)^(1/5)-1,"-")<0,"-",IFERROR((I62/E62)^(1/5)-1,"-")) -> -
A63: Other assets (net) | B63: =Settings!$C$6 -> USD | C63: 0 | D63: 0 | E63: 0 | F63: 0 | J63: =IF(IFERROR((I63/E63)^(1/5)-1,"-")<0,"-",IFERROR((I63/E63)^(1/5)-1,"-")) -> -
A64: Non-Current Assets | B64: =Settings!$C$6 -> USD | C64: =SUM(C61:C63) -> 0 | D64: =SUM(D61:D63) -> 50000 | E64: =SUM(E61:E63) -> 50000 | F64: =SUM(F61:F63) -> 50000 | G64: =SUM(G61:G63) -> 50000 | H64: =SUM(H61:H63) -> 50000 | I64: =SUM(I61:I63) -> 50000 | J64: =IF(IFERROR((I64/E64)^(1/5)-1,"-")<0,"-",IFERROR((I64/E64)^(1/5)-1,"-")) -> 0
B65: =Settings!$C$6 -> USD
A66: Total Assets | B66: =Settings!$C$6 -> USD | C66: =SUM(C64,C59) -> 179229.67 | D66: =SUM(D64,D59) -> 330835.1 | E66: =SUM(E64,E59) -> 1381631.5 | F66: =SUM(F64,F59) -> 2688644.7 | G66: =SUM(G64,G59) -> 5863323.3 | H66: =SUM(H64,H59) -> 14854726 | I66: =SUM(I64,I59) -> 30910607
B67: =Settings!$C$6 -> USD
A68: Accounts payable | B68: =Settings!$C$6 -> USD | C68: ='FS-Month'!O62 -> 0 | D68: ='FS-Month'!AA62 -> 0 | E68: ='FS-Month'!AM62 -> 0 | F68: ='FS-Month'!AY62 -> 0 | G68: ='FS-Month'!BK62 -> 0 | H68: ='FS-Month'!BW62 -> 0 | I68: ='FS-Month'!CI62 -> 0
A69: Deferred Revenue | B69: =Settings!$C$6 -> USD | C69: ='FS-Month'!O64 -> 0 | D69: ='FS-Month'!AA64 -> 619298.63 | E69: ='FS-Month'!AM64 -> 1844903 | F69: ='FS-Month'!AY64 -> 2445139.7 | G69: ='FS-Month'!BK64 -> 4271189.9 | H69: ='FS-Month'!BW64 -> 8109345.2 | I69: ='FS-Month'!CI64 -> 12361223
A70: Total Liabilities | B70: =Settings!$C$6 -> USD | C70: =SUM(C68:C69) -> 0 | D70: =SUM(D68:D69) -> 619298.63 | E70: =SUM(E68:E69) -> 1844903 | F70: =SUM(F68:F69) -> 2445139.7 | G70: =SUM(G68:G69) -> 4271189.9 | H70: =SUM(H68:H69) -> 8109345.2 | I70: =SUM(I68:I69) -> 12361223 | J70: =IF(IFERROR((I70/E70)^(1/5)-1,"-")<0,"-",IFERROR((I70/E70)^(1/5)-1,"-")) -> 0.4629099
B71: =Settings!$C$6 -> USD
A72: Common equity | B72: =Settings!$C$6 -> USD | C72: ='FS-Month'!O67 -> 400000 | D72: ='FS-Month'!AA67 -> 700000 | E72: ='FS-Month'!AM67 -> 700000 | F72: ='FS-Month'!AY67 -> 700000 | G72: ='FS-Month'!BK67 -> 700000 | H72: ='FS-Month'!BW67 -> 700000 | I72: ='FS-Month'!CI67 -> 700000 | J72: =IF(IFERROR((I72/E72)^(1/5)-1,"-")<0,"-",IFERROR((I72/E72)^(1/5)-1,"-")) -> 0
A73: Retainied Earnings | B73: =Settings!$C$6 -> USD | C73: ='FS-Month'!O69 -> -220770.33 | D73: ='FS-Month'!AA69 -> -988463.53 | E73: ='FS-Month'!AM69 -> -1163271.5 | F73: ='FS-Month'!AY69 -> -456495.03 | G73: ='FS-Month'!BK69 -> 892133.36 | H73: ='FS-Month'!BW69 -> 6045381 | I73: ='FS-Month'!CI69 -> 17849384 | J73: =IF(IFERROR((I73/E73)^(1/5)-1,"-")<0,"-",IFERROR((I73/E73)^(1/5)-1,"-")) -> -
A74: Total Equity | B74: =Settings!$C$6 -> USD | C74: =C72+C73 -> 179229.67 | D74: =D72+D73 -> -288463.53 | E74: =E72+E73 -> -463271.47 | F74: =F72+F73 -> 243504.97 | G74: =G72+G73 -> 1592133.4 | H74: =H72+H73 -> 6745381 | I74: =I72+I73 -> 18549384 | J74: =IF(IFERROR((I74/E74)^(1/5)-1,"-")<0,"-",IFERROR((I74/E74)^(1/5)-1,"-")) -> -
J75: =IF(IFERROR((I75/E75)^(1/5)-1,"-")<0,"-",IFERROR((I75/E75)^(1/5)-1,"-")) -> -
A76: Total Liabilities + Equity | B76: =Settings!$C$6 -> USD | C76: =C74+C70 -> 179229.67 | D76: =D74+D70 -> 330835.1 | E76: =E74+E70 -> 1381631.5 | F76: =F74+F70 -> 2688644.7 | G76: =G74+G70 -> 5863323.3 | H76: =H74+H70 -> 14854726 | I76: =I74+I70 -> 30910607 | J76: =IF(IFERROR((I76/E76)^(1/5)-1,"-")<0,"-",IFERROR((I76/E76)^(1/5)-1,"-")) -> 0.86184302
A77: Check | C77: =C76-C66 -> 0 | D77: =D76-D66 -> 0 | E77: =E76-E66 -> 0 | F77: =F76-F66 -> 0 | G77: =G76-G66 -> 0 | H77: =H76-H66 -> 0 | I77: =I76-I66 -> 0
A80: CASH FLOW
A82: Initial cash balance | B82: =Settings!$C$6 -> USD | C82: 100000 | D82: =C93 -> 179229.67 | E82: =D93 -> 280835.1 | F82: =E93 -> 1331631.5 | G82: =F93 -> 2638644.7 | H82: =G93 -> 5813323.3 | I82: =H93 -> 14804726 | J82: =IF(IFERROR((I82/E82)^(1/5)-1,"-")<0,"-",IFERROR((I82/E82)^(1/5)-1,"-")) -> 1.2099874
A83: Cash infusions | B83: =Settings!$C$6 -> USD | C83: 0 | D83: =SUM('FS-Month'!P79:AA79) -> 0 | E83: =SUM('FS-Month'!AB79:AM79) -> 0 | F83: =SUM('FS-Month'!AN79:AY79) -> 0 | G83: =SUM('FS-Month'!AZ79:BK79) -> 0 | H83: =SUM('FS-Month'!BL79:BW79) -> 0 | I83: =SUM('FS-Month'!BX79:CI79) -> 0 | J83: =IF(IFERROR((I83/E83)^(1/5)-1,"-")<0,"-",IFERROR((I83/E83)^(1/5)-1,"-")) -> -
A84: Operating change in cash | B84: =Settings!$C$6 -> USD | C84: =C85+C88+C89-C90+C91-C92 -> 79229.667 | D84: =D85+D88+D89-D90+D91-D92 -> 101605.44 | E84: =E85+E88+E89-E90+E91-E92 -> 1050796.4 | F84: =F85+F88+F89-F90+F91-F92 -> 1307013.2 | G84: =G85+G88+G89-G90+G91-G92 -> 3174678.6 | H84: =H85+H88+H89-H90+H91-H92 -> 8991402.9 | I84: =I85+I88+I89-I90+I91-I92 -> 16055881 | J84: =IF(IFERROR((I84/E84)^(1/5)-1,"-")<0,"-",IFERROR((I84/E84)^(1/5)-1,"-")) -> 0.7251351
A85: Net income | B85: =Settings!$C$6 -> USD | C85: =C50 -> -220770.33 | D85: =D50 -> -767693.19 | E85: =E50 -> -174807.95 | F85: =F50 -> 706776.45 | G85: =G50 -> 1348628.4 | H85: =H50 -> 5153247.6 | I85: =I50 -> 11804004 | J85: =IF(IFERROR((I85/E85)^(1/5)-1,"-")<0,"-",IFERROR((I85/E85)^(1/5)-1,"-")) -> -
A88: (+) D&A | B88: =Settings!$C$6 -> USD | C88: =SUM('FS-Month'!D84:O84) -> 0 | D88: =SUM('FS-Month'!P84:AA84) -> 0 | E88: =SUM('FS-Month'!AB84:AM84) -> 0 | F88: =SUM('FS-Month'!AN84:AY84) -> 0 | G88: =SUM('FS-Month'!AZ84:BK84) -> 0 | H88: =SUM('FS-Month'!BA84:BL84) -> 0 | I88: =SUM('FS-Month'!BB84:BM84) -> 0 | J88: =IF(IFERROR((I88/E88)^(1/5)-1,"-")<0,"-",IFERROR((I88/E88)^(1/5)-1,"-")) -> -
A89: (+) Cash from Investors / Change in WC | B89: =Settings!$C$6 -> USD | C89: =SUM('FS-Month'!D85:O85) -> 300000 | D89: =SUM('FS-Month'!P85:AA85) -> 300000 | E89: =SUM('FS-Month'!AB85:AM85) -> 0 | F89: =SUM('FS-Month'!AN85:AY85) -> 0 | G89: =SUM('FS-Month'!AZ85:BK85) -> 0 | H89: =SUM('FS-Month'!BA85:BL85) -> 0 | I89: =SUM('FS-Month'!BB85:BM85) -> 0 | J89: =IF(IFERROR((I89/E89)^(1/5)-1,"-")<0,"-",IFERROR((I89/E89)^(1/5)-1,"-")) -> -
A90: (-) Intangible Assets | B90: =Settings!$C$6 -> USD | C90: =SUM('FS-Month'!D86:O86) -> 0 | D90: =SUM('FS-Month'!P86:AA86) -> 50000 | E90: =SUM('FS-Month'!AB86:AM86) -> 0 | F90: =SUM('FS-Month'!AN86:AY86) -> 0 | G90: =SUM('FS-Month'!AZ86:BK86) -> 0 | H90: =SUM('FS-Month'!BA86:BL86) -> 0 | I90: =SUM('FS-Month'!BB86:BM86) -> 0 | J90: =IF(IFERROR((I90/E90)^(1/5)-1,"-")<0,"-",IFERROR((I90/E90)^(1/5)-1,"-")) -> -
A91: (+) Change in debt | B91: =Settings!$C$6 -> USD | C91: =SUM('FS-Month'!D87:O87) -> 0 | D91: =SUM('FS-Month'!P87:AA87) -> 619298.63 | E91: =SUM('FS-Month'!AB87:AM87) -> 1225604.4 | F91: =SUM('FS-Month'!AN87:AY87) -> 600236.71 | G91: =SUM('FS-Month'!AZ87:BK87) -> 1826050.2 | H91: =SUM('FS-Month'!BL87:BW87) -> 3838155.3 | I91: =SUM('FS-Month'!BX87:CI87) -> 4251877.8 | J91: =IF(IFERROR((I91/E91)^(1/5)-1,"-")<0,"-",IFERROR((I91/E91)^(1/5)-1,"-")) -> 0.28246669
A92: (-) Dividends | B92: =Settings!$C$6 -> USD | C92: =SUM('FS-Month'!D88:O88) -> 0 | D92: =SUM('FS-Month'!P88:AA88) -> 0 | E92: =SUM('FS-Month'!AB88:AM88) -> 0 | F92: =SUM('FS-Month'!AN88:AY88) -> 0 | G92: =SUM('FS-Month'!AZ88:BK88) -> 0 | H92: =SUM('FS-Month'!BA88:BL88) -> 0 | I92: =SUM('FS-Month'!BB88:BM88) -> 0 | J92: =IF(IFERROR((I92/E92)^(1/5)-1,"-")<0,"-",IFERROR((I92/E92)^(1/5)-1,"-")) -> -
A93: Ending cash balance | B93: =Settings!$C$6 -> USD | C93: =SUM(C82,C83,C84) -> 179229.67 | D93: =SUM(D82,D83,D84) -> 280835.1 | E93: =SUM(E82,E83,E84) -> 1331631.5 | F93: =SUM(F82,F83,F84) -> 2638644.7 | G93: =SUM(G82,G83,G84) -> 5813323.3 | H93: =SUM(H82,H83,H84) -> 14804726 | I93: =SUM(I82,I83,I84) -> 30860607 | J93: =IF(IFERROR((I93/E93)^(1/5)-1,"-")<0,"-",IFERROR((I93/E93)^(1/5)-1,"-")) -> 0.87501212
A94: Total capital requirements | B94: =Settings!$C$6 -> USD | C94: ='FS-Month'!D90 -> -24859.417
A95: CASH FLOW CHECK | C95: =C93=C59 -> TRUE | D95: =D93=D59 -> TRUE | E95: =E93=E59 -> TRUE | F95: =F93=F59 -> TRUE | G95: =G93=G59 -> TRUE | H95: =H93=H59 -> TRUE | I95: =I93=I59 -> TRUE
A97: VALUATION
A99: EBIT | B99: =Settings!$C$6 -> USD | C99: =C45 -> -220770.33 | D99: =D45 -> -767693.19 | E99: =E45 -> -174807.95 | F99: =F45 -> 706776.45 | G99: =G45 -> 1348628.4 | H99: =H45 -> 5153247.6 | I99: =I45 -> 11804004 | J99: =IF(IFERROR((I99/F99)^(1/5)-1,"-")<0,"-",IFERROR((I99/F99)^(1/5)-1,"-")) -> 0.75610085
A100: (-) Taxes | B100: =Settings!$C$6 -> USD | C100: =C49 -> 0 | D100: =D49 -> 0 | E100: =E49 -> 0 | F100: =F49 -> 0 | G100: =G49 -> 0 | H100: =H49 -> 0 | I100: =I49 -> 0 | J100: =IF(IFERROR((I100/F100)^(1/5)-1,"-")<0,"-",IFERROR((I100/F100)^(1/5)-1,"-")) -> -
A101: (-) Interests | B101: =Settings!$C$6 -> USD | C101: =C48 -> 0 | D101: =D48 -> 0 | E101: =E48 -> 0 | F101: =F48 -> 0 | G101: =G48 -> 0 | H101: =H48 -> 0 | I101: =I48 -> 0 | J101: =IF(IFERROR((I101/F101)^(1/5)-1,"-")<0,"-",IFERROR((I101/F101)^(1/5)-1,"-")) -> -
A102: Net income | B102: =Settings!$C$6 -> USD | C102: =C99-C100-C101 -> -220770.33 | D102: =D99-D100-D101 -> -767693.19 | E102: =E99-E100-E101 -> -174807.95 | F102: =F99-F100-F101 -> 706776.45 | G102: =G99-G100-G101 -> 1348628.4 | H102: =H99-H100-H101 -> 5153247.6 | I102: =I99-I100-I101 -> 11804004 | J102: =IF(IFERROR((I102/F102)^(1/5)-1,"-")<0,"-",IFERROR((I102/F102)^(1/5)-1,"-")) -> 0.75610085
A103: (+) D&A | B103: =Settings!$C$6 -> USD | C103: =C44 -> 0 | D103: =D44 -> 0 | E103: =E44 -> 0 | F103: =F44 -> 0 | G103: =G44 -> 0 | H103: =H44 -> 0 | I103: =I44 -> 0 | J103: =IF(IFERROR((I103/F103)^(1/5)-1,"-")<0,"-",IFERROR((I103/F103)^(1/5)-1,"-")) -> -
A104: Gross cash flow | B104: =Settings!$C$6 -> USD | C104: =C102+C103 -> -220770.33 | D104: =D102+D103 -> -767693.19 | E104: =E102+E103 -> -174807.95 | F104: =F102+F103 -> 706776.45 | G104: =G102+G103 -> 1348628.4 | H104: =H102+H103 -> 5153247.6 | I104: =I102+I103 -> 11804004 | J104: =IF(IFERROR((I104/F104)^(1/5)-1,"-")<0,"-",IFERROR((I104/F104)^(1/5)-1,"-")) -> 0.75610085
A105: (-) Change in WC | B105: =Settings!$C$6 -> USD | C105: =C89 -> 300000 | D105: =D89 -> 300000 | E105: =E89 -> 0 | F105: =F89 -> 0 | G105: =G89 -> 0 | H105: =H89 -> 0 | I105: =I89 -> 0 | J105: =IF(IFERROR((I105/F105)^(1/5)-1,"-")<0,"-",IFERROR((I105/F105)^(1/5)-1,"-")) -> -
A106: (-) CAPEX | B106: =Settings!$C$6 -> USD | C106: =C90 -> 0 | D106: =D90 -> 50000 | E106: =E90 -> 0 | F106: =F90 -> 0 | G106: =G90 -> 0 | H106: =H90 -> 0 | I106: =I90 -> 0 | J106: =IF(IFERROR((I106/F106)^(1/5)-1,"-")<0,"-",IFERROR((I106/F106)^(1/5)-1,"-")) -> -
A107: (+) Equity investment | B107: =Settings!$C$6 -> USD | C107: =C83 -> 0 | D107: =D83 -> 0 | E107: =E83 -> 0 | F107: =F83 -> 0 | G107: =G83 -> 0 | H107: =H83 -> 0 | I107: =I83 -> 0 | J107: =IF(IFERROR((I107/F107)^(1/5)-1,"-")<0,"-",IFERROR((I107/F107)^(1/5)-1,"-")) -> -
A108: (+) Debt | B108: =Settings!$C$6 -> USD | C108: =C68 -> 0 | D108: =D68-C68 -> 0 | E108: =E68-D68 -> 0 | F108: =F68-E68 -> 0 | G108: =G68-F68 -> 0 | H108: =H68-G68 -> 0 | I108: =I68-H68 -> 0 | J108: =IF(IFERROR((I108/F108)^(1/5)-1,"-")<0,"-",IFERROR((I108/F108)^(1/5)-1,"-")) -> -
A109: Free cash flow | B109: =Settings!$C$6 -> USD | C109: =C104+C105-C106+C107+C108 -> 79229.667 | D109: =D104+D105-D106+D107+D108 -> -517693.19 | E109: =E104+E105-E106+E107+E108 -> -174807.95 | F109: =F104+F105-F106+F107+F108 -> 706776.45 | G109: =G104+G105-G106+G107+G108 -> 1348628.4 | H109: =H104+H105-H106+H107+H108 -> 5153247.6 | I109: =I104+I105-I106+I107+I108 -> 11804004 | J109: =IF(IFERROR((I109/F109)^(1/5)-1,"-")<0,"-",IFERROR((I109/F109)^(1/5)-1,"-")) -> 0.75610085
A110: Exit value | B110: =Settings!$C$6 -> USD | I110: =IF(Settings!$C$20="xEBITDA",(I41*(Settings!$C$22))) -> 1.1804004e+08 | J110: =IF(IFERROR((I110/F110)^(1/5)-1,"-")<0,"-",IFERROR((I110/F110)^(1/5)-1,"-")) -> -
A111: Discounted cash flow | B111: =Settings!$C$6 -> USD | C111: =SUM(C109:C110) -> 79229.667 | D111: =SUM(D109:D110) -> -517693.19 | E111: =SUM(E109:E110) -> -174807.95 | F111: =SUM(F109:F110) -> 706776.45 | G111: =SUM(G109:G110) -> 1348628.4 | H111: =SUM(H109:H110) -> 5153247.6 | I111: =SUM(I109:I110) -> 1.2984404e+08 | J111: =IF(IFERROR((I111/F111)^(1/5)-1,"-")<0,"-",IFERROR((I111/F111)^(1/5)-1,"-")) -> 1.8367952

Sheet FS-Month
A1: =Settings!C5 -> VReeMind
A2: Financial Statement (Monthly)
A3: =+TODAY() -> 44143
C6: START | D6: =Settings!$C$7 -> 43466 | E6: =EDATE(D6,1) -> 43497 | F6: =EDATE(E6,1) -> 43525 | G6: =EDATE(F6,1) -> 43556 | H6: =EDATE(G6,1) -> 43586 | I6: =EDATE(H6,1) -> 43617 | J6: =EDATE(I6,1) -> 43647 | K6: =EDATE(J6,1) -> 43678 | L6: =EDATE(K6,1) -> 43709 | ... DG6: =EDATE(DF6,1) -> 46722
B7: Unit | D7: 1 | E7: =D7+1 -> 2 | F7: =E7+1 -> 3 | G7: =F7+1 -> 4 | H7: =G7+1 -> 5 | I7: =H7+1 -> 6 | J7: =I7+1 -> 7 | K7: =J7+1 -> 8 | L7: =K7+1 -> 9 | ... DG7: =DF7+1 -> 108
A9: KEY INDICATORS
A10: INCOME STATEMENT
Y11: =Y12=Revenue!Y21 -> TRUE | Z11: =Z12=Revenue!Z21 -> TRUE | AA11: =AA12=Revenue!AA21 -> TRUE | AB11: =AB12=Revenue!AB21 -> TRUE | AC11: =AC12=Revenue!AC21 -> TRUE | AD11: =AD12=Revenue!AD21 -> TRUE | AE11: =AE12=Revenue!AE21 -> TRUE | AF11: =AF12=Revenue!AF21 -> TRUE | ... DG11: =DG12=Revenue!DG21 -> TRUE
A12: Revenue | B12: =Settings!$C$6 -> USD | D12: =Revenue!D56 -> 0 | E12: =SUM(E13:E16) -> 0 | F12: =SUM(F13:F16) -> 0 | G12: =SUM(G13:G16) -> 0 | H12: =SUM(H13:H16) -> 0 | I12: =SUM(I13:I16) -> 0 | J12: =SUM(J13:J16) -> 0 | K12: =SUM(K13:K16) -> 0 | L12: =SUM(L13:L16) -> 0 | ... DG12: =SUM(DG13:DG16) -> 5861415.3
A13: =Revenue!A17 -> SOURCE #1: Self-Service Subscriptions | B13: =Settings!$C$6 -> USD | D13: =Revenue!D17 -> 0 | E13: =Revenue!E17 -> 0 | F13: =Revenue!F17 -> 0 | G13: =Revenue!G17 -> 0 | H13: =Revenue!H17 -> 0 | I13: =Revenue!I17 -> 0 | J13: =Revenue!J17 -> 0 | K13: =Revenue!K17 -> 0 | ... DG13: =Revenue!DG17 -> 5861415.3
A14: =Revenue!A18 -> SOURCE #2: Inbound Sales | B14: =Settings!$C$6 -> USD | D14: =Revenue!D18 -> 0 | E14: =Revenue!E18 -> 0 | F14: =Revenue!F18 -> 0 | G14: =Revenue!G18 -> 0 | H14: =Revenue!H18 -> 0 | I14: =Revenue!I18 -> 0 | J14: =Revenue!J18 -> 0 | K14: =Revenue!K18 -> 0 | ... DG14: =Revenue!DG18 -> 0
A15: =Revenue!A19 -> SOURCE #3: Outbound Sales | B15: =Settings!$C$6 -> USD | D15: =Revenue!D19 -> 0 | E15: =Revenue!E19 -> 0 | F15: =Revenue!F19 -> 0 | G15: =Revenue!G19 -> 0 | H15: =Revenue!H19 -> 0 | I15: =Revenue!I19 -> 0 | J15: =Revenue!J19 -> 0 | K15: =Revenue!K19 -> 0 | ... DG15: =Revenue!DG19 -> 0
A16: =Revenue!A20 -> Renewals | B16: =Settings!$C$6 -> USD | D16: =Revenue!D20 -> 0 | E16: =Revenue!E20 -> 0 | F16: =Revenue!F20 -> 0 | G16: =Revenue!G20 -> 0 | H16: =Revenue!H20 -> 0 | I16: =Revenue!I20 -> 0 | J16: =Revenue!J20 -> 0 | K16: =Revenue!K20 -> 0 | ... DG16: =Revenue!DG20 -> ERR
A18: COGS | B18: =Settings!$C$6 -> USD | D18: =SUM(D19:D21) -> 0 | E18: =SUM(E19:E21) -> 0 | F18: =SUM(F19:F21) -> 0 | G18: =SUM(G19:G21) -> 0 | H18: =SUM(H19:H21) -> 0 | I18: =SUM(I19:I21) -> 0 | J18: =SUM(J19:J21) -> 0 | K18: =SUM(K19:K21) -> 0 | ... DG18: =SUM(DG19:DG21) -> 1797470.1
A19: =COGS!A19 -> CATEGORY #1: Hosting/Customer Service | B19: =Settings!$C$6 -> USD | D19: =COGS!E19 -> 0 | E19: =COGS!F19 -> 0 | F19: =COGS!G19 -> 0 | G19: =COGS!H19 -> 0 | H19: =COGS!I19 -> 0 | I19: =COGS!J19 -> 0 | J19: =COGS!K19 -> 0 | K19: =COGS!L19 -> 0 | ... DG19: =COGS!DH19 -> 39045.523
A20: =COGS!A20 -> CATEGORY #2: Partnership Commissions | B20: =Settings!$C$6 -> USD | D20: =COGS!E20 -> 0 | E20: =COGS!F20 -> 0 | F20: =COGS!G20 -> 0 | G20: =COGS!H20 -> 0 | H20: =COGS!I20 -> 0 | I20: =COGS!J20 -> 0 | J20: =COGS!K20 -> 0 | K20: =COGS!L20 -> 0 | ... DG20: =COGS!DH20 -> 0
A21: =COGS!A21 -> CATEGORY #3: App Store Fees | B21: =Settings!$C$6 -> USD | D21: =COGS!E21 -> 0 | E21: =COGS!F21 -> 0 | F21: =COGS!G21 -> 0 | G21: =COGS!H21 -> 0 | H21: =COGS!I21 -> 0 | I21: =COGS!J21 -> 0 | J21: =COGS!K21 -> 0 | K21: =COGS!L21 -> 0 | ... DG21: =COGS!DH21 -> 1758424.6
A22: Gross Profit | B22: =Settings!$C$6 -> USD | D22: =D12-D18 -> 0 | E22: =E12-E18 -> 0 | F22: =F12-F18 -> 0 | G22: =G12-G18 -> 0 | H22: =H12-H18 -> 0 | I22: =I12-I18 -> 0 | J22: =J12-J18 -> 0 | K22: =K12-K18 -> 0 | ... DG22: =DG12-DG18 -> 4063945.2
A23: Gross margin | B23: % | D23: =IFERROR(D22/D$12,"-") -> - | E23: =IFERROR(E22/E$12,"-") -> - | F23: =IFERROR(F22/F$12,"-") -> - | G23: =IFERROR(G22/G$12,"-") -> - | H23: =IFERROR(H22/H$12,"-") -> - | I23: =IFERROR(I22/I$12,"-") -> - | J23: =IFERROR(J22/J$12,"-") -> - | K23: =IFERROR(K22/K$12,"-") -> - | ... DG23: =IFERROR(DG22/DG$12,"-") -> 0.69333855
A25: SG&A | B25: =Settings!$C$6 -> USD | D25: =SUM(D26:D33) -> 20458.333 | E25: =SUM(E26:E33) -> 6875 | F25: =SUM(F26:F33) -> 9875 | G25: =SUM(G26:G33) -> 21958.333 | H25: =SUM(H26:H33) -> 15958.333 | I25: =SUM(I26:I33) -> 16179.583 | J25: =SUM(J26:J33) -> 21500.5 | K25: =SUM(K26:K33) -> 18500.5 | ... DG25: =SUM(DG26:DG33) -> 219713.63
A26: ='SG&A'!A22 -> PAYROLL | B26: =Settings!$C$6 -> USD | D26: ='SG&A'!F22 -> 11458.333 | E26: ='SG&A'!G22 -> 6875 | F26: ='SG&A'!H22 -> 6875 | G26: ='SG&A'!I22 -> 11458.333 | H26: ='SG&A'!J22 -> 11458.333 | I26: ='SG&A'!K22 -> 11458.333 | J26: ='SG&A'!L22 -> 13750 | K26: ='SG&A'!M22 -> 13750 | ... DG26: ='SG&A'!DI22 -> 169176.13
A27: ='SG&A'!A23 -> MARKETING & GROWTH | B27: =Settings!$C$6 -> USD | D27: ='SG&A'!F23 -> 0 | E27: ='SG&A'!G23 -> 0 | F27: ='SG&A'!H23 -> 3000 | G27: ='SG&A'!I23 -> 3000 | H27: ='SG&A'!J23 -> 3000 | I27: ='SG&A'!K23 -> 3000 | J27: ='SG&A'!L23 -> 3000 | K27: ='SG&A'!M23 -> 3000 | ... DG27: ='SG&A'!DI23 -> 40000
A28: ='SG&A'!A24 -> LEGAL, ADVISORY, PROF. SERVICES | B28: =Settings!$C$6 -> USD | D28: ='SG&A'!F24 -> 0 | E28: ='SG&A'!G24 -> 0 | F28: ='SG&A'!H24 -> 0 | G28: ='SG&A'!I24 -> 1500 | H28: ='SG&A'!J24 -> 1500 | I28: ='SG&A'!K24 -> 1500 | J28: ='SG&A'!L24 -> 1500 | K28: ='SG&A'!M24 -> 1500 | ... DG28: ='SG&A'!DI24 -> 7000
A29: ='SG&A'!A25 -> WFA Stipend | B29: =Settings!$C$6 -> USD | D29: ='SG&A'!F25 -> 9000 | E29: ='SG&A'!G25 -> 0 | F29: ='SG&A'!H25 -> 0 | G29: ='SG&A'!I25 -> 6000 | H29: ='SG&A'!J25 -> 0 | I29: ='SG&A'!K25 -> 0 | J29: ='SG&A'!L25 -> 3000 | K29: ='SG&A'!M25 -> 0 | ... DG29: ='SG&A'!DI25 -> 0
A30: ='SG&A'!A26 -> TECH SUPPORT & SERVICES | B30: =Settings!$C$6 -> USD | D30: ='SG&A'!F26 -> 0 | E30: ='SG&A'!G26 -> 0 | F30: ='SG&A'!H26 -> 0 | G30: ='SG&A'!I26 -> 0 | H30: ='SG&A'!J26 -> 0 | I30: ='SG&A'!K26 -> 221.25 | J30: ='SG&A'!L26 -> 250.5 | K30: ='SG&A'!M26 -> 250.5 | ... DG30: ='SG&A'!DI26 -> 1537.5
A31: ='SG&A'!A27 -> INSURANCE | B31: =Settings!$C$6 -> USD | D31: ='SG&A'!F27 -> 0 | E31: ='SG&A'!G27 -> 0 | F31: ='SG&A'!H27 -> 0 | G31: ='SG&A'!I27 -> 0 | H31: ='SG&A'!J27 -> 0 | I31: ='SG&A'!K27 -> 0 | J31: ='SG&A'!L27 -> 0 | K31: ='SG&A'!M27 -> 0 | ... DG31: ='SG&A'!DI27 -> 2000
A32: ='SG&A'!A28 -> 0 | B32: =Settings!$C$6 -> USD | D32: ='SG&A'!F28 -> 0 | E32: ='SG&A'!G28 -> 0 | F32: ='SG&A'!H28 -> 0 | G32: ='SG&A'!I28 -> 0 | H32: ='SG&A'!J28 -> 0 | I32: ='SG&A'!K28 -> 0 | J32: ='SG&A'!L28 -> 0 | K32: ='SG&A'!M28 -> 0 | ... DG32: ='SG&A'!DI28 -> 0
A33: ='SG&A'!A29 -> OTHER EXPENSES | B33: =Settings!$C$6 -> USD | D33: ='SG&A'!F29 -> 0 | E33: ='SG&A'!G29 -> 0 | F33: ='SG&A'!H29 -> 0 | G33: ='SG&A'!I29 -> 0 | H33: ='SG&A'!J29 -> 0 | I33: ='SG&A'!K29 -> 0 | J33: ='SG&A'!L29 -> 0 | K33: ='SG&A'!M29 -> 0 | ... DG33: ='SG&A'!DI29 -> 0
A34: EBITDA | B34: =Settings!$C$6 -> USD | D34: =D22-D25 -> -20458.333 | E34: =E22-E25 -> -6875 | F34: =F22-F25 -> -9875 | G34: =G22-G25 -> -21958.333 | H34: =H22-H25 -> -15958.333 | I34: =I22-I25 -> -16179.583 | J34: =J22-J25 -> -21500.5 | K34: =K22-K25 -> -18500.5 | ... DG34: =DG22-DG25 -> 3844231.5
A35: EBITDA margin | B35: % | D35: =IFERROR(MAX((D34/D$12),0),"-") -> - | E35: =IFERROR(MAX((E34/E$12),0),"-") -> - | F35: =IFERROR(MAX((F34/F$12),0),"-") -> - | G35: =IFERROR(MAX((G34/G$12),0),"-") -> - | H35: =IFERROR(MAX((H34/H$12),0),"-") -> - | I35: =IFERROR(MAX((I34/I$12),0),"-") -> - | J35: =IFERROR(MAX((J34/J$12),0),"-") -> - | K35: =IFERROR(MAX((K34/K$12),0),"-") -> - | ... DG35: =IFERROR(MAX((DG34/DG$12),0),"-") -> 0.65585381
A37: D&A | B37: =Settings!$C$6 -> USD | D37: ='WK+CAPEX'!D77 -> 0 | E37: ='WK+CAPEX'!E77 -> 0 | F37: ='WK+CAPEX'!F77 -> 0 | G37: ='WK+CAPEX'!G77 -> 0 | H37: ='WK+CAPEX'!H77 -> 0 | I37: ='WK+CAPEX'!I77 -> 0 | J37: ='WK+CAPEX'!J77 -> 0 | K37: ='WK+CAPEX'!K77 -> 0 | ... AH37: ='WK+CAPEX'!AH77 -> 0 | AI37: 0 | AJ37: 0 | AK37: 0 | AL37: 0 | AM37: 0 | AN37: 0 | AO37: 0 | AP37: 0 | AQ37: 0 | AR37: 0 | AS37: 0 | AT37: 0 | AU37: 0 | AV37: 0 | AW37: 0 | AX37: 0 | AY37: 0 | AZ37: 0 | BA37: 0 | BB37: 0 | BC37: 0 | BD37: 0 | BE37: 0 | BF37: 0 | BG37: 0 | BH37: 0 | BI37: 0 | BJ37: 0 | BK37: 0 | BL37: 0 | BM37: 0 | BN37: 0 | BO37: 0 | BP37: 0 | BQ37: 0 | BR37: 0 | BS37: 0 | BT37: 0 | BU37: 0 | BV37: 0 | BW37: 0 | BX37: 0 | BY37: 0 | BZ37: 0 | CA37: 0 | CB37: 0 | CC37: 0 | CD37: 0 | CE37: 0 | CF37: 0 | CG37: 0 | CH37: 0 | CI37: 0 | CJ37: 0 | CK37: 0 | CL37: 0 | CM37: 0 | CN37: 0 | CO37: 0 | CP37: 0 | CQ37: 0 | CR37: 0 | CS37: 0 | CT37: 0 | CU37: 0 | CV37: 0 | CW37: 0 | CX37: 0 | CY37: 0 | CZ37: 0 | DA37: 0 | DB37: 0 | DC37: 0 | DD37: 0 | DE37: 0 | DF37: 0 | DG37: 0
A38: EBIT | B38: =Settings!$C$6 -> USD | D38: =D34-D37 -> -20458.333 | E38: =E34-E37 -> -6875 | F38: =F34-F37 -> -9875 | G38: =G34-G37 -> -21958.333 | H38: =H34-H37 -> -15958.333 | I38: =I34-I37 -> -16179.583 | J38: =J34-J37 -> -21500.5 | K38: =K34-K37 -> -18500.5 | ... DG38: =DG34-DG37 -> 3844231.5
A39: EBIT margin | E39: =IFERROR(MAX((E38/E$12),0),"-") -> - | F39: =IFERROR(MAX((F38/F$12),0),"-") -> - | G39: =IFERROR(MAX((G38/G$12),0),"-") -> - | H39: =IFERROR(MAX((H38/H$12),0),"-") -> - | I39: =IFERROR(MAX((I38/I$12),0),"-") -> - | J39: =IFERROR(MAX((J38/J$12),0),"-") -> - | K39: =IFERROR(MAX((K38/K$12),0),"-") -> - | L39: =IFERROR(MAX((L38/L$12),0),"-") -> - | ... DG39: =IFERROR(MAX((DG38/DG$12),0),"-") -> 0.65585381
A41: Interest expense | B41: =Settings!$C$6 -> USD | D41: =D63*(Settings!$C$24/12) -> 0 | E41: =E63*(Settings!$C$24/12) -> 0 | F41: =F63*(Settings!$C$24/12) -> 0 | G41: =G63*(Settings!$C$24/12) -> 0 | H41: =H63*(Settings!$C$24/12) -> 0 | I41: =I63*(Settings!$C$24/12) -> 0 | J41: =J63*(Settings!$C$24/12) -> 0 | K41: =K63*(Settings!$C$24/12) -> 0 | ... DG41: =DG63*(Settings!$C$24/12) -> 0
A42: Income taxes | B42: =Settings!$C$6 -> USD | D42: =IF(D38>0,D38*Settings!$C$16,"0") -> 0 | E42: =IF(E38>0,E38*Settings!$C$16,"0") -> 0 | F42: =IF(F38>0,F38*Settings!$C$16,"0") -> 0 | G42: =IF(G38>0,G38*Settings!$C$16,"0") -> 0 | H42: =IF(H38>0,H38*Settings!$C$16,"0") -> 0 | I42: =IF(I38>0,I38*Settings!$C$16,"0") -> 0 | J42: =IF(J38>0,J38*Settings!$C$16,"0") -> 0 | K42: =IF(K38>0,K38*Settings!$C$16,"0") -> 0 | ... DG42: =IF(DG38>0,DG38*Settings!$C$16,"0") -> 0
A43: Net income | B43: =Settings!$C$6 -> USD | D43: =D38-D41-D42 -> -20458.333 | E43: =E38-E41-E42 -> -6875 | F43: =F38-F41-F42 -> -9875 | G43: =G38-G41-G42 -> -21958.333 | H43: =H38-H41-H42 -> -15958.333 | I43: =I38-I41-I42 -> -16179.583 | J43: =J38-J41-J42 -> -21500.5 | K43: =K38-K41-K42 -> -18500.5 | ... DG43: =DG38-DG41-DG42 -> 3844231.5
A44: Net margin | D44: =IFERROR(MAX((D43/D$12),0),"-") -> - | E44: =IFERROR(MAX((E43/E$12),0),"-") -> - | F44: =IFERROR(MAX((F43/F$12),0),"-") -> - | G44: =IFERROR(MAX((G43/G$12),0),"-") -> - | H44: =IFERROR(MAX((H43/H$12),0),"-") -> - | I44: =IFERROR(MAX((I43/I$12),0),"-") -> - | J44: =IFERROR(MAX((J43/J$12),0),"-") -> - | K44: =IFERROR(MAX((K43/K$12),0),"-") -> - | ... DG44: =IFERROR(MAX((DG43/DG$12),0),"-") -> 0.65585381
A47: BALANCE SHEET
A49: Operating cash | B49: =[1]Settings!$C$6 -> USD | C49: 100000 | D49: =C49+D82 -> 79541.667 | E49: =D49+E82 -> 72666.667 | F49: =E49+F82 -> 62791.667 | G49: =F49+G82 -> 40833.333 | H49: =G49+H82 -> 24875 | I49: =H49+I82 -> 8695.4167 | J49: =I49+J82 -> 287194.92 | K49: =J49+K82 -> 268694.42 | ... DG49: =DF49+DG82 -> 79282433
A50: Prepaid expenses | B50: =[1]Settings!$C$6 -> USD | D50: 0 | E50: 0 | F50: 0 | G50: 0 | H50: 0 | I50: 0 | J50: 0 | K50: 0 | L50: 0 | M50: 0 | N50: 0 | O50: 0 | P50: 0 | Q50: 0 | R50: 0 | S50: 0 | T50: 0 | U50: 0 | V50: 0 | W50: 0 | X50: 0 | Y50: 0 | Z50: 0 | AA50: 0 | AB50: 0 | AC50: 0 | AD50: 0 | AE50: 0 | AF50: 0 | AG50: 0 | AH50: 0 | AI50: 0 | AJ50: 0 | AK50: 0 | AL50: 0 | AM50: 0 | AN50: 0 | AO50: 0 | AP50: 0 | AQ50: 0 | AR50: 0 | AS50: 0 | AT50: 0 | AU50: 0 | AV50: 0 | AW50: 0 | AX50: 0 | AY50: 0 | AZ50: 0
A51: Current Assets | B51: =[1]Settings!$C$6 -> USD | C51: =SUM(C49:C50) -> 100000 | D51: =SUM(D49:D50) -> 79541.667 | E51: =SUM(E49:E50) -> 72666.667 | F51: =SUM(F49:F50) -> 62791.667 | G51: =SUM(G49:G50) -> 40833.333 | H51: =SUM(H49:H50) -> 24875 | I51: =SUM(I49:I50) -> 8695.4167 | J51: =SUM(J49:J50) -> 287194.92 | ... DG51: =SUM(DG49:DG50) -> 79282433
A53: PP&E (net) | B53: =[1]Settings!$C$6 -> USD
A54: Intangible assets | B54: =[1]Settings!$C$6 -> USD | V54: 50000 | W54: 50000 | X54: 50000 | Y54: 50000 | Z54: 50000 | AA54: 50000 | AB54: 50000 | AC54: 50000 | AD54: 50000 | AE54: 50000 | AF54: 50000 | AG54: 50000 | AH54: 50000 | AI54: 50000 | AJ54: 50000 | AK54: 50000 | AL54: 50000 | AM54: 50000 | AN54: 50000 | AO54: 50000 | AP54: 50000 | AQ54: 50000 | AR54: 50000 | AS54: 50000 | AT54: 50000 | AU54: 50000 | AV54: 50000 | AW54: 50000 | AX54: 50000 | AY54: 50000 | AZ54: 50000 | BA54: 50000 | BB54: 50000 | BC54: 50000 | BD54: 50000 | BE54: 50000 | BF54: 50000 | BG54: 50000 | BH54: 50000 | BI54: 50000 | BJ54: 50000 | BK54: 50000 | BL54: 50000 | BM54: 50000 | BN54: 50000 | BO54: 50000 | BP54: 50000 | BQ54: 50000 | BR54: 50000 | BS54: 50000 | BT54: 50000 | BU54: 50000 | BV54: 50000 | BW54: 50000 | BX54: 50000 | BY54: 50000 | BZ54: 50000 | CA54: 50000 | CB54: 50000 | CC54: 50000 | CD54: 50000 | CE54: 50000 | CF54: 50000 | CG54: 50000 | CH54: 50000 | CI54: 50000 | CJ54: 50000 | CK54: 50000 | CL54: 50000 | CM54: 50000 | CN54: 50000 | CO54: 50000 | CP54: 50000 | CQ54: 50000 | CR54: 50000 | CS54: 50000 | CT54: 50000 | CU54: 50000 | CV54: 50000 | CW54: 50000 | CX54: 50000 | CY54: 50000 | CZ54: 50000 | DA54: 50000 | DB54: 50000 | DC54: 50000 | DD54: 50000 | DE54: 50000 | DF54: 50000 | DG54: 50000
A55: Investments | B55: =[1]Settings!$C$6 -> USD
A56: Other assets (net) | B56: =[1]Settings!$C$6 -> USD
A57: Non-Current Assets | B57: =[1]Settings!$C$6 -> USD | D57: =SUM(D53:D56) -> 0 | E57: =SUM(E53:E56) -> 0 | F57: =SUM(F53:F56) -> 0 | G57: =SUM(G53:G56) -> 0 | H57: =SUM(H53:H56) -> 0 | I57: =SUM(I53:I56) -> 0 | J57: =SUM(J53:J56) -> 0 | K57: =SUM(K53:K56) -> 0 | ... U57: =SUM(U53:U56) -> 0 | V57: 50000 | W57: 50000 | X57: 50000 | Y57: 50000 | Z57: 50000 | AA57: 50000 | AB57: 50000 | AC57: 50000 | AD57: 50000 | AE57: 50000 | AF57: 50000 | AG57: 50000 | AH57: 50000 | AI57: 50000 | AJ57: 50000 | AK57: 50000 | AL57: 50000 | AM57: 50000 | AN57: 50000 | AO57: 50000 | AP57: 50000 | AQ57: 50000 | AR57: 50000 | AS57: 50000 | AT57: 50000 | AU57: 50000 | AV57: 50000 | AW57: 50000 | AX57: 50000 | AY57: 50000 | AZ57: 50000 | BA57: 50000 | BB57: 50000 | BC57: 50000 | BD57: 50000 | BE57: 50000 | BF57: 50000 | BG57: 50000 | BH57: 50000 | BI57: 50000 | BJ57: 50000 | BK57: 50000 | BL57: 50000 | BM57: 50000 | BN57: 50000 | BO57: 50000 | BP57: 50000 | BQ57: 50000 | BR57: 50000 | BS57: 50000 | BT57: 50000 | BU57: 50000 | BV57: 50000 | BW57: 50000 | BX57: 50000 | BY57: 50000 | BZ57: 50000 | CA57: 50000 | CB57: 50000 | CC57: 50000 | CD57: 50000 | CE57: 50000 | CF57: 50000 | CG57: 50000 | CH57: 50000 | CI57: 50000 | CJ57: 50000 | CK57: 50000 | CL57: 50000 | CM57: 50000 | CN57: 50000 | CO57: 50000 | CP57: 50000 | CQ57: 50000 | CR57: 50000 | CS57: 50000 | CT57: 50000 | CU57: 50000 | CV57: 50000 | CW57: 50000 | CX57: 50000 | CY57: 50000 | CZ57: 50000 | DA57: 50000 | DB57: 50000 | DC57: 50000 | DD57: 50000 | DE57: 50000 | DF57: 50000 | DG57: 50000
B58: =[1]Settings!$C$6 -> USD
A59: Total Assets | B59: =[1]Settings!$C$6 -> USD | D59: =SUM(D51,D57) -> 79541.667 | E59: =SUM(E51,E57) -> 72666.667 | F59: =SUM(F51,F57) -> 62791.667 | G59: =SUM(G51,G57) -> 40833.333 | H59: =SUM(H51,H57) -> 24875 | I59: =SUM(I51,I57) -> 8695.4167 | J59: =SUM(J51,J57) -> 287194.92 | K59: =SUM(K51,K57) -> 268694.42 | ... DG59: =SUM(DG51,DG57) -> 79332433
B60: =[1]Settings!$C$6 -> USD
A61: Financial obligations (Debt) | B61: =[1]Settings!$C$6 -> USD | D61: 0 | E61: =D61+E77/(1-[1]Settings!$C$23)-E77 -> 0 | F61: =E61+F77/(1-[1]Settings!$C$23)-F77 -> 0 | G61: =F61+G77/(1-[1]Settings!$C$23)-G77 -> 0 | H61: =G61+H77/(1-[1]Settings!$C$23)-H77 -> 0 | I61: =H61+I77/(1-[1]Settings!$C$23)-I77 -> 0 | J61: =I61+J77/(1-[1]Settings!$C$23)-J77 -> 0 | K61: =J61+K77/(1-[1]Settings!$C$23)-K77 -> 0 | L61: =K61+L77/(1-[1]Settings!$C$23)-L77 -> 0 | ... DG61: =DF61+DG77/(1-[1]Settings!$C$23)-DG77 -> 0
A62: Accounts payable | B62: =[1]Settings!$C$6 -> USD | BA62: ='[1]WK+CAPEX'!BA33 -> 0 | BB62: ='[1]WK+CAPEX'!BB33 -> 0 | BC62: ='[1]WK+CAPEX'!BC33 -> 0 | BD62: ='[1]WK+CAPEX'!BD33 -> 0 | BE62: ='[1]WK+CAPEX'!BE33 -> 0 | BF62: ='[1]WK+CAPEX'!BF33 -> 0 | BG62: ='[1]WK+CAPEX'!BG33 -> 0 | BH62: ='[1]WK+CAPEX'!BH33 -> 0 | ... DG62: ='[1]WK+CAPEX'!DG33 -> 0
A63: Provisions | B63: =[1]Settings!$C$6 -> USD
A64: Deferred Revenue | B64: =[1]Settings!$C$6 -> USD | D64: =DEFERRED!J16 -> 0 | E64: =DEFERRED!K16 -> 0 | F64: =DEFERRED!L16 -> 0 | G64: =DEFERRED!M16 -> 0 | H64: =DEFERRED!N16 -> 0 | I64: =DEFERRED!O16 -> 0 | J64: =DEFERRED!P16 -> 0 | K64: =DEFERRED!Q16 -> 0 | ... DG64: =DEFERRED!DM16 -> 29600978
A65: Total Liabilities | B65: =[1]Settings!$C$6 -> USD | D65: =SUM(D61:D64) -> 0 | E65: =SUM(E61:E64) -> 0 | F65: =SUM(F61:F64) -> 0 | G65: =SUM(G61:G64) -> 0 | H65: =SUM(H61:H64) -> 0 | I65: =SUM(I61:I64) -> 0 | J65: =SUM(J61:J64) -> 0 | K65: =SUM(K61:K64) -> 0 | ... DG65: =SUM(DG61:DG64) -> 29600978
B66: =[1]Settings!$C$6 -> USD
A67: Common equity | B67: =[1]Settings!$C$6 -> USD | C67: 100000 | D67: =C79+D85 -> 100000 | E67: =D67+E85 -> 100000 | F67: =E67+F85 -> 100000 | G67: =F67+G85 -> 100000 | H67: =G67+H85 -> 100000 | I67: =H67+I85 -> 100000 | J67: =I67+J85 -> 400000 | K67: =J67+K85 -> 400000 | L67: =K67+L85 -> 400000 | ... DG67: =DF67+DG85 -> 700000
A68: Net Income (Loss) | B68: =[1]Settings!$C$6 -> USD | D68: =D43 -> -20458.333 | E68: =E43 -> -6875 | F68: =F43 -> -9875 | G68: =G43 -> -21958.333 | H68: =H43 -> -15958.333 | I68: =I43 -> -16179.583 | J68: =J43 -> -21500.5 | K68: =K43 -> -18500.5 | ... DG68: =DG43 -> 3844231.5
A69: Retained Earnings | B69: =[1]Settings!$C$6 -> USD | D69: =SUM(C68:C69)-D88 -> 0 | E69: =SUM($D$68:E68) -> -27333.333 | F69: =SUM($D$68:F68) -> -37208.333 | G69: =SUM($D$68:G68) -> -59166.667 | H69: =SUM($D$68:H68) -> -75125 | I69: =SUM($D$68:I68) -> -91304.583 | J69: =SUM($D$68:J68) -> -112805.08 | K69: =SUM($D$68:K68) -> -131305.58 | L69: =SUM($D$68:L68) -> -149806.08 | ... DG69: =SUM($D$68:DG68) -> 49031454
A70: Total Equity | B70: =[1]Settings!$C$6 -> USD | C70: 100000 | D70: =D67+D68+D69 -> 79541.667 | E70: =E67+E69 -> 72666.667 | F70: =F67+F69 -> 62791.667 | G70: =G67+G69 -> 40833.333 | H70: =H67+H69 -> 24875 | I70: =I67+I69 -> 8695.4167 | J70: =J67+J69 -> 287194.92 | K70: =K67+K69 -> 268694.42 | L70: =L67+L69 -> 250193.92 | ... DG70: =DG67+DG69 -> 49731454
B71: =[1]Settings!$C$6 -> USD
A72: Total Liabilities + Equity | B72: =[1]Settings!$C$6 -> USD | D72: =SUM(D65,D70) -> 79541.667 | E72: =SUM(E65,E70) -> 72666.667 | F72: =SUM(F65,F70) -> 62791.667 | G72: =SUM(G65,G70) -> 40833.333 | H72: =SUM(H65,H70) -> 24875 | I72: =SUM(I65,I70) -> 8695.4167 | J72: =SUM(J65,J70) -> 287194.92 | K72: =SUM(K65,K70) -> 268694.42 | ... DG72: =SUM(DG65,DG70) -> 79332433
A73: Check | D73: =D72-D59 -> 0 | E73: =E72-E59 -> 0 | F73: =F72-F59 -> 0 | G73: =G72-G59 -> 0 | H73: =H72-H59 -> 0 | I73: =I72-I59 -> 0 | J73: =J72-J59 -> 0 | K73: =K72-K59 -> 0 | ... DG73: =DG72-DG59 -> 0
A76: CASH FLOW
A78: Initial cash balance | B78: =Settings!$C$6 -> USD | D78: 100000 | E78: =D89 -> 79541.667 | F78: =E89 -> 72666.667 | G78: =F89 -> 62791.667 | H78: =G89 -> 40833.333 | I78: =H89 -> 24875 | J78: =I89 -> 8695.4167 | K78: =J89 -> 287194.92 | L78: =K89 -> 268694.42 | ... DG78: =DF89 -> 81299616
A79: Cash infusions/Cash from Sales | B79: =Settings!$C$6 -> USD | C79: 100000 | D79: 0 | E79: 0 | F79: 0 | G79: 0 | H79: 0 | I79: 0 | J79: 0 | K79: 0 | L79: 0 | M79: 0 | N79: 0 | O79: 0 | P79: 0 | Q79: 0 | R79: 0 | S79: 0 | T79: 0 | U79: 0 | V79: 0 | W79: 0 | X79: 0 | Y79: 0 | Z79: 0 | AA79: 0 | AB79: 0 | AC79: 0 | AD79: 0 | AE79: 0 | AF79: 0 | AG79: 0 | AH79: 0 | AI79: 0 | AJ79: 0 | AK79: 0 | AL79: 0 | AM79: 0 | AN79: 0 | AO79: 0 | AP79: 0 | AQ79: 0 | AR79: 0 | AS79: 0 | AT79: 0 | AU79: 0 | AV79: 0 | AW79: 0 | AX79: 0 | AY79: 0 | AZ79: 0 | BA79: 0 | BB79: 0 | BC79: 0 | BD79: 0 | BE79: 0 | BF79: 0 | BG79: 0 | BH79: 0 | BI79: 0 | BJ79: 0 | BK79: 0 | BL79: 0 | BM79: 0 | BN79: 0 | BO79: 0 | BP79: 0 | BQ79: 0 | BR79: 0 | BS79: 0 | BT79: 0 | BU79: 0 | BV79: 0 | BW79: 0 | BX79: 0 | BY79: 0 | BZ79: 0 | CA79: 0 | CB79: 0 | CC79: 0 | CD79: 0 | CE79: 0 | CF79: 0 | CG79: 0 | CH79: 0 | CI79: 0 | CJ79: 0 | CK79: 0 | CL79: 0 | CM79: 0 | CN79: 0 | CO79: 0 | CP79: 0 | CQ79: 0 | CR79: 0 | CS79: 0 | CT79: 0 | CU79: 0 | CV79: 0 | CW79: 0 | CX79: 0 | CY79: 0 | CZ79: 0 | DA79: 0 | DB79: 0 | DC79: 0 | DD79: 0 | DE79: 0 | DF79: 0 | DG79: 0
A80: Cash from Sales | B80: =Settings!$C$6 -> USD | D80: =DEFERRED!J12 -> 0 | E80: =DEFERRED!K12 -> 0 | F80: =DEFERRED!L12 -> 0 | G80: =DEFERRED!M12 -> 0 | H80: =DEFERRED!N12 -> 0 | I80: =DEFERRED!O12 -> 0 | J80: =DEFERRED!P12 -> 0 | K80: =DEFERRED!Q12 -> 0 | ... U80: =DEFERRED!AA12 -> 0 | W80: =DEFERRED!AC12 -> 0 | X80: =DEFERRED!AD12 -> 0 | Y80: =DEFERRED!AE12 -> 828000 | Z80: =DEFERRED!AF12 -> 0 | AA80: =DEFERRED!AG12 -> 0 | AB80: =DEFERRED!AH12 -> 1092000 | AC80: =DEFERRED!AI12 -> 0 | AD80: =DEFERRED!AJ12 -> 0 | ... DG80: =DEFERRED!DM12 -> 0
A81: Investor Cash | B81: =Settings!$C$6 -> USD | D81: =IF(D$6=Projections!$C$4,Projections!$C$5,0) -> 0 | E81: =IF(E$6=Projections!$C$4,Projections!$C$5,0) -> 0 | F81: =IF(F$6=Projections!$C$4,Projections!$C$5,0) -> 0 | G81: =IF(G$6=Projections!$C$4,Projections!$C$5,0) -> 0 | H81: =IF(H$6=Projections!$C$4,Projections!$C$5,0) -> 0 | I81: =IF(I$6=Projections!$C$4,Projections!$C$5,0) -> 0 | J81: =IF(J$6=Projections!$C$4,Projections!$C$5,0) -> 0 | K81: =IF(K$6=Projections!$C$4,Projections!$C$5,0) -> 0 | L81: =IF(L$6=Projections!$C$4,Projections!$C$5,0) -> 0 | M81: 0 | N81: =IF(N$6=Projections!$C$4,Projections!$C$5,0) -> 0 | O81: =IF(O$6=Projections!$C$4,Projections!$C$5,0) -> 0 | P81: =IF(P$6=Projections!$C$4,Projections!$C$5,0) -> 0 | Q81: 0 | R81: =IF(R$6=Projections!$C$4,Projections!$C$5,0) -> 0 | S81: =IF(S$6=Projections!$C$4,Projections!$C$5,0) -> 0 | T81: =IF(T$6=Projections!$C$4,Projections!$C$5,0) -> 0 | U81: =IF(U$6=Projections!$C$4,Projections!$C$5,0) -> 0 | W81: =IF(W$6=Projections!$C$4,Projections!$C$5,0) -> 0 | X81: =IF(X$6=Projections!$C$4,Projections!$C$5,0) -> 0 | Y81: =IF(Y$6=Projections!$C$4,Projections!$C$5,0) -> 0 | Z81: =IF(Z$6=Projections!$C$4,Projections!$C$5,0) -> 0 | AA81: =IF(AA$6=Projections!$C$4,Projections!$C$5,0) -> 0 | AB81: 0 | AC81: 0 | AD81: 0 | AE81: 0 | AF81: 0 | AG81: 0 | AH81: 0 | AI81: 0 | AJ81: 0 | AK81: 0 | AL81: 0 | AM81: 0 | AN81: 0 | AO81: 0 | AP81: 0 | AQ81: 0 | AR81: 0 | AS81: 0 | AT81: 0 | AU81: 0 | AV81: 0 | AW81: 0 | AX81: 0 | AY81: 0 | AZ81: 0 | BA81: 0 | BB81: 0 | BC81: 0 | BD81: 0 | BE81: 0 | BF81: 0 | BG81: 0 | BH81: 0 | BI81: 0 | BJ81: 0 | BK81: 0 | BL81: 0 | BM81: 0 | BN81: 0 | BO81: 0 | BP81: 0 | BQ81: 0 | BR81: 0 | BS81: 0 | BT81: 0 | BU81: 0 | BV81: 0 | BW81: 0 | BX81: 0 | BY81: 0 | BZ81: 0 | CA81: 0 | CB81: 0 | CC81: 0 | CD81: 0 | CE81: 0 | CF81: 0 | CG81: 0 | CH81: 0 | CI81: 0 | CJ81: 0 | CK81: 0 | CL81: 0 | CM81: 0 | CN81: 0 | CO81: 0 | CP81: 0 | CQ81: 0 | CR81: 0 | CS81: 0 | CT81: 0 | CU81: 0 | CV81: 0 | CW81: 0 | CX81: 0 | CY81: 0 | CZ81: 0 | DA81: 0 | DB81: 0 | DC81: 0 | DD81: 0 | DE81: 0 | DF81: 0 | DG81: 0
A82: Operating change in cash | B82: =Settings!$C$6 -> USD | D82: =SUM(D83:D88) -> -20458.333 | E82: =SUM(E83:E88) -> -6875 | F82: =SUM(F83:F88) -> -9875 | G82: =SUM(G83:G88) -> -21958.333 | H82: =SUM(H83:H88) -> -15958.333 | I82: =SUM(I83:I88) -> -16179.583 | J82: =SUM(J83:J88) -> 278499.5 | K82: =SUM(K83:K88) -> -18500.5 | ... N82: =SUM(N83:N88) -> -20821.417 | O82: =O83+O84+O85-O86+O87-O88 -> -26321.417 | P82: =SUM(P83:P88) -> -40838.25 | Q82: =SUM(Q83:Q88) -> -52759.417 | R82: =SUM(R83:R88) -> 259240.58 | S82: =SUM(S83:S88) -> -47455.333 | T82: =T83+T84+T85-T86+T87-T88 -> -44455.333 | U82: =U83+U84+U85-U86+U87-U88 -> -94455.333 | V82: =V83+V84+V85-V86+V87-V88 -> -94455.333 | W82: =W83+W84+W85-W86+W87-W88 -> -44455.333 | X82: =X83+X84+X85-X86+X87-X88 -> -44455.333 | Y82: =Y83+Y84+Y85-Y86+Y87-Y88 -> 450933.52 | Z82: =Z83+Z84+Z85-Z86+Z87-Z88 -> -68472.511 | AA82: =AA83+AA84+AA85-AA86+AA87-AA88 -> -76766.484 | ... DG82: =DG83+DG84+DG85-DG86+DG87-DG88 -> -2017183.7
A83: Net income | B83: =Settings!$C$6 -> USD | D83: =D43 -> -20458.333 | E83: =E43 -> -6875 | F83: =F43 -> -9875 | G83: =G43 -> -21958.333 | H83: =H43 -> -15958.333 | I83: =I43 -> -16179.583 | J83: =J43 -> -21500.5 | K83: =K43 -> -18500.5 | ... DG83: =DG43 -> 3844231.5
A84: (+) D&A | B84: =Settings!$C$6 -> USD | D84: =D37 -> 0 | E84: =E37 -> 0 | F84: =F37 -> 0 | G84: =G37 -> 0 | H84: =H37 -> 0 | I84: =I37 -> 0 | J84: =J37 -> 0 | K84: =K37 -> 0 | ... DG84: =DG37 -> 0
A85: (+) Change in WC | B85: =Settings!$C$6 -> USD | D85: =DEFERRED!J16 -> 0 | E85: =DEFERRED!K16 -> 0 | F85: =DEFERRED!L16 -> 0 | G85: =DEFERRED!M16 -> 0 | H85: =DEFERRED!N16 -> 0 | I85: =DEFERRED!O16 -> 0 | J85: 300000 | K85: =DEFERRED!Q16 -> 0 | L85: 0 | M85: =DEFERRED!S16 -> 0 | N85: =DEFERRED!T16 -> 0 | O85: =DEFERRED!U16 -> 0 | P85: 0 | Q85: 0 | R85: 300000 | S85: 0 | T85: 0 | V85: 0 | W85: 0 | X85: 0 | Y85: 0 | Z85: 0 | AA85: 0 | AB85: 0 | AC85: 0 | AD85: 0 | AE85: 0 | AF85: 0 | AG85: 0 | AH85: 0 | AI85: 0 | AJ85: 0 | AK85: 0 | AL85: 0 | AM85: 0 | AN85: 0 | AO85: 0 | AP85: 0 | AQ85: 0 | AR85: 0 | AS85: 0 | AT85: 0 | AU85: 0 | AV85: 0 | AW85: 0 | AX85: 0 | AY85: 0 | AZ85: 0 | BA85: 0 | BB85: 0 | BC85: 0 | BD85: 0 | BE85: 0 | BF85: 0 | BG85: 0 | BH85: 0 | BI85: 0 | BJ85: 0 | BK85: 0 | BL85: 0 | BM85: 0 | BN85: 0 | BO85: 0 | BP85: 0 | BQ85: 0 | BR85: 0 | BS85: 0 | BT85: 0 | BU85: 0 | BV85: 0 | BW85: 0 | BX85: 0 | BY85: 0 | BZ85: 0 | CA85: 0 | CB85: 0 | CC85: 0 | CD85: 0 | CE85: 0 | CF85: 0 | CG85: 0 | CH85: 0 | CI85: 0 | CJ85: 0 | CK85: 0 | CL85: 0 | CM85: 0 | CN85: 0 | CO85: 0 | CP85: 0 | CQ85: 0 | CR85: 0 | CS85: 0 | CT85: 0 | CU85: 0 | CV85: 0 | CW85: 0 | CX85: 0 | CY85: 0 | CZ85: 0 | DA85: 0 | DB85: 0 | DC85: 0 | DD85: 0 | DE85: 0 | DF85: 0 | DG85: 0
A86: (+) Change in intangible assets | B86: =Settings!$C$6 -> USD | D86: 0 | E86: 0 | F86: 0 | G86: 0 | H86: 0 | I86: 0 | J86: 0 | K86: 0 | L86: 0 | M86: 0 | N86: 0 | O86: 0 | P86: 0 | Q86: 0 | R86: 0 | S86: 0 | T86: 0 | U86: 0 | V86: 50000 | W86: 0 | X86: 0 | Y86: 0 | Z86: 0 | AA86: 0 | AB86: 0 | AC86: 0 | AD86: 0 | AE86: 0 | AF86: 0 | AG86: 0 | AH86: 0 | AI86: 0 | AJ86: 0 | AK86: 0 | AL86: 0 | AM86: 0 | AN86: 0 | AO86: 0 | AP86: 0 | AQ86: 0 | AR86: 0 | AS86: 0 | AT86: 0 | AU86: 0 | AV86: 0 | AW86: 0 | AX86: 0 | AY86: 0 | AZ86: 0 | BA86: 0 | BB86: 0 | BC86: 0 | BD86: 0 | BE86: 0 | BF86: 0 | BG86: 0 | BH86: 0 | BI86: 0 | BJ86: 0 | BK86: 0 | BL86: 0 | BM86: 0 | BN86: 0 | BO86: 0 | BP86: 0 | BQ86: 0 | BR86: 0 | BS86: 0 | BT86: 0 | BU86: 0 | BV86: 0 | BW86: 0 | BX86: 0 | BY86: 0 | BZ86: 0 | CA86: 0 | CB86: 0 | CC86: 0 | CD86: 0 | CE86: 0 | CF86: 0 | CG86: 0 | CH86: 0 | CI86: 0 | CJ86: 0 | CK86: 0 | CL86: 0 | CM86: 0 | CN86: 0 | CO86: 0 | CP86: 0 | CQ86: 0 | CR86: 0 | CS86: 0 | CT86: 0 | CU86: 0 | CV86: 0 | CW86: 0 | CX86: 0 | CY86: 0 | CZ86: 0 | DA86: 0 | DB86: 0 | DC86: 0 | DD86: 0 | DE86: 0 | DF86: 0 | DG86: 0
A87: (+) Change in debt | B87: =Settings!$C$6 -> USD | D87: 0 | E87: =E65-D65 -> 0 | F87: =F65-E65 -> 0 | G87: =G65-F65 -> 0 | H87: =H65-G65 -> 0 | I87: =I65-H65 -> 0 | J87: =J65-I65 -> 0 | K87: =K65-J65 -> 0 | L87: =L65-K65 -> 0 | ... DG87: =DG65-DF65 -> -5861415.3
A88: (-) Dividends | B88: =Settings!$C$6 -> USD | D88: 0 | E88: 0 | F88: 0 | G88: 0 | H88: 0 | I88: 0 | J88: 0 | K88: 0 | L88: 0 | M88: 0 | N88: 0 | O88: 0 | P88: 0 | Q88: 0 | R88: 0 | S88: 0 | T88: 0 | U88: 0
A89: Ending cash balance | B89: =Settings!$C$6 -> USD | D89: =SUM(D78,D82) -> 79541.667 | E89: =SUM(E78,E82) -> 72666.667 | F89: =SUM(F78,F82) -> 62791.667 | G89: =SUM(G78,G82) -> 40833.333 | H89: =SUM(H78,H82) -> 24875 | I89: =SUM(I78,I82) -> 8695.4167 | J89: =SUM(J78,J82) -> 287194.92 | K89: =SUM(K78,K82) -> 268694.42 | ... DG89: =SUM(DG78,DG82) -> 79282433
A90: Total capital requirements | B90: =Settings!$C$6 -> USD | D90: =MIN(D89:DG89) -> -24859.417
E91: =SUM($D$86:E86) -> 0 | F91: =SUM($D$86:F86) -> 0 | G91: =SUM($D$86:G86) -> 0 | H91: =SUM($D$86:H86) -> 0 | I91: =SUM($D$86:I86) -> 0 | J91: =SUM($D$86:J86) -> 0 | K91: =SUM($D$86:K86) -> 0 | L91: =SUM($D$86:L86) -> 0 | ... DG91: =SUM($D$86:DG86) -> 50000
E92: =SUM($D$85:E85) -> 0 | F92: =SUM($D$85:F85) -> 0 | G92: =SUM($D$85:G85) -> 0 | H92: =SUM($D$85:H85) -> 0 | I92: =SUM($D$85:I85) -> 0 | J92: =SUM($D$85:J85) -> 300000 | K92: =SUM($D$85:K85) -> 300000 | L92: =SUM($D$85:L85) -> 300000 | ... DG92: =SUM($D$85:DG85) -> 600000
E93: =SUM($D$83:E84) -> -27333.333 | F93: =SUM($D$83:F84) -> -37208.333 | G93: =SUM($D$83:G84) -> -59166.667 | H93: =SUM($D$83:H84) -> -75125 | I93: =SUM($D$83:I84) -> -91304.583 | J93: =SUM($D$83:J84) -> -112805.08 | K93: =SUM($D$83:K84) -> -131305.58 | L93: =SUM($D$83:L84) -> -149806.08 | ... DG93: =SUM($D$83:DG84) -> 49031454
A96: VALUATION
A98: EBIT | B98: =Settings!$C$6 -> USD | D98: =D38 -> -20458.333 | E98: =E38 -> -6875 | F98: =F38 -> -9875 | G98: =G38 -> -21958.333 | H98: =H38 -> -15958.333 | I98: =I38 -> -16179.583 | J98: =J38 -> -21500.5 | K98: =K38 -> -18500.5 | ... DG98: =DG38 -> 3844231.5
A99: (-) Taxes | B99: =Settings!$C$6 -> USD | D99: =D42 -> 0 | E99: =E42 -> 0 | F99: =F42 -> 0 | G99: =G42 -> 0 | H99: =H42 -> 0 | I99: =I42 -> 0 | J99: =J42 -> 0 | K99: =K42 -> 0 | ... DG99: =DG42 -> 0
A100: EBIAT | B100: =Settings!$C$6 -> USD | D100: =D98-D99 -> -20458.333 | E100: =E98-E99 -> -6875 | F100: =F98-F99 -> -9875 | G100: =G98-G99 -> -21958.333 | H100: =H98-H99 -> -15958.333 | I100: =I98-I99 -> -16179.583 | J100: =J98-J99 -> -21500.5 | K100: =K98-K99 -> -18500.5 | ... DG100: =DG98-DG99 -> 3844231.5
A101: (+) D&A | B101: =Settings!$C$6 -> USD | D101: =D37 -> 0 | E101: =E37 -> 0 | F101: =F37 -> 0 | G101: =G37 -> 0 | H101: =H37 -> 0 | I101: =I37 -> 0 | J101: =J37 -> 0 | K101: =K37 -> 0 | ... DG101: =DG37 -> 0
A102: Gross cash flow | B102: =Settings!$C$6 -> USD | D102: =D100+D101 -> -20458.333 | E102: =E100+E101 -> -6875 | F102: =F100+F101 -> -9875 | G102: =G100+G101 -> -21958.333 | H102: =H100+H101 -> -15958.333 | I102: =I100+I101 -> -16179.583 | J102: =J100+J101 -> -21500.5 | K102: =K100+K101 -> -18500.5 | ... DG102: =DG100+DG101 -> 3844231.5
A103: (-) Change in WC | B103: =Settings!$C$6 -> USD | D103: =D85 -> 0 | E103: =E85 -> 0 | F103: =F85 -> 0 | G103: =G85 -> 0 | H103: =H85 -> 0 | I103: =I85 -> 0 | J103: =J85 -> 300000 | K103: =K85 -> 0 | ... DG103: =DG85 -> 0
A104: (-) CAPEX | B104: =Settings!$C$6 -> USD | D104: =D86 -> 0 | E104: =E86 -> 0 | F104: =F86 -> 0 | G104: =G86 -> 0 | H104: =H86 -> 0 | I104: =I86 -> 0 | J104: =J86 -> 0 | K104: =K86 -> 0 | ... DG104: =DG86 -> 0
A105: Free cash flow | B105: =Settings!$C$6 -> USD | D105: =D102+D103-D104 -> -20458.333 | E105: =E102+E103-E104 -> -6875 | F105: =F102+F103-F104 -> -9875 | G105: =G102+G103-G104 -> -21958.333 | H105: =H102+H103-H104 -> -15958.333 | I105: =I102+I103-I104 -> -16179.583 | J105: =J102+J103-J104 -> 278499.5 | K105: =K102+K103-K104 -> -18500.5 | ... DG105: =DG102+DG103-DG104 -> 3844231.5

Sheet Revenue
A1: =Settings!C5 -> VReeMind
A2: Revenue
A3: =+TODAY() -> 44143
D6: ='FS-Month'!D6 -> 43466 | E6: ='FS-Month'!E6 -> 43497 | F6: ='FS-Month'!F6 -> 43525 | G6: ='FS-Month'!G6 -> 43556 | H6: ='FS-Month'!H6 -> 43586 | I6: ='FS-Month'!I6 -> 43617 | J6: ='FS-Month'!J6 -> 43647 | K6: ='FS-Month'!K6 -> 43678 | ... DG6: ='FS-Month'!DG6 -> 46722
C7: Unit | D7: ='FS-Month'!D7 -> 1 | E7: ='FS-Month'!E7 -> 2 | F7: ='FS-Month'!F7 -> 3 | G7: ='FS-Month'!G7 -> 4 | H7: ='FS-Month'!H7 -> 5 | I7: ='FS-Month'!I7 -> 6 | J7: ='FS-Month'!J7 -> 7 | K7: ='FS-Month'!K7 -> 8 | ... DG7: ='FS-Month'!DG7 -> 108
A8: KEY INDICATORS
A9: =DEFERRED!A10 -> 2020 | B9: =DEFERRED!B10 -> 276
A10: =DEFERRED!A11 -> 2021 | B10: =DEFERRED!B11 -> 312
A11: =DEFERRED!A12 -> 2022 | B11: =DEFERRED!B12 -> 312
A12: =DEFERRED!A13 -> 2023 | B12: =DEFERRED!B13 -> 324
A13: =DEFERRED!A14 -> 2024 | B13: =DEFERRED!B14 -> 372
A14: =DEFERRED!A15 -> 2025 | B14: =DEFERRED!B15 -> 384
A15: CONSOLIDATED REVENUE
A17: =A26 -> SOURCE #1: Self-Service Subscriptions | C17: =Settings!$C$6 -> USD | D17: =DEFERRED!J14 -> 0 | E17: =DEFERRED!K14 -> 0 | F17: =DEFERRED!L14 -> 0 | G17: =DEFERRED!M14 -> 0 | H17: =DEFERRED!N14 -> 0 | I17: =DEFERRED!O14 -> 0 | J17: =DEFERRED!P14 -> 0 | K17: =DEFERRED!Q14 -> 0 | ... DG17: =DEFERRED!DM14 -> 5861415.3
A18: =A58 -> SOURCE #2: Inbound Sales | C18: =Settings!$C$6 -> USD | D18: =D119 -> 0 | E18: =E119 -> 0 | F18: =F119 -> 0 | G18: =G119 -> 0 | H18: =H119 -> 0 | I18: =I119 -> 0 | J18: =J119 -> 0 | K18: =K119 -> 0 | ... BK18: =BK119 -> 0
A19: =A122 -> SOURCE #3: Outbound Sales | C19: =Settings!$C$6 -> USD | D19: =D170 -> 0 | E19: =E170 -> 0 | F19: =F170 -> 0 | G19: =G170 -> 0 | H19: =H170 -> 0 | I19: =I170 -> 0 | J19: =J170 -> 0 | K19: =K170 -> 0 | ... BK19: =BK170 -> 0
A20: Renewals | C20: =Settings!$C$6 -> USD | D20: =D188 -> 0 | E20: =E188 -> 0 | F20: =F188 -> 0 | G20: =G188 -> 0 | H20: =H188 -> 0 | I20: =I188 -> 0 | J20: =J188 -> 0 | K20: =K188 -> 0 | ... AJ20: =AJ188 -> 0 | AK20: =IF(YEAR(AK$6)=$A10,AK32*$B10,IF(YEAR(AK$6)=$A11,AK32*$B11,IF(YEAR(AK$6)=$A12,AK32*$B12,IF(YEAR(AK$6)=$A13,AK32*$B13,IF(YEAR(AK$6)=$A14,AK32*$B14,"ERR"))))) -> 280800 | AL20: =IF(YEAR(AL$6)=$A10,AL32*$B10,IF(YEAR(AL$6)=$A11,AL32*$B11,IF(YEAR(AL$6)=$A12,AL32*$B12,IF(YEAR(AL$6)=$A13,AL32*$B13,IF(YEAR(AL$6)=$A14,AL32*$B14,"ERR"))))) -> 0 | AM20: =IF(YEAR(AM$6)=$A10,AM32*$B10,IF(YEAR(AM$6)=$A11,AM32*$B11,IF(YEAR(AM$6)=$A12,AM32*$B12,IF(YEAR(AM$6)=$A13,AM32*$B13,IF(YEAR(AM$6)=$A14,AM32*$B14,"ERR"))))) -> 0 | AN20: =IF(YEAR(AN$6)=$A10,AN32*$B10,IF(YEAR(AN$6)=$A11,AN32*$B11,IF(YEAR(AN$6)=$A12,AN32*$B12,IF(YEAR(AN$6)=$A13,AN32*$B13,IF(YEAR(AN$6)=$A14,AN32*$B14,"ERR"))))) -> 327600 | AO20: =IF(YEAR(AO$6)=$A10,AO32*$B10,IF(YEAR(AO$6)=$A11,AO32*$B11,IF(YEAR(AO$6)=$A12,AO32*$B12,IF(YEAR(AO$6)=$A13,AO32*$B13,IF(YEAR(AO$6)=$A14,AO32*$B14,"ERR"))))) -> 0 | AP20: =IF(YEAR(AP$6)=$A10,AP32*$B10,IF(YEAR(AP$6)=$A11,AP32*$B11,IF(YEAR(AP$6)=$A12,AP32*$B12,IF(YEAR(AP$6)=$A13,AP32*$B13,IF(YEAR(AP$6)=$A14,AP32*$B14,"ERR"))))) -> 0 | AQ20: =IF(YEAR(AQ$6)=$A10,AQ32*$B10,IF(YEAR(AQ$6)=$A11,AQ32*$B11,IF(YEAR(AQ$6)=$A12,AQ32*$B12,IF(YEAR(AQ$6)=$A13,AQ32*$B13,IF(YEAR(AQ$6)=$A14,AQ32*$B14,"ERR"))))) -> 327600 | AR20: =IF(YEAR(AR$6)=$A10,AR32*$B10,IF(YEAR(AR$6)=$A11,AR32*$B11,IF(YEAR(AR$6)=$A12,AR32*$B12,IF(YEAR(AR$6)=$A13,AR32*$B13,IF(YEAR(AR$6)=$A14,AR32*$B14,"ERR"))))) -> 0 | ... DG20: =IF(YEAR(DG$6)=$A10,DG32*$B10,IF(YEAR(DG$6)=$A11,DG32*$B11,IF(YEAR(DG$6)=$A12,DG32*$B12,IF(YEAR(DG$6)=$A13,DG32*$B13,IF(YEAR(DG$6)=$A14,DG32*$B14,"ERR"))))) -> ERR
A21: TOTAL | C21: =Settings!$C$6 -> USD | D21: =SUM(D17:D20) -> 0 | E21: =SUM(E17:E20) -> 0 | F21: =SUM(F17:F20) -> 0 | G21: =SUM(G17:G20) -> 0 | H21: =SUM(H17:H20) -> 0 | I21: =SUM(I17:I20) -> 0 | J21: =SUM(J17:J20) -> 0 | K21: =SUM(K17:K20) -> 0 | ... DG21: =SUM(DG17:DG20) -> 5861415.3
A26: =Projections!A30 -> SOURCE #1: Self-Service Subscriptions | C26: =Projections!$C$30 -> Enabled
A27: Annual Billing Model
A28: Churn Rate | C28: % | D28: =Projections!$C$38 -> 0.7 | E28: =Projections!$C$38 -> 0.7 | F28: =Projections!$C$38 -> 0.7 | G28: =Projections!$C$38 -> 0.7 | H28: =Projections!$C$38 -> 0.7 | I28: =Projections!$C$38 -> 0.7 | J28: =Projections!$C$38 -> 0.7 | K28: =Projections!$C$38 -> 0.7 | ... DF28: =Projections!$C$38 -> 0.7
A30: Subscribers
A31: New Customers | C31: # | D31: 0 | E31: 0 | F31: 0 | G31: 0 | H31: 0 | I31: 0 | J31: 0 | K31: 0 | L31: 0 | M31: 0 | N31: 0 | O31: 0 | P31: 0 | Q31: 0 | R31: 0 | S31: 0 | T31: 0 | U31: 0 | V31: 0 | W31: 0 | X31: 0 | Y31: 3000 | Z31: 0 | AA31: 0 | AB31: 3500 | AC31: 0 | AD31: 0 | AE31: 3500 | AF31: 0 | AG31: 0 | AH31: 4000 | AI31: 0 | AJ31: 0 | AK31: 4100 | AL31: 0 | AM31: 0 | AN31: 5000 | AO31: 0 | AP31: 0 | AQ31: 5300 | AR31: 0 | AS31: 0 | AT31: 5250 | AU31: 0 | AV31: 0 | AW31: 5250 | AX31: 0 | AY31: 0 | AZ31: 7500 | BB31: 0 | BC31: 7500 | BD31: 0 | BE31: 0 | BF31: 9280 | BG31: 0 | BH31: 0 | BI31: 9000 | BJ31: 0 | BK31: 0 | BL31: 10000 | BM31: 0 | BN31: 0 | BO31: 13500 | BP31: 0 | BQ31: 0 | BR31: 15000 | BS31: 0 | BT31: 0 | BU31: 14750 | BV31: 0 | BW31: 0 | BX31: 20000 | BY31: 0 | BZ31: 0 | CA31: 22000 | CB31: 0 | CC31: 0 | CD31: 22000 | CE31: 0 | CF31: 0 | CG31: 21200 | CH31: 0 | CI31: 0 | CJ31: 35000 | CK31: 0 | CL31: 0 | CM31: 35000 | CN31: 0 | CO31: 0 | CP31: 35000 | CQ31: 0 | CR31: 0 | CS31: 35000 | CT31: 0 | CU31: 0 | CV31: 33480.345 | CW31: 0 | CX31: 0 | CY31: 40176.414 | CZ31: 0 | DA31: 0 | DB31: 48211.697 | DC31: 0 | DD31: 0 | DE31: 57854.037 | DF31: 0 | DG31: 0
A32: Renewing Customers | C32: # | D32: =SUM(D37:D41) -> 0 | E32: =SUM(E37:E41) -> 0 | F32: =SUM(F37:F41) -> 0 | G32: =SUM(G37:G41) -> 0 | H32: =SUM(H37:H41) -> 0 | I32: =SUM(I37:I41) -> 0 | J32: =SUM(J37:J41) -> 0 | K32: =SUM(K37:K41) -> 0 | ... AJ32: =SUM(AJ37:AJ41) -> 0 | AK32: =SUM(AK37:AK43) -> 900 | AL32: =SUM(AL37:AL43) -> 0 | AM32: =SUM(AM37:AM43) -> 0 | AN32: =SUM(AN37:AN43) -> 1050 | AO32: =SUM(AO37:AO43) -> 0 | AP32: =SUM(AP37:AP43) -> 0 | AQ32: =SUM(AQ37:AQ43) -> 1050 | AR32: =SUM(AR37:AR43) -> 0 | ... DF32: =SUM(DF37:DF43) -> 0
A33: Total Active Customers | C33: # | D33: =D31-D32 -> 0 | E33: =E31-E32 -> 0 | F33: =F31-F32 -> 0 | G33: =G31-G32 -> 0 | H33: =H31-H32 -> 0 | I33: =I31-I32 -> 0 | J33: =J31-J32 -> 0 | K33: =K31-K32 -> 0 | ... O33: =O31-O32 -> 0 | P33: =IF(P$7<=12,SUM($D31:P31),SUM(E31:P32)) -> 0 | Q33: =IF(Q$7<=12,SUM($D31:Q31),SUM(F31:Q32)) -> 0 | R33: =IF(R$7<=12,SUM($D31:R31),SUM(G31:R32)) -> 0 | S33: =IF(S$7<=12,SUM($D31:S31),SUM(H31:S32)) -> 0 | T33: =IF(T$7<=12,SUM($D31:T31),SUM(I31:T32)) -> 0 | U33: =IF(U$7<=12,SUM($D31:U31),SUM(J31:U32)) -> 0 | V33: =IF(V$7<=12,SUM($D31:V31),SUM(K31:V32)) -> 0 | W33: =IF(W$7<=12,SUM($D31:W31),SUM(L31:W32)) -> 0 | ... DF33: =IF(DF$7<=12,SUM($D31:DF31),SUM(CU31:DF32)) -> 189162.49
A35: Cohorts
A36: Renewing Customers
A37: =YEAR(D$6) -> 2019 | C37: # | D37: =IF(YEAR(D$6)=$A37,"",IF(YEAR(D$6)=($A37+1),ROUND(#REF!*(1-D$28),0),ROUND(#REF!*(1-D$28),0))) | E37: =IF(YEAR(E$6)=$A37,"",IF(YEAR(E$6)=($A37+1),ROUND(#REF!*(1-E$28),0),ROUND(#REF!*(1-E$28),0))) | F37: =IF(YEAR(F$6)=$A37,"",IF(YEAR(F$6)=($A37+1),ROUND(#REF!*(1-F$28),0),ROUND(#REF!*(1-F$28),0))) | G37: =IF(YEAR(G$6)=$A37,"",IF(YEAR(G$6)=($A37+1),ROUND(#REF!*(1-G$28),0),ROUND(#REF!*(1-G$28),0))) | H37: =IF(YEAR(H$6)=$A37,"",IF(YEAR(H$6)=($A37+1),ROUND(#REF!*(1-H$28),0),ROUND(#REF!*(1-H$28),0))) | I37: =IF(YEAR(I$6)=$A37,"",IF(YEAR(I$6)=($A37+1),ROUND(#REF!*(1-I$28),0),ROUND(#REF!*(1-I$28),0))) | J37: =IF(YEAR(J$6)=$A37,"",IF(YEAR(J$6)=($A37+1),ROUND(#REF!*(1-J$28),0),ROUND(#REF!*(1-J$28),0))) | K37: =IF(YEAR(K$6)=$A37,"",IF(YEAR(K$6)=($A37+1),ROUND(#REF!*(1-K$28),0),ROUND(#REF!*(1-K$28),0))) | L37: =IF(YEAR(L$6)=$A37,"",IF(YEAR(L$6)=($A37+1),ROUND(#REF!*(1-L$28),0),ROUND(#REF!*(1-L$28),0))) | M37: =IF(YEAR(M$6)=$A37,"",IF(YEAR(M$6)=($A37+1),ROUND(A$31*(1-M$28),0),ROUND(A37*(1-M$28),0))) | N37: =IF(YEAR(N$6)=$A37,"",IF(YEAR(N$6)=($A37+1),ROUND(B$31*(1-N$28),0),ROUND(B37*(1-N$28),0))) | O37: =IF(YEAR(O$6)=$A37,"",IF(YEAR(O$6)=($A37+1),ROUND(C$31*(1-O$28),0),ROUND(C37*(1-O$28),0))) | P37: =IF(YEAR(P$6)=$A37,"",IF(YEAR(P$6)=($A37+1),ROUND(D$31*(1-P$28),0),ROUND(D37*(1-P$28),0))) -> 0 | Q37: =IF(YEAR(Q$6)=$A37,"",IF(YEAR(Q$6)=($A37+1),ROUND(E$31*(1-Q$28),0),ROUND(E37*(1-Q$28),0))) -> 0 | R37: =IF(YEAR(R$6)=$A37,"",IF(YEAR(R$6)=($A37+1),ROUND(F$31*(1-R$28),0),ROUND(F37*(1-R$28),0))) -> 0 | S37: =IF(YEAR(S$6)=$A37,"",IF(YEAR(S$6)=($A37+1),ROUND(G$31*(1-S$28),0),ROUND(G37*(1-S$28),0))) -> 0 | T37: =IF(YEAR(T$6)=$A37,"",IF(YEAR(T$6)=($A37+1),ROUND(H$31*(1-T$28),0),ROUND(H37*(1-T$28),0))) -> 0 | ... DF37: =IF(YEAR(DF$6)=$A37,"",IF(YEAR(DF$6)=($A37+1),ROUND(CT$31*(1-DF$28),0),ROUND(CT37*(1-DF$28),0))) -> 0
A38: =YEAR(P$6) -> 2020 | C38: # | P38: =IF(YEAR(P$6)=$A38,"",IF(YEAR(P$6)=($A38+1),ROUND(D$31*(1-P$28),0),ROUND(D38*(1-P$28),0))) | Q38: =IF(YEAR(Q$6)=$A38,"",IF(YEAR(Q$6)=($A38+1),ROUND(E$31*(1-Q$28),0),ROUND(E38*(1-Q$28),0))) | R38: =IF(YEAR(R$6)=$A38,"",IF(YEAR(R$6)=($A38+1),ROUND(F$31*(1-R$28),0),ROUND(F38*(1-R$28),0))) | S38: =IF(YEAR(S$6)=$A38,"",IF(YEAR(S$6)=($A38+1),ROUND(G$31*(1-S$28),0),ROUND(G38*(1-S$28),0))) | T38: =IF(YEAR(T$6)=$A38,"",IF(YEAR(T$6)=($A38+1),ROUND(H$31*(1-T$28),0),ROUND(H38*(1-T$28),0))) | U38: =IF(YEAR(U$6)=$A38,"",IF(YEAR(U$6)=($A38+1),ROUND(I$31*(1-U$28),0),ROUND(I38*(1-U$28),0))) | V38: =IF(YEAR(V$6)=$A38,"",IF(YEAR(V$6)=($A38+1),ROUND(J$31*(1-V$28),0),ROUND(J38*(1-V$28),0))) | W38: =IF(YEAR(W$6)=$A38,"",IF(YEAR(W$6)=($A38+1),ROUND(K$31*(1-W$28),0),ROUND(K38*(1-W$28),0))) | ... DF38: =IF(YEAR(DF$6)=$A38,"",IF(YEAR(DF$6)=($A38+1),ROUND(CT$31*(1-DF$28),0),ROUND(CT38*(1-DF$28),0))) -> 0
A39: =YEAR(AB$6) -> 2021 | C39: # | P39: =IF(YEAR(P$6)=$A39,"",IF(YEAR(P$6)=($A39+1),ROUND(D$31*(1-P$28),0),ROUND(D39*(1-P$28),0))) -> 0 | Q39: =IF(YEAR(Q$6)=$A39,"",IF(YEAR(Q$6)=($A39+1),ROUND(E$31*(1-Q$28),0),ROUND(E39*(1-Q$28),0))) -> 0 | R39: =IF(YEAR(R$6)=$A39,"",IF(YEAR(R$6)=($A39+1),ROUND(F$31*(1-R$28),0),ROUND(F39*(1-R$28),0))) -> 0 | S39: =IF(YEAR(S$6)=$A39,"",IF(YEAR(S$6)=($A39+1),ROUND(G$31*(1-S$28),0),ROUND(G39*(1-S$28),0))) -> 0 | T39: =IF(YEAR(T$6)=$A39,"",IF(YEAR(T$6)=($A39+1),ROUND(H$31*(1-T$28),0),ROUND(H39*(1-T$28),0))) -> 0 | U39: =IF(YEAR(U$6)=$A39,"",IF(YEAR(U$6)=($A39+1),ROUND(I$31*(1-U$28),0),ROUND(I39*(1-U$28),0))) -> 0 | V39: =IF(YEAR(V$6)=$A39,"",IF(YEAR(V$6)=($A39+1),ROUND(J$31*(1-V$28),0),ROUND(J39*(1-V$28),0))) -> 0 | W39: =IF(YEAR(W$6)=$A39,"",IF(YEAR(W$6)=($A39+1),ROUND(K$31*(1-W$28),0),ROUND(K39*(1-W$28),0))) -> 0 | ... DF39: =IF(YEAR(DF$6)=$A39,"",IF(YEAR(DF$6)=($A39+1),ROUND(CT$31*(1-DF$28),0),ROUND(CT39*(1-DF$28),0))) -> 0
A40: =YEAR(AN$6) -> 2022 | C40: # | P40: =IF(YEAR(P$6)=$A40,"",IF(YEAR(P$6)=($A40+1),ROUND(D$31*(1-P$28),0),ROUND(D40*(1-P$28),0))) -> 0 | Q40: =IF(YEAR(Q$6)=$A40,"",IF(YEAR(Q$6)=($A40+1),ROUND(E$31*(1-Q$28),0),ROUND(E40*(1-Q$28),0))) -> 0 | R40: =IF(YEAR(R$6)=$A40,"",IF(YEAR(R$6)=($A40+1),ROUND(F$31*(1-R$28),0),ROUND(F40*(1-R$28),0))) -> 0 | S40: =IF(YEAR(S$6)=$A40,"",IF(YEAR(S$6)=($A40+1),ROUND(G$31*(1-S$28),0),ROUND(G40*(1-S$28),0))) -> 0 | T40: =IF(YEAR(T$6)=$A40,"",IF(YEAR(T$6)=($A40+1),ROUND(H$31*(1-T$28),0),ROUND(H40*(1-T$28),0))) -> 0 | U40: =IF(YEAR(U$6)=$A40,"",IF(YEAR(U$6)=($A40+1),ROUND(I$31*(1-U$28),0),ROUND(I40*(1-U$28),0))) -> 0 | V40: =IF(YEAR(V$6)=$A40,"",IF(YEAR(V$6)=($A40+1),ROUND(J$31*(1-V$28),0),ROUND(J40*(1-V$28),0))) -> 0 | W40: =IF(YEAR(W$6)=$A40,"",IF(YEAR(W$6)=($A40+1),ROUND(K$31*(1-W$28),0),ROUND(K40*(1-W$28),0))) -> 0 | ... DF40: =IF(YEAR(DF$6)=$A40,"",IF(YEAR(DF$6)=($A40+1),ROUND(CT$31*(1-DF$28),0),ROUND(CT40*(1-DF$28),0))) -> 0
A41: =YEAR(AZ$6) -> 2023 | C41: # | P41: =IF(YEAR(P$6)=$A41,"",IF(YEAR(P$6)=($A41+1),ROUND(D$31*(1-P$28),0),ROUND(D41*(1-P$28),0))) -> 0 | Q41: =IF(YEAR(Q$6)=$A41,"",IF(YEAR(Q$6)=($A41+1),ROUND(E$31*(1-Q$28),0),ROUND(E41*(1-Q$28),0))) -> 0 | R41: =IF(YEAR(R$6)=$A41,"",IF(YEAR(R$6)=($A41+1),ROUND(F$31*(1-R$28),0),ROUND(F41*(1-R$28),0))) -> 0 | S41: =IF(YEAR(S$6)=$A41,"",IF(YEAR(S$6)=($A41+1),ROUND(G$31*(1-S$28),0),ROUND(G41*(1-S$28),0))) -> 0 | T41: =IF(YEAR(T$6)=$A41,"",IF(YEAR(T$6)=($A41+1),ROUND(H$31*(1-T$28),0),ROUND(H41*(1-T$28),0))) -> 0 | U41: =IF(YEAR(U$6)=$A41,"",IF(YEAR(U$6)=($A41+1),ROUND(I$31*(1-U$28),0),ROUND(I41*(1-U$28),0))) -> 0 | V41: =IF(YEAR(V$6)=$A41,"",IF(YEAR(V$6)=($A41+1),ROUND(J$31*(1-V$28),0),ROUND(J41*(1-V$28),0))) -> 0 | W41: =IF(YEAR(W$6)=$A41,"",IF(YEAR(W$6)=($A41+1),ROUND(K$31*(1-W$28),0),ROUND(K41*(1-W$28),0))) -> 0 | ... DF41: =IF(YEAR(DF$6)=$A41,"",IF(YEAR(DF$6)=($A41+1),ROUND(CT$31*(1-DF$28),0),ROUND(CT41*(1-DF$28),0))) -> 0
A42: =YEAR(BL$6) -> 2024 | C42: # | P42: =IF(YEAR(P$6)=$A42,"",IF(YEAR(P$6)=($A42+1),ROUND(D$31*(1-P$28),0),ROUND(D42*(1-P$28),0))) -> 0 | Q42: =IF(YEAR(Q$6)=$A42,"",IF(YEAR(Q$6)=($A42+1),ROUND(E$31*(1-Q$28),0),ROUND(E42*(1-Q$28),0))) -> 0 | R42: =IF(YEAR(R$6)=$A42,"",IF(YEAR(R$6)=($A42+1),ROUND(F$31*(1-R$28),0),ROUND(F42*(1-R$28),0))) -> 0 | S42: =IF(YEAR(S$6)=$A42,"",IF(YEAR(S$6)=($A42+1),ROUND(G$31*(1-S$28),0),ROUND(G42*(1-S$28),0))) -> 0 | T42: =IF(YEAR(T$6)=$A42,"",IF(YEAR(T$6)=($A42+1),ROUND(H$31*(1-T$28),0),ROUND(H42*(1-T$28),0))) -> 0 | U42: =IF(YEAR(U$6)=$A42,"",IF(YEAR(U$6)=($A42+1),ROUND(I$31*(1-U$28),0),ROUND(I42*(1-U$28),0))) -> 0 | V42: =IF(YEAR(V$6)=$A42,"",IF(YEAR(V$6)=($A42+1),ROUND(J$31*(1-V$28),0),ROUND(J42*(1-V$28),0))) -> 0 | W42: =IF(YEAR(W$6)=$A42,"",IF(YEAR(W$6)=($A42+1),ROUND(K$31*(1-W$28),0),ROUND(K42*(1-W$28),0))) -> 0 | ... DF42: =IF(YEAR(DF$6)=$A42,"",IF(YEAR(DF$6)=($A42+1),ROUND(CT$31*(1-DF$28),0),ROUND(CT42*(1-DF$28),0))) -> 0
A43: =YEAR(BX$6) -> 2025 | C43: # | P43: =IF(YEAR(P$6)=$A43,"",IF(YEAR(P$6)=($A43+1),ROUND(D$31*(1-P$28),0),ROUND(D43*(1-P$28),0))) -> 0 | Q43: =IF(YEAR(Q$6)=$A43,"",IF(YEAR(Q$6)=($A43+1),ROUND(E$31*(1-Q$28),0),ROUND(E43*(1-Q$28),0))) -> 0 | R43: =IF(YEAR(R$6)=$A43,"",IF(YEAR(R$6)=($A43+1),ROUND(F$31*(1-R$28),0),ROUND(F43*(1-R$28),0))) -> 0 | S43: =IF(YEAR(S$6)=$A43,"",IF(YEAR(S$6)=($A43+1),ROUND(G$31*(1-S$28),0),ROUND(G43*(1-S$28),0))) -> 0 | T43: =IF(YEAR(T$6)=$A43,"",IF(YEAR(T$6)=($A43+1),ROUND(H$31*(1-T$28),0),ROUND(H43*(1-T$28),0))) -> 0 | U43: =IF(YEAR(U$6)=$A43,"",IF(YEAR(U$6)=($A43+1),ROUND(I$31*(1-U$28),0),ROUND(I43*(1-U$28),0))) -> 0 | V43: =IF(YEAR(V$6)=$A43,"",IF(YEAR(V$6)=($A43+1),ROUND(J$31*(1-V$28),0),ROUND(J43*(1-V$28),0))) -> 0 | W43: =IF(YEAR(W$6)=$A43,"",IF(YEAR(W$6)=($A43+1),ROUND(K$31*(1-W$28),0),ROUND(K43*(1-W$28),0))) -> 0 | ... DF43: =IF(YEAR(DF$6)=$A43,"",IF(YEAR(DF$6)=($A43+1),ROUND(CT$31*(1-DF$28),0),ROUND(CT43*(1-DF$28),0))) -> 0
A45: Annual Billing Summary
A46: New MRR | C46: =Settings!$C$6 -> USD | D46: =D31*Projections!$C$36 -> 0 | E46: =E31*Projections!$C$36 -> 0 | F46: =F31*Projections!$C$36 -> 0 | G46: =G31*Projections!$C$36 -> 0 | H46: =H31*Projections!$C$36 -> 0 | I46: =I31*Projections!$C$36 -> 0 | J46: =J31*Projections!$C$36 -> 0 | K46: =K31*Projections!$C$36 -> 0 | ... DF46: =DF31*Projections!$C$36 -> 0
A47: Renewing MRR | C47: =Settings!$C$6 -> USD | D47: =D32*Projections!$C$36 -> 0 | E47: =E32*Projections!$C$36 -> 0 | F47: =F32*Projections!$C$36 -> 0 | G47: =G32*Projections!$C$36 -> 0 | H47: =H32*Projections!$C$36 -> 0 | I47: =I32*Projections!$C$36 -> 0 | J47: =J32*Projections!$C$36 -> 0 | K47: =K32*Projections!$C$36 -> 0 | ... DF47: =DF32*Projections!$C$36 -> 0
A51: Totals
A52: LTV Subscribed this Month | C52: =Settings!$C$6 -> USD
A55: Monthly Revenue | C55: =Settings!$C$6 -> USD | D55: =D17 -> 0 | E55: =E17 -> 0 | F55: =F17 -> 0 | G55: =G17 -> 0 | H55: =H17 -> 0 | I55: =I17 -> 0 | J55: =J17 -> 0 | K55: =K17 -> 0 | ... BK55: =BK17 -> 915792.66
A56: Total Revenue | O56: =SUM(D55:O55) -> 0 | P56: =SUM(E55:P55) -> 0 | Q56: =SUM(F55:Q55) -> 0 | R56: =SUM(G55:R55) -> 0 | S56: =SUM(H55:S55) -> 0 | T56: =SUM(I55:T55) -> 0 | U56: =SUM(J55:U55) -> 0 | V56: =SUM(K55:V55) -> 0 | ... BK56: =SUM(AZ55:BK55) -> 8956669.8
A58: =Projections!A60 -> SOURCE #2: Inbound Sales | C58: =Projections!$C$60 -> Disabled
A62: Leads from Paid Traffic
A63: Cost of Acqusition per Lead | C63: =Settings!$C$6 -> USD | D63: =IF($C$58="Enabled",IF(D$6=Projections!$C$65,Projections!$C$81,IF(D$6>Projections!$C$65,MAX(Projections!$C$82+C63,Projections!$C$83),0)),0) -> 0 | E63: =IF($C$58="Enabled",IF(E$6=Projections!$C$65,Projections!$C$81,IF(E$6>Projections!$C$65,MAX(Projections!$C$82+D63,Projections!$C$83),0)),0) -> 0 | F63: =IF($C$58="Enabled",IF(F$6=Projections!$C$65,Projections!$C$81,IF(F$6>Projections!$C$65,MAX(Projections!$C$82+E63,Projections!$C$83),0)),0) -> 0 | G63: =IF($C$58="Enabled",IF(G$6=Projections!$C$65,Projections!$C$81,IF(G$6>Projections!$C$65,MAX(Projections!$C$82+F63,Projections!$C$83),0)),0) -> 0 | H63: =IF($C$58="Enabled",IF(H$6=Projections!$C$65,Projections!$C$81,IF(H$6>Projections!$C$65,MAX(Projections!$C$82+G63,Projections!$C$83),0)),0) -> 0 | I63: =IF($C$58="Enabled",IF(I$6=Projections!$C$65,Projections!$C$81,IF(I$6>Projections!$C$65,MAX(Projections!$C$82+H63,Projections!$C$83),0)),0) -> 0 | J63: =IF($C$58="Enabled",IF(J$6=Projections!$C$65,Projections!$C$81,IF(J$6>Projections!$C$65,MAX(Projections!$C$82+I63,Projections!$C$83),0)),0) -> 0 | K63: =IF($C$58="Enabled",IF(K$6=Projections!$C$65,Projections!$C$81,IF(K$6>Projections!$C$65,MAX(Projections!$C$82+J63,Projections!$C$83),0)),0) -> 0 | ... BK63: =IF($C$58="Enabled",IF(BK$6=Projections!$C$65,Projections!$C$81,IF(BK$6>Projections!$C$65,MAX(Projections!$C$82+BJ63,Projections!$C$83),0)),0) -> 0
A64: Expected Leads Added via Ads | C64: # | D64: =IFERROR(ROUNDDOWN(#REF!/D63,0),0) -> 0 | E64: =IFERROR(ROUNDDOWN(#REF!/E63,0),0) -> 0 | F64: =IFERROR(ROUNDDOWN(#REF!/F63,0),0) -> 0 | G64: =IFERROR(ROUNDDOWN(#REF!/G63,0),0) -> 0 | H64: =IFERROR(ROUNDDOWN(#REF!/H63,0),0) -> 0 | I64: =IFERROR(ROUNDDOWN(#REF!/I63,0),0) -> 0 | J64: =IFERROR(ROUNDDOWN(#REF!/J63,0),0) -> 0 | K64: =IFERROR(ROUNDDOWN(#REF!/K63,0),0) -> 0 | ... BK64: =IFERROR(ROUNDDOWN(#REF!/BK63,0),0) -> 0
A67: Leads from Organic Traffic
A68: Expected Conversions from Organic Traffic | C68: # | D68: =IF(AND($C$58="Enabled",D$6>=Projections!$C$65),ROUNDDOWN(#REF!*Projections!$C$72,0),0) -> 0 | E68: =IF(AND($C$58="Enabled",E$6>=Projections!$C$65),ROUNDDOWN(#REF!*Projections!$C$72,0),0) -> 0 | F68: =IF(AND($C$58="Enabled",F$6>=Projections!$C$65),ROUNDDOWN(#REF!*Projections!$C$72,0),0) -> 0 | G68: =IF(AND($C$58="Enabled",G$6>=Projections!$C$65),ROUNDDOWN(#REF!*Projections!$C$72,0),0) -> 0 | H68: =IF(AND($C$58="Enabled",H$6>=Projections!$C$65),ROUNDDOWN(#REF!*Projections!$C$72,0),0) -> 0 | I68: =IF(AND($C$58="Enabled",I$6>=Projections!$C$65),ROUNDDOWN(#REF!*Projections!$C$72,0),0) -> 0 | J68: =IF(AND($C$58="Enabled",J$6>=Projections!$C$65),ROUNDDOWN(#REF!*Projections!$C$72,0),0) -> 0 | K68: =IF(AND($C$58="Enabled",K$6>=Projections!$C$65),ROUNDDOWN(#REF!*Projections!$C$72,0),0) -> 0 | ... BK68: =IF(AND($C$58="Enabled",BK$6>=Projections!$C$65),ROUNDDOWN(#REF!*Projections!$C$72,0),0) -> 0
A70: Lead Handling
A71: Total Leads Generated | D71: =D68+D64 -> 0 | E71: =E68+E64 -> 0 | F71: =F68+F64 -> 0 | G71: =G68+G64 -> 0 | H71: =H68+H64 -> 0 | I71: =I68+I64 -> 0 | J71: =J68+J64 -> 0 | K71: =K68+K64 -> 0 | ... BK71: =BK68+BK64 -> 0
A72: Agents needed to handle leads | D72: =IFERROR(ROUNDUP(D71/Projections!$C$86,0),"") | E72: =IFERROR(ROUNDUP(E71/Projections!$C$86,0),"") | F72: =IFERROR(ROUNDUP(F71/Projections!$C$86,0),"") | G72: =IFERROR(ROUNDUP(G71/Projections!$C$86,0),"") | H72: =IFERROR(ROUNDUP(H71/Projections!$C$86,0),"") | I72: =IFERROR(ROUNDUP(I71/Projections!$C$86,0),"") | J72: =IFERROR(ROUNDUP(J71/Projections!$C$86,0),"") | K72: =IFERROR(ROUNDUP(K71/Projections!$C$86,0),"") | ... BK72: =IFERROR(ROUNDUP(BK71/Projections!$C$86,0),"")
A76: Monthly Billing Model
A77: Churn Rate | C77: % | D77: =Projections!$C$68 -> 0 | E77: =Projections!$C$68 -> 0 | F77: =Projections!$C$68 -> 0 | G77: =Projections!$C$68 -> 0 | H77: =Projections!$C$68 -> 0 | I77: =Projections!$C$68 -> 0 | J77: =Projections!$C$68 -> 0 | K77: =Projections!$C$68 -> 0 | ... BK77: =Projections!$C$68 -> 0
A79: Subscribers
A80: New Customers | C80: # | D80: =IF(Projections!$C$67="Monthly",ROUND(D71*Projections!$C$90,0),0) -> 0 | E80: =IF(Projections!$C$67="Monthly",ROUND(E71*Projections!$C$90,0),0) -> 0 | F80: =IF(Projections!$C$67="Monthly",ROUND(F71*Projections!$C$90,0),0) -> 0 | G80: =IF(Projections!$C$67="Monthly",ROUND(G71*Projections!$C$90,0),0) -> 0 | H80: =IF(Projections!$C$67="Monthly",ROUND(H71*Projections!$C$90,0),0) -> 0 | I80: =IF(Projections!$C$67="Monthly",ROUND(I71*Projections!$C$90,0),0) -> 0 | J80: =IF(Projections!$C$67="Monthly",ROUND(J71*Projections!$C$90,0),0) -> 0 | K80: =IF(Projections!$C$67="Monthly",ROUND(K71*Projections!$C$90,0),0) -> 0 | ... BK80: =IF(Projections!$C$67="Monthly",ROUND(BK71*Projections!$C$90,0),0) -> 0
A81: Lost Customers | C81: # | D81: =IFERROR(ROUND(C82*D77,0),0) -> 0 | E81: =IFERROR(ROUND(D82*E77,0),0) -> 0 | F81: =IFERROR(ROUND(E82*F77,0),0) -> 0 | G81: =IFERROR(ROUND(F82*G77,0),0) -> 0 | H81: =IFERROR(ROUND(G82*H77,0),0) -> 0 | I81: =IFERROR(ROUND(H82*I77,0),0) -> 0 | J81: =IFERROR(ROUND(I82*J77,0),0) -> 0 | K81: =IFERROR(ROUND(J82*K77,0),0) -> 0 | ... BK81: =IFERROR(ROUND(BJ82*BK77,0),0) -> 0
A82: Total Customers | C82: # | D82: =IFERROR(D80-D81+C82,D80) -> 0 | E82: =IFERROR(E80-E81+D82,E80) -> 0 | F82: =IFERROR(F80-F81+E82,F80) -> 0 | G82: =IFERROR(G80-G81+F82,G80) -> 0 | H82: =IFERROR(H80-H81+G82,H80) -> 0 | I82: =IFERROR(I80-I81+H82,I80) -> 0 | J82: =IFERROR(J80-J81+I82,J80) -> 0 | K82: =IFERROR(K80-K81+J82,K80) -> 0 | ... BK82: =IFERROR(BK80-BK81+BJ82,BK80) -> 0
A84: MRR
A85: New MRR | C85: =Settings!$C$6 -> USD | D85: =D80*Projections!$C$66 -> 0 | E85: =E80*Projections!$C$66 -> 0 | F85: =F80*Projections!$C$66 -> 0 | G85: =G80*Projections!$C$66 -> 0 | H85: =H80*Projections!$C$66 -> 0 | I85: =I80*Projections!$C$66 -> 0 | J85: =J80*Projections!$C$66 -> 0 | K85: =K80*Projections!$C$66 -> 0 | ... BK85: =BK80*Projections!$C$66 -> 0
A86: Lost MRR | C86: =Settings!$C$6 -> USD | D86: =D81*Projections!$C$66 -> 0 | E86: =E81*Projections!$C$66 -> 0 | F86: =F81*Projections!$C$66 -> 0 | G86: =G81*Projections!$C$66 -> 0 | H86: =H81*Projections!$C$66 -> 0 | I86: =I81*Projections!$C$66 -> 0 | J86: =J81*Projections!$C$66 -> 0 | K86: =K81*Projections!$C$66 -> 0 | ... BK86: =BK81*Projections!$C$66 -> 0
A87: Monthly Recurring Revenue | C87: =Settings!$C$6 -> USD | D87: =IF(Projections!$C$67="Monthly",D82*Projections!$C$66,0) -> 0 | E87: =IF(Projections!$C$67="Monthly",E82*Projections!$C$66,0) -> 0 | F87: =IF(Projections!$C$67="Monthly",F82*Projections!$C$66,0) -> 0 | G87: =IF(Projections!$C$67="Monthly",G82*Projections!$C$66,0) -> 0 | H87: =IF(Projections!$C$67="Monthly",H82*Projections!$C$66,0) -> 0 | I87: =IF(Projections!$C$67="Monthly",I82*Projections!$C$66,0) -> 0 | J87: =IF(Projections!$C$67="Monthly",J82*Projections!$C$66,0) -> 0 | K87: =IF(Projections!$C$67="Monthly",K82*Projections!$C$66,0) -> 0 | ... BK87: =IF(Projections!$C$67="Monthly",BK82*Projections!$C$66,0) -> 0
A90: Annual Billing Model
A91: Churn Rate | C91: % | D91: =Projections!$C$68 -> 0 | E91: =Projections!$C$68 -> 0 | F91: =Projections!$C$68 -> 0 | G91: =Projections!$C$68 -> 0 | H91: =Projections!$C$68 -> 0 | I91: =Projections!$C$68 -> 0 | J91: =Projections!$C$68 -> 0 | K91: =Projections!$C$68 -> 0 | ... BK91: =Projections!$C$68 -> 0
A93: Subscribers
A94: New Customers | C94: # | D94: =IF(Projections!$C$67="Yearly",ROUND(D71*Projections!$C$90,0),0) -> 0 | E94: =IF(Projections!$C$67="Yearly",ROUND(E71*Projections!$C$90,0),0) -> 0 | F94: =IF(Projections!$C$67="Yearly",ROUND(F71*Projections!$C$90,0),0) -> 0 | G94: =IF(Projections!$C$67="Yearly",ROUND(G71*Projections!$C$90,0),0) -> 0 | H94: =IF(Projections!$C$67="Yearly",ROUND(H71*Projections!$C$90,0),0) -> 0 | I94: =IF(Projections!$C$67="Yearly",ROUND(I71*Projections!$C$90,0),0) -> 0 | J94: =IF(Projections!$C$67="Yearly",ROUND(J71*Projections!$C$90,0),0) -> 0 | K94: =IF(Projections!$C$67="Yearly",ROUND(K71*Projections!$C$90,0),0) -> 0 | ... BK94: =IF(Projections!$C$67="Yearly",ROUND(BK71*Projections!$C$90,0),0) -> 0
A95: Renewing Customers | C95: # | D95: =SUM(D100:D106) -> 0 | E95: =SUM(E100:E106) -> 0 | F95: =SUM(F100:F106) -> 0 | G95: =SUM(G100:G106) -> 0 | H95: =SUM(H100:H106) -> 0 | I95: =SUM(I100:I106) -> 0 | J95: =SUM(J100:J106) -> 0 | K95: =SUM(K100:K106) -> 0 | ... BK95: =SUM(BK100:BK106) -> #REF!
A96: Total Active Customers | C96: # | D96: =IF(D$7<=12,SUM($D94:D94),SUM(#REF!)) -> 0 | E96: =IF(E$7<=12,SUM($D94:E94),SUM(#REF!)) -> 0 | F96: =IF(F$7<=12,SUM($D94:F94),SUM(#REF!)) -> 0 | G96: =IF(G$7<=12,SUM($D94:G94),SUM(#REF!)) -> 0 | H96: =IF(H$7<=12,SUM($D94:H94),SUM(#REF!)) -> 0 | I96: =IF(I$7<=12,SUM($D94:I94),SUM(#REF!)) -> 0 | J96: =IF(J$7<=12,SUM($D94:J94),SUM(#REF!)) -> 0 | K96: =IF(K$7<=12,SUM($D94:K94),SUM(#REF!)) -> 0 | L96: =IF(L$7<=12,SUM($D94:L94),SUM(A94:L95)) -> 0 | M96: =IF(M$7<=12,SUM($D94:M94),SUM(B94:M95)) -> 0 | N96: =IF(N$7<=12,SUM($D94:N94),SUM(C94:N95)) -> 0 | O96: =IF(O$7<=12,SUM($D94:O94),SUM(D94:O95)) -> 0 | P96: =IF(P$7<=12,SUM($D94:P94),SUM(E94:P95)) -> #REF! | Q96: =IF(Q$7<=12,SUM($D94:Q94),SUM(F94:Q95)) -> #REF! | R96: =IF(R$7<=12,SUM($D94:R94),SUM(G94:R95)) -> #REF! | S96: =IF(S$7<=12,SUM($D94:S94),SUM(H94:S95)) -> #REF! | ... BK96: =IF(BK$7<=12,SUM($D94:BK94),SUM(AZ94:BK95)) -> #REF!
A98: Cohorts
A99: Renewing Customers
A100: =YEAR(D$6) -> 2019 | C100: # | D100: =IF(YEAR(D$6)=$A100,"",IF(YEAR(D$6)=($A100+1),ROUND(#REF!*(1-D$28),0),ROUND(#REF!*(1-D$28),0))) | E100: =IF(YEAR(E$6)=$A100,"",IF(YEAR(E$6)=($A100+1),ROUND(#REF!*(1-E$28),0),ROUND(#REF!*(1-E$28),0))) | F100: =IF(YEAR(F$6)=$A100,"",IF(YEAR(F$6)=($A100+1),ROUND(#REF!*(1-F$28),0),ROUND(#REF!*(1-F$28),0))) | G100: =IF(YEAR(G$6)=$A100,"",IF(YEAR(G$6)=($A100+1),ROUND(#REF!*(1-G$28),0),ROUND(#REF!*(1-G$28),0))) | H100: =IF(YEAR(H$6)=$A100,"",IF(YEAR(H$6)=($A100+1),ROUND(#REF!*(1-H$28),0),ROUND(#REF!*(1-H$28),0))) | I100: =IF(YEAR(I$6)=$A100,"",IF(YEAR(I$6)=($A100+1),ROUND(#REF!*(1-I$28),0),ROUND(#REF!*(1-I$28),0))) | J100: =IF(YEAR(J$6)=$A100,"",IF(YEAR(J$6)=($A100+1),ROUND(#REF!*(1-J$28),0),ROUND(#REF!*(1-J$28),0))) | K100: =IF(YEAR(K$6)=$A100,"",IF(YEAR(K$6)=($A100+1),ROUND(#REF!*(1-K$28),0),ROUND(#REF!*(1-K$28),0))) | L100: =IF(YEAR(L$6)=$A100,"",IF(YEAR(L$6)=($A100+1),ROUND(#REF!*(1-L$28),0),ROUND(#REF!*(1-L$28),0))) | M100: =IF(YEAR(M$6)=$A100,"",IF(YEAR(M$6)=($A100+1),ROUND(A$31*(1-M$28),0),ROUND(A100*(1-M$28),0))) | N100: =IF(YEAR(N$6)=$A100,"",IF(YEAR(N$6)=($A100+1),ROUND(B$31*(1-N$28),0),ROUND(B100*(1-N$28),0))) | O100: =IF(YEAR(O$6)=$A100,"",IF(YEAR(O$6)=($A100+1),ROUND(C$31*(1-O$28),0),ROUND(C100*(1-O$28),0))) | P100: =IF(YEAR(P$6)=$A100,"",IF(YEAR(P$6)=($A100+1),ROUND(D$94*(1-P$91),0),ROUND(D100*(1-P$91),0))) -> 0 | Q100: =IF(YEAR(Q$6)=$A100,"",IF(YEAR(Q$6)=($A100+1),ROUND(E$94*(1-Q$91),0),ROUND(E100*(1-Q$91),0))) -> 0 | R100: =IF(YEAR(R$6)=$A100,"",IF(YEAR(R$6)=($A100+1),ROUND(F$94*(1-R$91),0),ROUND(F100*(1-R$91),0))) -> 0 | S100: =IF(YEAR(S$6)=$A100,"",IF(YEAR(S$6)=($A100+1),ROUND(G$94*(1-S$91),0),ROUND(G100*(1-S$91),0))) -> 0 | T100: =IF(YEAR(T$6)=$A100,"",IF(YEAR(T$6)=($A100+1),ROUND(H$94*(1-T$91),0),ROUND(H100*(1-T$91),0))) -> 0 | U100: =IF(YEAR(U$6)=$A100,"",IF(YEAR(U$6)=($A100+1),ROUND(I$94*(1-U$91),0),ROUND(I100*(1-U$91),0))) -> 0 | V100: =IF(YEAR(V$6)=$A100,"",IF(YEAR(V$6)=($A100+1),ROUND(J$94*(1-V$91),0),ROUND(J100*(1-V$91),0))) -> 0 | W100: =IF(YEAR(W$6)=$A100,"",IF(YEAR(W$6)=($A100+1),ROUND(K$94*(1-W$91),0),ROUND(K100*(1-W$91),0))) -> 0 | ... BK100: =IF(YEAR(BK$6)=$A100,"",IF(YEAR(BK$6)=($A100+1),ROUND(AY$94*(1-BK$91),0),ROUND(AY100*(1-BK$91),0))) -> 0
A101: =YEAR(P$6) -> 2020 | C101: # | P101: =IF(YEAR(P$6)=$A101,"",IF(YEAR(P$6)=($A101+1),ROUND(D$94*(1-P$91),0),ROUND(D101*(1-P$91),0))) | Q101: =IF(YEAR(Q$6)=$A101,"",IF(YEAR(Q$6)=($A101+1),ROUND(E$94*(1-Q$91),0),ROUND(E101*(1-Q$91),0))) | R101: =IF(YEAR(R$6)=$A101,"",IF(YEAR(R$6)=($A101+1),ROUND(F$94*(1-R$91),0),ROUND(F101*(1-R$91),0))) | S101: =IF(YEAR(S$6)=$A101,"",IF(YEAR(S$6)=($A101+1),ROUND(G$94*(1-S$91),0),ROUND(G101*(1-S$91),0))) | T101: =IF(YEAR(T$6)=$A101,"",IF(YEAR(T$6)=($A101+1),ROUND(H$94*(1-T$91),0),ROUND(H101*(1-T$91),0))) | U101: =IF(YEAR(U$6)=$A101,"",IF(YEAR(U$6)=($A101+1),ROUND(I$94*(1-U$91),0),ROUND(I101*(1-U$91),0))) | V101: =IF(YEAR(V$6)=$A101,"",IF(YEAR(V$6)=($A101+1),ROUND(J$94*(1-V$91),0),ROUND(J101*(1-V$91),0))) | W101: =IF(YEAR(W$6)=$A101,"",IF(YEAR(W$6)=($A101+1),ROUND(K$94*(1-W$91),0),ROUND(K101*(1-W$91),0))) | ... BK101: =IF(YEAR(BK$6)=$A101,"",IF(YEAR(BK$6)=($A101+1),ROUND(AY$94*(1-BK$91),0),ROUND(AY101*(1-BK$91),0))) -> 0
A102: =YEAR(AB$6) -> 2021 | C102: # | P102: =IF(YEAR(P$6)=$A102,"",IF(YEAR(P$6)=($A102+1),ROUND(D$94*(1-P$91),0),ROUND(D102*(1-P$91),0))) -> 0 | Q102: =IF(YEAR(Q$6)=$A102,"",IF(YEAR(Q$6)=($A102+1),ROUND(E$94*(1-Q$91),0),ROUND(E102*(1-Q$91),0))) -> 0 | R102: =IF(YEAR(R$6)=$A102,"",IF(YEAR(R$6)=($A102+1),ROUND(F$94*(1-R$91),0),ROUND(F102*(1-R$91),0))) -> 0 | S102: =IF(YEAR(S$6)=$A102,"",IF(YEAR(S$6)=($A102+1),ROUND(G$94*(1-S$91),0),ROUND(G102*(1-S$91),0))) -> 0 | T102: =IF(YEAR(T$6)=$A102,"",IF(YEAR(T$6)=($A102+1),ROUND(H$94*(1-T$91),0),ROUND(H102*(1-T$91),0))) -> 0 | U102: =IF(YEAR(U$6)=$A102,"",IF(YEAR(U$6)=($A102+1),ROUND(I$94*(1-U$91),0),ROUND(I102*(1-U$91),0))) -> 0 | V102: =IF(YEAR(V$6)=$A102,"",IF(YEAR(V$6)=($A102+1),ROUND(J$94*(1-V$91),0),ROUND(J102*(1-V$91),0))) -> 0 | W102: =IF(YEAR(W$6)=$A102,"",IF(YEAR(W$6)=($A102+1),ROUND(K$94*(1-W$91),0),ROUND(K102*(1-W$91),0))) -> 0 | ... BK102: =IF(YEAR(BK$6)=$A102,"",IF(YEAR(BK$6)=($A102+1),ROUND(AY$94*(1-BK$91),0),ROUND(AY102*(1-BK$91),0))) -> 0
A103: =YEAR(AN$6) -> 2022 | C103: # | P103: =IF(YEAR(P$6)=$A103,"",IF(YEAR(P$6)=($A103+1),ROUND(D$94*(1-P$91),0),ROUND(D103*(1-P$91),0))) -> 0 | Q103: =IF(YEAR(Q$6)=$A103,"",IF(YEAR(Q$6)=($A103+1),ROUND(E$94*(1-Q$91),0),ROUND(E103*(1-Q$91),0))) -> 0 | R103: =IF(YEAR(R$6)=$A103,"",IF(YEAR(R$6)=($A103+1),ROUND(F$94*(1-R$91),0),ROUND(F103*(1-R$91),0))) -> 0 | S103: =IF(YEAR(S$6)=$A103,"",IF(YEAR(S$6)=($A103+1),ROUND(G$94*(1-S$91),0),ROUND(G103*(1-S$91),0))) -> 0 | T103: =IF(YEAR(T$6)=$A103,"",IF(YEAR(T$6)=($A103+1),ROUND(H$94*(1-T$91),0),ROUND(H103*(1-T$91),0))) -> 0 | U103: =IF(YEAR(U$6)=$A103,"",IF(YEAR(U$6)=($A103+1),ROUND(I$94*(1-U$91),0),ROUND(I103*(1-U$91),0))) -> 0 | V103: =IF(YEAR(V$6)=$A103,"",IF(YEAR(V$6)=($A103+1),ROUND(J$94*(1-V$91),0),ROUND(J103*(1-V$91),0))) -> 0 | W103: =IF(YEAR(W$6)=$A103,"",IF(YEAR(W$6)=($A103+1),ROUND(K$94*(1-W$91),0),ROUND(K103*(1-W$91),0))) -> 0 | ... BK103: =IF(YEAR(BK$6)=$A103,"",IF(YEAR(BK$6)=($A103+1),ROUND(AY$94*(1-BK$91),0),ROUND(AY103*(1-BK$91),0))) -> 0
A104: =YEAR(AZ$6) -> 2023 | C104: # | P104: =IF(YEAR(P$6)=$A104,"",IF(YEAR(P$6)=($A104+1),ROUND(D$94*(1-P$91),0),ROUND(D104*(1-P$91),0))) -> 0 | Q104: =IF(YEAR(Q$6)=$A104,"",IF(YEAR(Q$6)=($A104+1),ROUND(E$94*(1-Q$91),0),ROUND(E104*(1-Q$91),0))) -> 0 | R104: =IF(YEAR(R$6)=$A104,"",IF(YEAR(R$6)=($A104+1),ROUND(F$94*(1-R$91),0),ROUND(F104*(1-R$91),0))) -> 0 | S104: =IF(YEAR(S$6)=$A104,"",IF(YEAR(S$6)=($A104+1),ROUND(G$94*(1-S$91),0),ROUND(G104*(1-S$91),0))) -> 0 | T104: =IF(YEAR(T$6)=$A104,"",IF(YEAR(T$6)=($A104+1),ROUND(H$94*(1-T$91),0),ROUND(H104*(1-T$91),0))) -> 0 | U104: =IF(YEAR(U$6)=$A104,"",IF(YEAR(U$6)=($A104+1),ROUND(I$94*(1-U$91),0),ROUND(I104*(1-U$91),0))) -> 0 | V104: =IF(YEAR(V$6)=$A104,"",IF(YEAR(V$6)=($A104+1),ROUND(J$94*(1-V$91),0),ROUND(J104*(1-V$91),0))) -> 0 | W104: =IF(YEAR(W$6)=$A104,"",IF(YEAR(W$6)=($A104+1),ROUND(K$94*(1-W$91),0),ROUND(K104*(1-W$91),0))) -> 0 | ... BK104: =IF(YEAR(BK$6)=$A104,"",IF(YEAR(BK$6)=($A104+1),ROUND(AY$94*(1-BK$91),0),ROUND(AY104*(1-BK$91),0)))
A105: =YEAR(#REF!) -> #REF! | C105: # | P105: =IF(YEAR(P$6)=$A105,"",IF(YEAR(P$6)=($A105+1),ROUND(D$94*(1-P$91),0),ROUND(D105*(1-P$91),0))) -> #REF! | Q105: =IF(YEAR(Q$6)=$A105,"",IF(YEAR(Q$6)=($A105+1),ROUND(E$94*(1-Q$91),0),ROUND(E105*(1-Q$91),0))) -> #REF! | R105: =IF(YEAR(R$6)=$A105,"",IF(YEAR(R$6)=($A105+1),ROUND(F$94*(1-R$91),0),ROUND(F105*(1-R$91),0))) -> #REF! | S105: =IF(YEAR(S$6)=$A105,"",IF(YEAR(S$6)=($A105+1),ROUND(G$94*(1-S$91),0),ROUND(G105*(1-S$91),0))) -> #REF! | T105: =IF(YEAR(T$6)=$A105,"",IF(YEAR(T$6)=($A105+1),ROUND(H$94*(1-T$91),0),ROUND(H105*(1-T$91),0))) -> #REF! | U105: =IF(YEAR(U$6)=$A105,"",IF(YEAR(U$6)=($A105+1),ROUND(I$94*(1-U$91),0),ROUND(I105*(1-U$91),0))) -> #REF! | V105: =IF(YEAR(V$6)=$A105,"",IF(YEAR(V$6)=($A105+1),ROUND(J$94*(1-V$91),0),ROUND(J105*(1-V$91),0))) -> #REF! | W105: =IF(YEAR(W$6)=$A105,"",IF(YEAR(W$6)=($A105+1),ROUND(K$94*(1-W$91),0),ROUND(K105*(1-W$91),0))) -> #REF! | ... BK105: =IF(YEAR(BK$6)=$A105,"",IF(YEAR(BK$6)=($A105+1),ROUND(AY$94*(1-BK$91),0),ROUND(AY105*(1-BK$91),0))) -> #REF!
A106: =YEAR(#REF!) -> #REF! | C106: # | P106: =IF(YEAR(P$6)=$A106,"",IF(YEAR(P$6)=($A106+1),ROUND(D$94*(1-P$91),0),ROUND(D106*(1-P$91),0))) -> #REF! | Q106: =IF(YEAR(Q$6)=$A106,"",IF(YEAR(Q$6)=($A106+1),ROUND(E$94*(1-Q$91),0),ROUND(E106*(1-Q$91),0))) -> #REF! | R106: =IF(YEAR(R$6)=$A106,"",IF(YEAR(R$6)=($A106+1),ROUND(F$94*(1-R$91),0),ROUND(F106*(1-R$91),0))) -> #REF! | S106: =IF(YEAR(S$6)=$A106,"",IF(YEAR(S$6)=($A106+1),ROUND(G$94*(1-S$91),0),ROUND(G106*(1-S$91),0))) -> #REF! | T106: =IF(YEAR(T$6)=$A106,"",IF(YEAR(T$6)=($A106+1),ROUND(H$94*(1-T$91),0),ROUND(H106*(1-T$91),0))) -> #REF! | U106: =IF(YEAR(U$6)=$A106,"",IF(YEAR(U$6)=($A106+1),ROUND(I$94*(1-U$91),0),ROUND(I106*(1-U$91),0))) -> #REF! | V106: =IF(YEAR(V$6)=$A106,"",IF(YEAR(V$6)=($A106+1),ROUND(J$94*(1-V$91),0),ROUND(J106*(1-V$91),0))) -> #REF! | W106: =IF(YEAR(W$6)=$A106,"",IF(YEAR(W$6)=($A106+1),ROUND(K$94*(1-W$91),0),ROUND(K106*(1-W$91),0))) -> #REF! | ... BK106: =IF(YEAR(BK$6)=$A106,"",IF(YEAR(BK$6)=($A106+1),ROUND(AY$94*(1-BK$91),0),ROUND(AY106*(1-BK$91),0))) -> #REF!
A108: Annual Billing Summary
A109: New MRR | C109: =Settings!$C$6 -> USD | D109: =D94*Projections!$C$66 -> 0 | E109: =E94*Projections!$C$66 -> 0 | F109: =F94*Projections!$C$66 -> 0 | G109: =G94*Projections!$C$66 -> 0 | H109: =H94*Projections!$C$66 -> 0 | I109: =I94*Projections!$C$66 -> 0 | J109: =J94*Projections!$C$66 -> 0 | K109: =K94*Projections!$C$66 -> 0 | ... BK109: =BK94*Projections!$C$66 -> 0
A110: Renewing MRR | C110: =Settings!$C$6 -> USD | D110: =D95*Projections!$C$66 -> 0 | E110: =E95*Projections!$C$66 -> 0 | F110: =F95*Projections!$C$66 -> 0 | G110: =G95*Projections!$C$66 -> 0 | H110: =H95*Projections!$C$66 -> 0 | I110: =I95*Projections!$C$66 -> 0 | J110: =J95*Projections!$C$66 -> 0 | K110: =K95*Projections!$C$66 -> 0 | ... BK110: =BK95*Projections!$C$66 -> #REF!
A111: Billed Cash Flow | C111: =Settings!$C$6 -> USD | D111: =SUM(D109:D110)*12 -> 0 | E111: =SUM(E109:E110)*12 -> 0 | F111: =SUM(F109:F110)*12 -> 0 | G111: =SUM(G109:G110)*12 -> 0 | H111: =SUM(H109:H110)*12 -> 0 | I111: =SUM(I109:I110)*12 -> 0 | J111: =SUM(J109:J110)*12 -> 0 | K111: =SUM(K109:K110)*12 -> 0 | ... BK111: =SUM(BK109:BK110)*12 -> #REF!
A114: Totals
A115: Monthly Recurring Revenue | C115: =Settings!$C$6 -> USD | D115: =D96*Projections!$C$66+D87 -> 0 | E115: =E96*Projections!$C$66+E87 -> 0 | F115: =F96*Projections!$C$66+F87 -> 0 | G115: =G96*Projections!$C$66+G87 -> 0 | H115: =H96*Projections!$C$66+H87 -> 0 | I115: =I96*Projections!$C$66+I87 -> 0 | J115: =J96*Projections!$C$66+J87 -> 0 | K115: =K96*Projections!$C$66+K87 -> 0 | ... BK115: =BK96*Projections!$C$66+BK87 -> #REF!
A116: LTV Subscribed this Month | C116: =Settings!$C$6 -> USD | D116: =IF(Projections!$C$67="Monthly",D80*Projections!$C$66/D77,IF(Projections!$C$67="Yearly",D94*Projections!$C$66/(D91/12),0)) -> 0 | E116: =IF(Projections!$C$67="Monthly",E80*Projections!$C$66/E77,IF(Projections!$C$67="Yearly",E94*Projections!$C$66/(E91/12),0)) -> 0 | F116: =IF(Projections!$C$67="Monthly",F80*Projections!$C$66/F77,IF(Projections!$C$67="Yearly",F94*Projections!$C$66/(F91/12),0)) -> 0 | G116: =IF(Projections!$C$67="Monthly",G80*Projections!$C$66/G77,IF(Projections!$C$67="Yearly",G94*Projections!$C$66/(G91/12),0)) -> 0 | H116: =IF(Projections!$C$67="Monthly",H80*Projections!$C$66/H77,IF(Projections!$C$67="Yearly",H94*Projections!$C$66/(H91/12),0)) -> 0 | I116: =IF(Projections!$C$67="Monthly",I80*Projections!$C$66/I77,IF(Projections!$C$67="Yearly",I94*Projections!$C$66/(I91/12),0)) -> 0 | J116: =IF(Projections!$C$67="Monthly",J80*Projections!$C$66/J77,IF(Projections!$C$67="Yearly",J94*Projections!$C$66/(J91/12),0)) -> 0 | K116: =IF(Projections!$C$67="Monthly",K80*Projections!$C$66/K77,IF(Projections!$C$67="Yearly",K94*Projections!$C$66/(K91/12),0)) -> 0 | ... BK116: =IF(Projections!$C$67="Monthly",BK80*Projections!$C$66/BK77,IF(Projections!$C$67="Yearly",BK94*Projections!$C$66/(BK91/12),0)) -> 0
A119: Total | C119: =Settings!$C$6 -> USD | D119: 0 | E119: 0 | F119: 0 | G119: 0 | H119: 0 | I119: 0 | J119: 0 | K119: 0 | L119: 0 | M119: 0 | N119: 0 | O119: 0 | P119: 0 | Q119: 0 | R119: 0 | S119: 0 | T119: 0 | U119: 0 | V119: 0 | W119: 0 | X119: 0 | Y119: 0 | Z119: 0 | AA119: 0 | AB119: 0 | AC119: 0 | AD119: 0 | AE119: 0 | AF119: 0 | AG119: 0 | AH119: 0 | AI119: 0 | AJ119: 0 | AK119: 0 | AL119: 0 | AM119: 0 | AN119: 0 | AO119: 0 | AP119: 0 | AQ119: 0 | AR119: 0 | AS119: 0 | AT119: 0 | AU119: 0 | AV119: 0 | AW119: 0 | AX119: 0 | AY119: 0 | AZ119: 0 | BA119: 0 | BB119: 0 | BC119: 0 | BD119: 0 | BE119: 0 | BF119: 0 | BG119: 0 | BH119: 0 | BI119: 0 | BJ119: 0 | BK119: 0
A122: =Projections!A101 -> SOURCE #3: Outbound Sales | C122: =Projections!$C$101 -> Disabled
A124: Agents doing outbound sales | C124: # | D124: =IF($C$122="Enabled",'SG&A'!F137,0) -> 0 | E124: =IF($C$122="Enabled",'SG&A'!G137,0) -> 0 | F124: =IF($C$122="Enabled",'SG&A'!H137,0) -> 0 | G124: =IF($C$122="Enabled",'SG&A'!I137,0) -> 0 | H124: =IF($C$122="Enabled",'SG&A'!J137,0) -> 0 | I124: =IF($C$122="Enabled",'SG&A'!K137,0) -> 0 | J124: =IF($C$122="Enabled",'SG&A'!L137,0) -> 0 | K124: =IF($C$122="Enabled",'SG&A'!M137,0) -> 0 | ... BK124: =IF($C$122="Enabled",'SG&A'!BM137,0) -> 0
A125: Deals closed (including delay) | C125: # | D125: =IF(SalesCycle=1,(ROUND(D$124*Projections!$C$116,0)),IF(SalesCycle=2,(ROUND(C$124*Projections!$C$116,0)),IF(SalesCycle=3,(IFERROR(ROUND(B$124*Projections!$C$116,0),0)),IF(SalesCycle=6,(IFERROR(ROUND(#REF!*Projections!$C$116,0),0)))))) -> FALSE | E125: =IF(SalesCycle=1,(ROUND(E$124*Projections!$C$116,0)),IF(SalesCycle=2,(ROUND(D$124*Projections!$C$116,0)),IF(SalesCycle=3,(IFERROR(ROUND(C$124*Projections!$C$116,0),0)),IF(SalesCycle=6,(IFERROR(ROUND(#REF!*Projections!$C$116,0),0)))))) -> FALSE | F125: =IF(SalesCycle=1,(ROUND(F$124*Projections!$C$116,0)),IF(SalesCycle=2,(ROUND(E$124*Projections!$C$116,0)),IF(SalesCycle=3,(IFERROR(ROUND(D$124*Projections!$C$116,0),0)),IF(SalesCycle=6,(IFERROR(ROUND(A$124*Projections!$C$116,0),0)))))) -> FALSE | G125: =IF(SalesCycle=1,(ROUND(G$124*Projections!$C$116,0)),IF(SalesCycle=2,(ROUND(F$124*Projections!$C$116,0)),IF(SalesCycle=3,(IFERROR(ROUND(E$124*Projections!$C$116,0),0)),IF(SalesCycle=6,(IFERROR(ROUND(B$124*Projections!$C$116,0),0)))))) -> FALSE | H125: =IF(SalesCycle=1,(ROUND(H$124*Projections!$C$116,0)),IF(SalesCycle=2,(ROUND(G$124*Projections!$C$116,0)),IF(SalesCycle=3,(IFERROR(ROUND(F$124*Projections!$C$116,0),0)),IF(SalesCycle=6,(IFERROR(ROUND(C$124*Projections!$C$116,0),0)))))) -> FALSE | I125: =IF(SalesCycle=1,(ROUND(I$124*Projections!$C$116,0)),IF(SalesCycle=2,(ROUND(H$124*Projections!$C$116,0)),IF(SalesCycle=3,(IFERROR(ROUND(G$124*Projections!$C$116,0),0)),IF(SalesCycle=6,(IFERROR(ROUND(D$124*Projections!$C$116,0),0)))))) -> FALSE | J125: =IF(SalesCycle=1,(ROUND(J$124*Projections!$C$116,0)),IF(SalesCycle=2,(ROUND(I$124*Projections!$C$116,0)),IF(SalesCycle=3,(IFERROR(ROUND(H$124*Projections!$C$116,0),0)),IF(SalesCycle=6,(IFERROR(ROUND(E$124*Projections!$C$116,0),0)))))) -> FALSE | K125: =IF(SalesCycle=1,(ROUND(K$124*Projections!$C$116,0)),IF(SalesCycle=2,(ROUND(J$124*Projections!$C$116,0)),IF(SalesCycle=3,(IFERROR(ROUND(I$124*Projections!$C$116,0),0)),IF(SalesCycle=6,(IFERROR(ROUND(F$124*Projections!$C$116,0),0)))))) -> FALSE | L125: =IF(SalesCycle=1,(ROUND(L$124*Projections!$C$116,0)),IF(SalesCycle=2,(ROUND(K$124*Projections!$C$116,0)),IF(SalesCycle=3,(IFERROR(ROUND(J$124*Projections!$C$116,0),0)),IF(SalesCycle=6,(IFERROR(ROUND(G$124*Projections!$C$116,0),0)))))) -> FALSE | M125: =IF(SalesCycle=1,(ROUND(M$124*Projections!$C$116,0)),IF(SalesCycle=2,(ROUND(L$124*Projections!$C$116,0)),IF(SalesCycle=3,(IFERROR(ROUND(K$124*Projections!$C$116,0),0)),IF(SalesCycle=6,(IFERROR(ROUND(H$124*Projections!$C$116,0),0)))))) -> FALSE | ... BK125: =IF(SalesCycle=1,(ROUND(BK$124*Projections!$C$116,0)),IF(SalesCycle=2,(ROUND(BJ$124*Projections!$C$116,0)),IF(SalesCycle=3,(IFERROR(ROUND(BI$124*Projections!$C$116,0),0)),IF(SalesCycle=6,(IFERROR(ROUND(BF$124*Projections!$C$116,0),0)))))) -> FALSE
A127: Monthly Billing Model
A128: Churn Rate | C128: % | D128: =Projections!$C$108 -> 0 | E128: =Projections!$C$108 -> 0 | F128: =Projections!$C$108 -> 0 | G128: =Projections!$C$108 -> 0 | H128: =Projections!$C$108 -> 0 | I128: =Projections!$C$108 -> 0 | J128: =Projections!$C$108 -> 0 | K128: =Projections!$C$108 -> 0 | ... BK128: =Projections!$C$108 -> 0
A130: Subscribers
A131: New Customers | C131: # | D131: =IF(Projections!$C$107="Monthly",D$125,0) -> 0 | E131: =IF(Projections!$C$107="Monthly",E$125,0) -> 0 | F131: =IF(Projections!$C$107="Monthly",F$125,0) -> 0 | G131: =IF(Projections!$C$107="Monthly",G$125,0) -> 0 | H131: =IF(Projections!$C$107="Monthly",H$125,0) -> 0 | I131: =IF(Projections!$C$107="Monthly",I$125,0) -> 0 | J131: =IF(Projections!$C$107="Monthly",J$125,0) -> 0 | K131: =IF(Projections!$C$107="Monthly",K$125,0) -> 0 | ... BK131: =IF(Projections!$C$107="Monthly",BK$125,0) -> 0
A132: Lost Customers | C132: # | D132: =IFERROR(ROUND(C133*D128,0),0) -> 0 | E132: =IFERROR(ROUND(D133*E128,0),0) -> 0 | F132: =IFERROR(ROUND(E133*F128,0),0) -> 0 | G132: =IFERROR(ROUND(F133*G128,0),0) -> 0 | H132: =IFERROR(ROUND(G133*H128,0),0) -> 0 | I132: =IFERROR(ROUND(H133*I128,0),0) -> 0 | J132: =IFERROR(ROUND(I133*J128,0),0) -> 0 | K132: =IFERROR(ROUND(J133*K128,0),0) -> 0 | ... BK132: =IFERROR(ROUND(BJ133*BK128,0),0) -> 0
A133: Total Customers | C133: # | D133: =IFERROR(D131-D132+C133,D131) -> 0 | E133: =IFERROR(E131-E132+D133,E131) -> 0 | F133: =IFERROR(F131-F132+E133,F131) -> 0 | G133: =IFERROR(G131-G132+F133,G131) -> 0 | H133: =IFERROR(H131-H132+G133,H131) -> 0 | I133: =IFERROR(I131-I132+H133,I131) -> 0 | J133: =IFERROR(J131-J132+I133,J131) -> 0 | K133: =IFERROR(K131-K132+J133,K131) -> 0 | ... BK133: =IFERROR(BK131-BK132+BJ133,BK131) -> 0
A135: MRR
A136: New MRR | C136: =Settings!$C$6 -> USD | D136: =D131*Projections!$C$106 -> 0 | E136: =E131*Projections!$C$106 -> 0 | F136: =F131*Projections!$C$106 -> 0 | G136: =G131*Projections!$C$106 -> 0 | H136: =H131*Projections!$C$106 -> 0 | I136: =I131*Projections!$C$106 -> 0 | J136: =J131*Projections!$C$106 -> 0 | K136: =K131*Projections!$C$106 -> 0 | ... BK136: =BK131*Projections!$C$106 -> 0
A137: Lost MRR | C137: =Settings!$C$6 -> USD | D137: =D132*Projections!$C$106 -> 0 | E137: =E132*Projections!$C$106 -> 0 | F137: =F132*Projections!$C$106 -> 0 | G137: =G132*Projections!$C$106 -> 0 | H137: =H132*Projections!$C$106 -> 0 | I137: =I132*Projections!$C$106 -> 0 | J137: =J132*Projections!$C$106 -> 0 | K137: =K132*Projections!$C$106 -> 0 | ... BK137: =BK132*Projections!$C$106 -> 0
A138: Monthly Recurring Revenue | C138: =Settings!$C$6 -> USD | D138: =IF(Projections!$C$107="Monthly",D133*Projections!$C$106,0) -> 0 | E138: =IF(Projections!$C$107="Monthly",E133*Projections!$C$106,0) -> 0 | F138: =IF(Projections!$C$107="Monthly",F133*Projections!$C$106,0) -> 0 | G138: =IF(Projections!$C$107="Monthly",G133*Projections!$C$106,0) -> 0 | H138: =IF(Projections!$C$107="Monthly",H133*Projections!$C$106,0) -> 0 | I138: =IF(Projections!$C$107="Monthly",I133*Projections!$C$106,0) -> 0 | J138: =IF(Projections!$C$107="Monthly",J133*Projections!$C$106,0) -> 0 | K138: =IF(Projections!$C$107="Monthly",K133*Projections!$C$106,0) -> 0 | ... BK138: =IF(Projections!$C$107="Monthly",BK133*Projections!$C$106,0) -> 0
A141: Annual Billing Model
A142: Churn Rate | C142: % | D142: =Projections!$C$108 -> 0 | E142: =Projections!$C$108 -> 0 | F142: =Projections!$C$108 -> 0 | G142: =Projections!$C$108 -> 0 | H142: =Projections!$C$108 -> 0 | I142: =Projections!$C$108 -> 0 | J142: =Projections!$C$108 -> 0 | K142: =Projections!$C$108 -> 0 | ... BK142: =Projections!$C$108 -> 0
A144: Subscribers
A145: New Customers | C145: # | D145: =IF(Projections!$C$107="Yearly",D$125,0) -> 0 | E145: =IF(Projections!$C$107="Yearly",E$125,0) -> 0 | F145: =IF(Projections!$C$107="Yearly",F$125,0) -> 0 | G145: =IF(Projections!$C$107="Yearly",G$125,0) -> 0 | H145: =IF(Projections!$C$107="Yearly",H$125,0) -> 0 | I145: =IF(Projections!$C$107="Yearly",I$125,0) -> 0 | J145: =IF(Projections!$C$107="Yearly",J$125,0) -> 0 | K145: =IF(Projections!$C$107="Yearly",K$125,0) -> 0 | ... BK145: =IF(Projections!$C$107="Yearly",BK$125,0) -> 0
...

Sheet COGS
A1: =Settings!C5 -> VReeMind
A2: Operating Costs
A3: =+TODAY() -> 44143
E6: ='FS-Month'!D6 -> 43466 | F6: ='FS-Month'!E6 -> 43497 | G6: ='FS-Month'!F6 -> 43525 | H6: ='FS-Month'!G6 -> 43556 | I6: ='FS-Month'!H6 -> 43586 | J6: ='FS-Month'!I6 -> 43617 | K6: ='FS-Month'!J6 -> 43647 | L6: ='FS-Month'!K6 -> 43678 | ... DH6: ='FS-Month'!DG6 -> 46722
C7: Expense Category | D7: Unit | E7: ='FS-Month'!D7 -> 1 | F7: ='FS-Month'!E7 -> 2 | G7: ='FS-Month'!F7 -> 3 | H7: ='FS-Month'!G7 -> 4 | I7: ='FS-Month'!H7 -> 5 | J7: ='FS-Month'!I7 -> 6 | K7: ='FS-Month'!J7 -> 7 | L7: ='FS-Month'!K7 -> 8 | ... DH7: ='FS-Month'!DG7 -> 108
A9: KEY INDICATORS | E9: 0 | F9: 0 | G9: 0 | H9: 0 | I9: 0 | J9: 0 | K9: 0 | L9: 0 | M9: 0 | N9: 0 | O9: 0 | P9: 0 | Q9: 0 | R9: 0 | S9: 0 | T9: 0 | U9: 0 | V9: 0 | W9: 0 | X9: 0 | Y9: 0 | Z9: 2000 | AA9: 0 | AB9: 0 | AC9: 2200 | AD9: 0 | AE9: 0 | AF9: 2420 | AG9: 0 | AH9: 0 | AI9: 2662 | AJ9: 0 | AK9: 0 | AL9: 2928.2 | AM9: 0 | AN9: 0 | AO9: 3221.02 | AP9: 0 | AQ9: 0 | AR9: 3543.12 | AS9: 0 | AT9: 0 | AU9: 3897.4342 | AV9: 0 | AW9: 0 | AX9: 4287.1776 | AY9: 0 | AZ9: 0 | BA9: 4715.8954 | BB9: 0 | BC9: 0 | BD9: 5187.4849 | BE9: 0 | BF9: 0 | BG9: 5706.2334 | BH9: 0 | BI9: 0 | BJ9: 6276.8568 | BK9: 0 | BL9: 0 | BM9: 6904.5424 | BN9: 0 | BO9: 0 | BP9: 7594.9967 | BQ9: 0 | BR9: 0 | BS9: 8354.4963 | BT9: 0 | BU9: 0 | BV9: 9189.946 | BW9: 0 | BX9: 0 | BY9: 10108.941 | BZ9: 0 | CA9: 0 | CB9: 11119.835 | CC9: 0 | CD9: 0 | CE9: 12231.818 | CF9: 0 | CG9: 0 | CH9: 13455 | CI9: 0 | CJ9: 0 | CK9: 16146 | CL9: 0 | CM9: 0 | CN9: 19375.2 | CO9: 0 | CP9: 0 | CQ9: 23250.24 | CR9: 0 | CS9: 0 | CT9: 27900.288 | CU9: 0 | CV9: 0 | CW9: 33480.345 | CX9: 0 | CY9: 0 | CZ9: 40176.414 | DA9: 0 | DB9: 0 | DC9: 48211.697 | DD9: 0 | DE9: 0 | DF9: 57854.037 | DG9: 0 | DH9: 0 | DI9: 69424.844 | DJ9: 0 | DK9: 0 | DL9: 83309.813 | DM9: 0 | DN9: 0 | DO9: 99971.776 | DP9: 0 | DQ9: 0 | DR9: 119966.13 | DS9: 0 | DT9: 0 | DU9: 143959.36 | DV9: 0 | DW9: 0 | DX9: 172751.23 | DY9: 0 | DZ9: 0 | EA9: 207301.47 | EB9: 0 | EC9: 0 | ED9: 248761.77
A12: Average % of Tier 2 Tier 3 | B12: 0.57
A13: Avg # of Betterhelp sessions | B13: 4
A14: Cost Per session | B14: 45
A15: Averge per user | B15: =B14*B12*B13 -> 102.6
A17: CONSOLIDATED COGS
A19: =A25 -> CATEGORY #1: Hosting/Customer Service | D19: =Settings!$C$6 -> USD | E19: =E40 -> 0 | F19: =F40 -> 0 | G19: =G40 -> 0 | H19: =H40 -> 0 | I19: =I40 -> 0 | J19: =J40 -> 0 | K19: =K40 -> 0 | L19: =L40 -> 0 | ... DH19: =DH40 -> 39045.523
A20: =A43 -> CATEGORY #2: Partnership Commissions | D20: =Settings!$C$6 -> USD | E20: =E50 -> 0 | F20: =F50 -> 0 | G20: =G50 -> 0 | H20: =H50 -> 0 | I20: =I50 -> 0 | J20: =J50 -> 0 | K20: =K50 -> 0 | L20: =L50 -> 0 | ... DH20: =DH50 -> 0
A21: =A53 -> CATEGORY #3: App Store Fees | D21: =Settings!$C$6 -> USD | E21: =E60 -> 0 | F21: =F60 -> 0 | G21: =G60 -> 0 | H21: =H60 -> 0 | I21: =I60 -> 0 | J21: =J60 -> 0 | K21: =K60 -> 0 | L21: =L60 -> 0 | ... DH21: =DH60 -> 1758424.6
A22: Total COGS | D22: =Settings!$C$6 -> USD | E22: =SUM(E19:E21) -> 0 | F22: =SUM(F19:F21) -> 0 | G22: =SUM(G19:G21) -> 0 | H22: =SUM(H19:H21) -> 0 | I22: =SUM(I19:I21) -> 0 | J22: =SUM(J19:J21) -> 0 | K22: =SUM(K19:K21) -> 0 | L22: =SUM(L19:L21) -> 0 | ... DH22: =SUM(DH19:DH21) -> 1797470.1
A25: CATEGORY #1: Hosting/Customer Service
A27: AWS | C27: 0.01 | D27: =Settings!$C$6 -> USD | E27: =$C$27*E9 -> 0 | F27: =E27+(F9*$C$27) -> 0 | G27: =F27+(G9*$C$27) -> 0 | H27: =G27+(H9*$C$27) -> 0 | I27: =H27+(I9*$C$27) -> 0 | J27: =I27+(J9*$C$27) -> 0 | K27: =J27+(K9*$C$27) -> 0 | L27: =K27+(L9*$C$27) -> 0 | M27: =L27+(M9*$C$27) -> 0 | ... DH27: =DG27+(DH9*$C$27) -> 3943.9922
A28: Intercom | C28: 0.089 | D28: =Settings!$C$6 -> USD | E28: =$C$27*E9 -> 0 | F28: =E28+(F9*$C$28) -> 0 | G28: =F28+(G9*$C$28) -> 0 | H28: =G28+(H9*$C$28) -> 0 | I28: =H28+(I9*$C$28) -> 0 | J28: =I28+(J9*$C$28) -> 0 | K28: =J28+(K9*$C$28) -> 0 | L28: =K28+(L9*$C$28) -> 0 | M28: =L28+(M9*$C$28) -> 0 | ... DH28: =DG28+(DH9*$C$28) -> 35101.53
A29: Service 3 | D29: =Settings!$C$6 -> USD | E29: 0 | F29: =E29 -> 0 | G29: =F29 -> 0 | H29: =G29 -> 0 | I29: =H29 -> 0 | J29: =I29 -> 0 | K29: =J29 -> 0 | L29: =K29 -> 0 | M29: =L29 -> 0 | ... DH29: =DG29 -> 0
A30: Service 4 | D30: =Settings!$C$6 -> USD | E30: 0 | F30: =E30 -> 0 | G30: =F30 -> 0 | H30: =G30 -> 0 | I30: =H30 -> 0 | J30: =I30 -> 0 | K30: =J30 -> 0 | L30: =K30 -> 0 | M30: =L30 -> 0 | ... DH30: =DG30 -> 0
A31: Service 5 | D31: =Settings!$C$6 -> USD | E31: 0 | F31: =E31 -> 0 | G31: =F31 -> 0 | H31: =G31 -> 0 | I31: =H31 -> 0 | J31: =I31 -> 0 | K31: =J31 -> 0 | L31: =K31 -> 0 | M31: =L31 -> 0 | ... DH31: =DG31 -> 0
A32: Service 6 | D32: =Settings!$C$6 -> USD | E32: 0 | F32: =E32 -> 0 | G32: =F32 -> 0 | H32: =G32 -> 0 | I32: =H32 -> 0 | J32: =I32 -> 0 | K32: =J32 -> 0 | L32: =K32 -> 0 | M32: =L32 -> 0 | ... DH32: =DG32 -> 0
A33: Service 7 | D33: =Settings!$C$6 -> USD | E33: 0 | F33: =E33 -> 0 | G33: =F33 -> 0 | H33: =G33 -> 0 | I33: =H33 -> 0 | J33: =I33 -> 0 | K33: =J33 -> 0 | L33: =K33 -> 0 | M33: =L33 -> 0 | ... DH33: =DG33 -> 0
A34: Service 8 | D34: =Settings!$C$6 -> USD | E34: 0 | F34: =E34 -> 0 | G34: =F34 -> 0 | H34: =G34 -> 0 | I34: =H34 -> 0 | J34: =I34 -> 0 | K34: =J34 -> 0 | L34: =K34 -> 0 | M34: =L34 -> 0 | ... DH34: =DG34 -> 0
A35: Service 9 | D35: =Settings!$C$6 -> USD | E35: 0 | F35: =E35 -> 0 | G35: =F35 -> 0 | H35: =G35 -> 0 | I35: =H35 -> 0 | J35: =I35 -> 0 | K35: =J35 -> 0 | L35: =K35 -> 0 | M35: =L35 -> 0 | ... DH35: =DG35 -> 0
A36: Service 10 | D36: =Settings!$C$6 -> USD | E36: 0 | F36: =E36 -> 0 | G36: =F36 -> 0 | H36: =G36 -> 0 | I36: =H36 -> 0 | J36: =I36 -> 0 | K36: =J36 -> 0 | L36: =K36 -> 0 | M36: =L36 -> 0 | ... DH36: =DG36 -> 0
A37: Service 11 | D37: =Settings!$C$6 -> USD | E37: 0 | F37: =E37 -> 0 | G37: =F37 -> 0 | H37: =G37 -> 0 | I37: =H37 -> 0 | J37: =I37 -> 0 | K37: =J37 -> 0 | L37: =K37 -> 0 | M37: =L37 -> 0 | ... DH37: =DG37 -> 0
A38: Service 12 | D38: =Settings!$C$6 -> USD | E38: 0 | F38: =E38 -> 0 | G38: =F38 -> 0 | H38: =G38 -> 0 | I38: =H38 -> 0 | J38: =I38 -> 0 | K38: =J38 -> 0 | L38: =K38 -> 0 | M38: =L38 -> 0 | ... DH38: =DG38 -> 0
A39: Service 13 | D39: =Settings!$C$6 -> USD | E39: 0 | F39: =E39 -> 0 | G39: =F39 -> 0 | H39: =G39 -> 0 | I39: =H39 -> 0 | J39: =I39 -> 0 | K39: =J39 -> 0 | L39: =K39 -> 0 | M39: =L39 -> 0 | ... DH39: =DG39 -> 0
A40: Total | C40: Ops | D40: =Settings!$C$6 -> USD | E40: =SUM(E27:E39) -> 0 | F40: =SUM(F27:F39) -> 0 | G40: =SUM(G27:G39) -> 0 | H40: =SUM(H27:H39) -> 0 | I40: =SUM(I27:I39) -> 0 | J40: =SUM(J27:J39) -> 0 | K40: =SUM(K27:K39) -> 0 | L40: =SUM(L27:L39) -> 0 | ... DH40: =SUM(DH27:DH39) -> 39045.523
A43: CATEGORY #2: Partnership Commissions
A45: BETTERHELP TIER 2 | D45: =Settings!$C$6 -> USD | E45: 0 | F45: =E45 -> 0 | G45: =F45 -> 0 | H45: =G45 -> 0 | I45: =H45 -> 0 | J45: =I45 -> 0 | K45: =J45 -> 0 | L45: =K45 -> 0 | M45: =L45 -> 0 | ... DH45: =DG45 -> 0
A46: BETTERHELP TIER 3 | D46: =Settings!$C$6 -> USD | E46: 0 | F46: =E46 -> 0 | G46: =F46 -> 0 | H46: =G46 -> 0 | I46: =H46 -> 0 | J46: =I46 -> 0 | K46: =J46 -> 0 | L46: =K46 -> 0 | M46: =L46 -> 0 | ... DH46: =DG46 -> 0
A47: COST PER WEEK/SESSION | C47: 45 | D47: =Settings!$C$6 -> USD | E47: =(Revenue!D31*COGS!$B$12)*COGS!$B$13*$C$47 -> 0 | F47: =(Revenue!E31*COGS!$B$12)*COGS!$B$13*$C$47 -> 0 | G47: =(Revenue!F31*COGS!$B$12)*COGS!$B$13*$C$47 -> 0 | H47: =(Revenue!G31*COGS!$B$12)*COGS!$B$13*$C$47 -> 0 | I47: =(Revenue!H31*COGS!$B$12)*COGS!$B$13*$C$47 -> 0 | J47: =(Revenue!I31*COGS!$B$12)*COGS!$B$13*$C$47 -> 0 | K47: =(Revenue!J31*COGS!$B$12)*COGS!$B$13*$C$47 -> 0 | L47: =(Revenue!K31*COGS!$B$12)*COGS!$B$13*$C$47 -> 0 | ... DH47: =(Revenue!DG31*COGS!$B$12)*COGS!$B$13*$C$47 -> 0
A48: COST PER WEEK/SESSION | C48: 45 | D48: =Settings!$C$6 -> USD | E48: =(Revenue!D32*COGS!$B$12)*COGS!$B$13*$C$48 -> 0 | F48: =(Revenue!E32*COGS!$B$12)*COGS!$B$13*$C$48 -> 0 | G48: =(Revenue!F32*COGS!$B$12)*COGS!$B$13*$C$48 -> 0 | H48: =(Revenue!G32*COGS!$B$12)*COGS!$B$13*$C$48 -> 0 | I48: =(Revenue!H32*COGS!$B$12)*COGS!$B$13*$C$48 -> 0 | J48: =(Revenue!I32*COGS!$B$12)*COGS!$B$13*$C$48 -> 0 | K48: =(Revenue!J32*COGS!$B$12)*COGS!$B$13*$C$48 -> 0 | L48: =(Revenue!K32*COGS!$B$12)*COGS!$B$13*$C$48 -> 0 | ... DH48: =(Revenue!DG32*COGS!$B$12)*COGS!$B$13*$C$48 -> 0
A49: IPSOFT | C49: 0.05 | D49: =Settings!$C$6 -> USD | E49: =$C$49*Revenue!D55 -> 0 | F49: =$C$49*Revenue!E55 -> 0 | G49: =$C$49*Revenue!F55 -> 0 | H49: =$C$49*Revenue!G55 -> 0 | I49: =$C$49*Revenue!H55 -> 0 | J49: =$C$49*Revenue!I55 -> 0 | K49: =$C$49*Revenue!J55 -> 0 | L49: =$C$49*Revenue!K55 -> 0 | ... DH49: =$C$49*Revenue!DG55 -> 0
A50: Total | C50: Ops | D50: =Settings!$C$6 -> USD | E50: =SUM(E45:E49) -> 0 | F50: =SUM(F45:F49) -> 0 | G50: =SUM(G45:G49) -> 0 | H50: =SUM(H45:H49) -> 0 | I50: =SUM(I45:I49) -> 0 | J50: =SUM(J45:J49) -> 0 | K50: =SUM(K45:K49) -> 0 | L50: =SUM(L45:L49) -> 0 | ... DH50: =SUM(DH45:DH49) -> 0
A53: CATEGORY #3: App Store Fees
A57: App Store Commission | C57: 0.3 | D57: =Settings!$C$6 -> USD | E57: =$C$57*Revenue!D21 -> 0 | F57: =$C$57*Revenue!E21 -> 0 | G57: =$C$57*Revenue!F21 -> 0 | H57: =$C$57*Revenue!G21 -> 0 | I57: =$C$57*Revenue!H21 -> 0 | J57: =$C$57*Revenue!I21 -> 0 | K57: =$C$57*Revenue!J21 -> 0 | L57: =$C$57*Revenue!K21 -> 0 | ... DH57: =$C$57*Revenue!DG21 -> 1758424.6
A58: Stripe | C58: 0 | D58: =Settings!$C$6 -> USD | E58: =$C$57*Revenue!D55 -> 0 | F58: =$C$57*Revenue!E55 -> 0 | G58: =$C$57*Revenue!F55 -> 0 | H58: =$C$57*Revenue!G55 -> 0 | I58: =$C$57*Revenue!H55 -> 0 | J58: =$C$57*Revenue!I55 -> 0 | K58: =$C$57*Revenue!J55 -> 0 | L58: =$C$57*Revenue!K55 -> 0 | ... P58: =$C$57*Revenue!O55 -> 0 | Q58: =$C$58*Revenue!P55 -> 0 | R58: =$C$58*Revenue!Q55 -> 0 | S58: =$C$58*Revenue!R55 -> 0 | T58: =$C$58*Revenue!S55 -> 0 | U58: =$C$58*Revenue!T55 -> 0 | V58: =$C$58*Revenue!U55 -> 0 | W58: =$C$58*Revenue!V55 -> 0 | X58: =$C$58*Revenue!W55 -> 0 | ... DH58: =$C$58*Revenue!DG55 -> 0
A59: Service 3 | D59: =Settings!$C$6 -> USD | E59: 0 | F59: =E59 -> 0 | G59: =F59 -> 0 | H59: =G59 -> 0 | I59: =H59 -> 0 | J59: =I59 -> 0 | K59: =J59 -> 0 | L59: =K59 -> 0 | M59: =L59 -> 0 | ... DH59: =DG59 -> 0
A60: Total | C60: Ops | D60: =Settings!$C$6 -> USD | E60: =SUM(E57:E59) -> 0 | F60: =SUM(F57:F59) -> 0 | G60: =SUM(G57:G59) -> 0 | H60: =SUM(H57:H59) -> 0 | I60: =SUM(I57:I59) -> 0 | J60: =SUM(J57:J59) -> 0 | K60: =SUM(K57:K59) -> 0 | L60: =SUM(L57:L59) -> 0 | ... DH60: =SUM(DH57:DH59) -> 1758424.6

Sheet SG&A
A1: =Settings!C5 -> VReeMind
A2: Operating Expenses
A3: =+TODAY() -> 44143
F6: ='FS-Month'!D6 -> 43466 | G6: ='FS-Month'!E6 -> 43497 | H6: ='FS-Month'!F6 -> 43525 | I6: ='FS-Month'!G6 -> 43556 | J6: ='FS-Month'!H6 -> 43586 | K6: ='FS-Month'!I6 -> 43617 | L6: ='FS-Month'!J6 -> 43647 | M6: ='FS-Month'!K6 -> 43678 | ... DI6: ='FS-Month'!DG6 -> 46722
D7: Expense Category | E7: Unit | F7: ='FS-Month'!D7 -> 1 | G7: ='FS-Month'!E7 -> 2 | H7: ='FS-Month'!F7 -> 3 | I7: ='FS-Month'!G7 -> 4 | J7: ='FS-Month'!H7 -> 5 | K7: ='FS-Month'!I7 -> 6 | L7: ='FS-Month'!J7 -> 7 | M7: ='FS-Month'!K7 -> 8 | ... DI7: ='FS-Month'!DG7 -> 108
A9: KEY INDICATORS
A21: CONSOLIDATED SG&A
A22: =A32 -> PAYROLL | E22: =Settings!$C$6 -> USD | F22: =F89 -> 11458.333 | G22: =G89 -> 6875 | H22: =H89 -> 6875 | I22: =I89 -> 11458.333 | J22: =J89 -> 11458.333 | K22: =K89 -> 11458.333 | L22: =L89 -> 13750 | M22: =M89 -> 13750 | ... DI22: =DI89 -> 169176.13
A23: =A163 -> MARKETING & GROWTH | E23: =Settings!$C$6 -> USD | F23: =F209 -> 0 | G23: =G209 -> 0 | H23: =H209 -> 3000 | I23: =I209 -> 3000 | J23: =J209 -> 3000 | K23: =K209 -> 3000 | L23: =L209 -> 3000 | M23: =M209 -> 3000 | ... DI23: =DI209 -> 40000
A24: =A215 -> LEGAL, ADVISORY, PROF. SERVICES | E24: =Settings!$C$6 -> USD | F24: =F229 -> 0 | G24: =G229 -> 0 | H24: =H229 -> 0 | I24: =I229 -> 1500 | J24: =J229 -> 1500 | K24: =K229 -> 1500 | L24: =L229 -> 1500 | M24: =M229 -> 1500 | ... Q24: =Q229 -> 4000 | R24: 5000 | S24: =S229 -> 1500 | T24: =T229 -> 1500 | U24: =U229 -> 1500 | V24: =V229 -> 1500 | W24: =W229 -> 51500 | X24: =X229 -> 1500 | Y24: =Y229 -> 1500 | Z24: =Z229 -> 1500 | ... DI24: =DI229 -> 7000
A25: =A235 -> WFA Stipend | E25: =Settings!$C$6 -> USD | F25: =F239 -> 9000 | G25: =G239 -> 0 | H25: =H239 -> 0 | I25: =I239 -> 6000 | J25: =J239 -> 0 | K25: =K239 -> 0 | L25: =L239 -> 3000 | M25: =M239 -> 0 | ... DI25: =DI239 -> 0
A26: =A245 -> TECH SUPPORT & SERVICES | E26: =Settings!$C$6 -> USD | F26: =F266 -> 0 | G26: =G266 -> 0 | H26: =H266 -> 0 | I26: =I266 -> 0 | J26: =J266 -> 0 | K26: =K266 -> 221.25 | L26: =L266 -> 250.5 | M26: =M266 -> 250.5 | ... DI26: =DI266 -> 1537.5
A27: =A270 -> INSURANCE | E27: =Settings!$C$6 -> USD | F27: =F274 -> 0 | G27: =G274 -> 0 | H27: =H274 -> 0 | I27: =I274 -> 0 | J27: =J274 -> 0 | K27: =K274 -> 0 | L27: =L274 -> 0 | M27: =M274 -> 0 | ... DI27: =DI274 -> 2000
A28: =A277 -> 0 | E28: =Settings!$C$6 -> USD | F28: =F283 -> 0 | G28: =G283 -> 0 | H28: =H283 -> 0 | I28: =I283 -> 0 | J28: =J283 -> 0 | K28: =K283 -> 0 | L28: =L283 -> 0 | M28: =M283 -> 0 | ... DI28: =DI283 -> 0
A29: =A286 -> OTHER EXPENSES | E29: =Settings!$C$6 -> USD | F29: =F291 -> 0 | G29: =G291 -> 0 | H29: =H291 -> 0 | I29: =I291 -> 0 | J29: =J291 -> 0 | K29: =K291 -> 0 | L29: =L291 -> 0 | M29: =M291 -> 0 | ... DI29: =DI291 -> 0
A30: Total | E30: =Settings!$C$6 -> USD | F30: =SUM(F22:F29) -> 20458.333 | G30: =SUM(G22:G29) -> 6875 | H30: =SUM(H22:H29) -> 9875 | I30: =SUM(I22:I29) -> 21958.333 | J30: =SUM(J22:J29) -> 15958.333 | K30: =SUM(K22:K29) -> 16179.583 | L30: =SUM(L22:L29) -> 21500.5 | M30: =SUM(M22:M29) -> 18500.5 | ... DI30: =SUM(DI22:DI29) -> 219713.63
A31: Expenses Running total | Q31: =SUM(F30:Q30) -> 220770.33 | R31: =SUM(G30:R30) -> 241150.25 | S31: =SUM(H30:S30) -> 287034.67 | T31: =SUM(I30:T30) -> 317919.08 | U31: =SUM(J30:U30) -> 343416.08 | V31: =SUM(K30:V30) -> 371913.08 | W31: =SUM(L30:W30) -> 450188.83 | X31: =SUM(M30:X30) -> 473143.67 | ... DI31: =SUM(CX30:DI30) -> 2567837.2
A32: PAYROLL
A33: =A95 -> Operations
A34: =A96 -> CEO | D34: ='Team & Salaries'!B6 -> Ops | E34: =Settings!$C$6 -> USD | F34: ='Team & Salaries'!$D11*F96 -> 4583.3333 | G34: =('Team & Salaries'!$D6*G96)*((1+'Team & Salaries'!$Q6)^(ROUNDDOWN((COUNTIF(E34:$E34,">0")/12),0))) -> 2291.6667 | H34: =('Team & Salaries'!$D6*H96)*((1+'Team & Salaries'!$Q6)^(ROUNDDOWN((COUNTIF($E34:F34,">0")/12),0))) -> 2291.6667 | I34: =('Team & Salaries'!$D6*I96)*((1+'Team & Salaries'!$Q6)^(ROUNDDOWN((COUNTIF($E34:G34,">0")/12),0))) -> 2291.6667 | J34: =('Team & Salaries'!$D6*J96)*((1+'Team & Salaries'!$Q6)^(ROUNDDOWN((COUNTIF($E34:H34,">0")/12),0))) -> 2291.6667 | K34: =('Team & Salaries'!$D6*K96)*((1+'Team & Salaries'!$Q6)^(ROUNDDOWN((COUNTIF($E34:I34,">0")/12),0))) -> 2291.6667 | L34: =('Team & Salaries'!$D6*L96)*((1+'Team & Salaries'!$Q6)^(ROUNDDOWN((COUNTIF($E34:J34,">0")/12),0))) -> 2291.6667 | M34: =('Team & Salaries'!$D6*M96)*((1+'Team & Salaries'!$Q6)^(ROUNDDOWN((COUNTIF($E34:K34,">0")/12),0))) -> 2291.6667 | N34: =('Team & Salaries'!$D6*N96)*((1+'Team & Salaries'!$Q6)^(ROUNDDOWN((COUNTIF($E34:L34,">0")/12),0))) -> 2291.6667 | O34: =('Team & Salaries'!$D6*O96)*((1+'Team & Salaries'!$Q6)^(ROUNDDOWN((COUNTIF($E34:M34,">0")/12),0))) -> 2291.6667 | ... DI34: =('Team & Salaries'!$D6*DI96)*((1+'Team & Salaries'!$Q6)^(ROUNDDOWN((COUNTIF($E34:DG34,">0")/12),0))) -> 2903.0148
A35: =A97 -> UX Research | D35: ='Team & Salaries'!B7 -> Ops | E35: =Settings!$C$6 -> USD | F35: ='Team & Salaries'!$D12*F97 -> 4583.3333 | G35: =('Team & Salaries'!$D7*G97)*((1+'Team & Salaries'!$Q7)^(ROUNDDOWN((COUNTIF(E35:$E35,">0")/12),0))) -> 2291.6667 | H35: =('Team & Salaries'!$D7*H97)*((1+'Team & Salaries'!$Q7)^(ROUNDDOWN((COUNTIF($E35:F35,">0")/12),0))) -> 2291.6667 | I35: =('Team & Salaries'!$D7*I97)*((1+'Team & Salaries'!$Q7)^(ROUNDDOWN((COUNTIF($E35:G35,">0")/12),0))) -> 2291.6667 | J35: =('Team & Salaries'!$D7*J97)*((1+'Team & Salaries'!$Q7)^(ROUNDDOWN((COUNTIF($E35:H35,">0")/12),0))) -> 2291.6667 | K35: =('Team & Salaries'!$D7*K97)*((1+'Team & Salaries'!$Q7)^(ROUNDDOWN((COUNTIF($E35:I35,">0")/12),0))) -> 2291.6667 | L35: =('Team & Salaries'!$D7*L97)*((1+'Team & Salaries'!$Q7)^(ROUNDDOWN((COUNTIF($E35:J35,">0")/12),0))) -> 2291.6667 | M35: =('Team & Salaries'!$D7*M97)*((1+'Team & Salaries'!$Q7)^(ROUNDDOWN((COUNTIF($E35:K35,">0")/12),0))) -> 2291.6667 | N35: =('Team & Salaries'!$D7*N97)*((1+'Team & Salaries'!$Q7)^(ROUNDDOWN((COUNTIF($E35:L35,">0")/12),0))) -> 2291.6667 | O35: =('Team & Salaries'!$D7*O97)*((1+'Team & Salaries'!$Q7)^(ROUNDDOWN((COUNTIF($E35:M35,">0")/12),0))) -> 2291.6667 | ... DI35: =('Team & Salaries'!$D7*DI97)*((1+'Team & Salaries'!$Q7)^(ROUNDDOWN((COUNTIF($E35:DG35,">0")/12),0))) -> 2903.0148
A36: =A98 -> CFO | D36: ='Team & Salaries'!B8 -> Ops | E36: =Settings!$C$6 -> USD | F36: ='Team & Salaries'!$D13*F98 -> 0 | G36: =('Team & Salaries'!$D8*G98)*((1+'Team & Salaries'!$Q8)^(ROUNDDOWN((COUNTIF(E36:$E36,">0")/12),0))) -> 0 | H36: =('Team & Salaries'!$D8*H98)*((1+'Team & Salaries'!$Q8)^(ROUNDDOWN((COUNTIF($E36:F36,">0")/12),0))) -> 0 | I36: =('Team & Salaries'!$D8*I98)*((1+'Team & Salaries'!$Q8)^(ROUNDDOWN((COUNTIF($E36:G36,">0")/12),0))) -> 0 | J36: =('Team & Salaries'!$D8*J98)*((1+'Team & Salaries'!$Q8)^(ROUNDDOWN((COUNTIF($E36:H36,">0")/12),0))) -> 0 | K36: =('Team & Salaries'!$D8*K98)*((1+'Team & Salaries'!$Q8)^(ROUNDDOWN((COUNTIF($E36:I36,">0")/12),0))) -> 0 | L36: =('Team & Salaries'!$D8*L98)*((1+'Team & Salaries'!$Q8)^(ROUNDDOWN((COUNTIF($E36:J36,">0")/12),0))) -> 0 | M36: =('Team & Salaries'!$D8*M98)*((1+'Team & Salaries'!$Q8)^(ROUNDDOWN((COUNTIF($E36:K36,">0")/12),0))) -> 0 | N36: =('Team & Salaries'!$D8*N98)*((1+'Team & Salaries'!$Q8)^(ROUNDDOWN((COUNTIF($E36:L36,">0")/12),0))) -> 0 | O36: =('Team & Salaries'!$D8*O98)*((1+'Team & Salaries'!$Q8)^(ROUNDDOWN((COUNTIF($E36:M36,">0")/12),0))) -> 0 | ... DI36: =('Team & Salaries'!$D8*DI98)*((1+'Team & Salaries'!$Q8)^(ROUNDDOWN((COUNTIF($E36:DG36,">0")/12),0))) -> 2736.3698
A37: =A99 -> Intern | D37: ='Team & Salaries'!B9 -> Ops | E37: =Settings!$C$6 -> USD | F37: ='Team & Salaries'!$D14*F99 -> 0 | G37: =('Team & Salaries'!$D9*G99)*((1+'Team & Salaries'!$Q9)^(ROUNDDOWN((COUNTIF(E37:$E37,">0")/12),0))) -> 0 | H37: =('Team & Salaries'!$D9*H99)*((1+'Team & Salaries'!$Q9)^(ROUNDDOWN((COUNTIF($E37:F37,">0")/12),0))) -> 0 | I37: =('Team & Salaries'!$D9*I99)*((1+'Team & Salaries'!$Q9)^(ROUNDDOWN((COUNTIF($E37:G37,">0")/12),0))) -> 0 | J37: =('Team & Salaries'!$D9*J99)*((1+'Team & Salaries'!$Q9)^(ROUNDDOWN((COUNTIF($E37:H37,">0")/12),0))) -> 0 | K37: =('Team & Salaries'!$D9*K99)*((1+'Team & Salaries'!$Q9)^(ROUNDDOWN((COUNTIF($E37:I37,">0")/12),0))) -> 0 | L37: =('Team & Salaries'!$D9*L99)*((1+'Team & Salaries'!$Q9)^(ROUNDDOWN((COUNTIF($E37:J37,">0")/12),0))) -> 0 | M37: =('Team & Salaries'!$D9*M99)*((1+'Team & Salaries'!$Q9)^(ROUNDDOWN((COUNTIF($E37:K37,">0")/12),0))) -> 0 | N37: =('Team & Salaries'!$D9*N99)*((1+'Team & Salaries'!$Q9)^(ROUNDDOWN((COUNTIF($E37:L37,">0")/12),0))) -> 0 | O37: =('Team & Salaries'!$D9*O99)*((1+'Team & Salaries'!$Q9)^(ROUNDDOWN((COUNTIF($E37:M37,">0")/12),0))) -> 0 | ... DI37: =('Team & Salaries'!$D9*DI99)*((1+'Team & Salaries'!$Q9)^(ROUNDDOWN((COUNTIF($E37:DG37,">0")/12),0))) -> 2736.3698
A38: =A100 -> CEO 2 | D38: ='Team & Salaries'!B10 -> Ops | E38: =Settings!$C$6 -> USD | F38: ='Team & Salaries'!$D15*F100 -> 0 | G38: =('Team & Salaries'!$D10*G100)*((1+'Team & Salaries'!$Q10)^(ROUNDDOWN((COUNTIF(E38:$E38,">0")/12),0))) -> 0 | H38: =('Team & Salaries'!$D10*H100)*((1+'Team & Salaries'!$Q10)^(ROUNDDOWN((COUNTIF($E38:F38,">0")/12),0))) -> 0 | I38: =('Team & Salaries'!$D10*I100)*((1+'Team & Salaries'!$Q10)^(ROUNDDOWN((COUNTIF($E38:G38,">0")/12),0))) -> 0 | J38: =('Team & Salaries'!$D10*J100)*((1+'Team & Salaries'!$Q10)^(ROUNDDOWN((COUNTIF($E38:H38,">0")/12),0))) -> 0 | K38: =('Team & Salaries'!$D10*K100)*((1+'Team & Salaries'!$Q10)^(ROUNDDOWN((COUNTIF($E38:I38,">0")/12),0))) -> 0 | L38: =('Team & Salaries'!$D10*L100)*((1+'Team & Salaries'!$Q10)^(ROUNDDOWN((COUNTIF($E38:J38,">0")/12),0))) -> 0 | M38: =('Team & Salaries'!$D10*M100)*((1+'Team & Salaries'!$Q10)^(ROUNDDOWN((COUNTIF($E38:K38,">0")/12),0))) -> 0 | N38: =('Team & Salaries'!$D10*N100)*((1+'Team & Salaries'!$Q10)^(ROUNDDOWN((COUNTIF($E38:L38,">0")/12),0))) -> 0 | O38: =('Team & Salaries'!$D10*O100)*((1+'Team & Salaries'!$Q10)^(ROUNDDOWN((COUNTIF($E38:M38,">0")/12),0))) -> 0 | ... DI38: =('Team & Salaries'!$D10*DI100)*((1+'Team & Salaries'!$Q10)^(ROUNDDOWN((COUNTIF($E38:DG38,">0")/12),0))) -> 5849.6238
A39: =A101 -> CFO 2 | D39: ='Team & Salaries'!B11 -> Ops | E39: =Settings!$C$6 -> USD | F39: ='Team & Salaries'!$D16*F101 -> 0 | G39: =('Team & Salaries'!$D11*G101)*((1+'Team & Salaries'!$Q11)^(ROUNDDOWN((COUNTIF(E39:$E39,">0")/12),0))) -> 0 | H39: =('Team & Salaries'!$D11*H101)*((1+'Team & Salaries'!$Q11)^(ROUNDDOWN((COUNTIF($E39:F39,">0")/12),0))) -> 0 | I39: =('Team & Salaries'!$D11*I101)*((1+'Team & Salaries'!$Q11)^(ROUNDDOWN((COUNTIF($E39:G39,">0")/12),0))) -> 0 | J39: =('Team & Salaries'!$D11*J101)*((1+'Team & Salaries'!$Q11)^(ROUNDDOWN((COUNTIF($E39:H39,">0")/12),0))) -> 0 | K39: =('Team & Salaries'!$D11*K101)*((1+'Team & Salaries'!$Q11)^(ROUNDDOWN((COUNTIF($E39:I39,">0")/12),0))) -> 0 | L39: =('Team & Salaries'!$D11*L101)*((1+'Team & Salaries'!$Q11)^(ROUNDDOWN((COUNTIF($E39:J39,">0")/12),0))) -> 0 | M39: =('Team & Salaries'!$D11*M101)*((1+'Team & Salaries'!$Q11)^(ROUNDDOWN((COUNTIF($E39:K39,">0")/12),0))) -> 0 | N39: =('Team & Salaries'!$D11*N101)*((1+'Team & Salaries'!$Q11)^(ROUNDDOWN((COUNTIF($E39:L39,">0")/12),0))) -> 0 | O39: =('Team & Salaries'!$D11*O101)*((1+'Team & Salaries'!$Q11)^(ROUNDDOWN((COUNTIF($E39:M39,">0")/12),0))) -> 0 | ... DI39: =('Team & Salaries'!$D11*DI101)*((1+'Team & Salaries'!$Q11)^(ROUNDDOWN((COUNTIF($E39:DG39,">0")/12),0))) -> 5849.6238
A40: =A102 -> CTO 2 | D40: ='Team & Salaries'!B12 -> Ops | E40: =Settings!$C$6 -> USD | F40: ='Team & Salaries'!$D17*F102 -> 0 | G40: =('Team & Salaries'!$D12*G102)*((1+'Team & Salaries'!$Q12)^(ROUNDDOWN((COUNTIF(E40:$E40,">0")/12),0))) -> 0 | H40: =('Team & Salaries'!$D12*H102)*((1+'Team & Salaries'!$Q12)^(ROUNDDOWN((COUNTIF($E40:F40,">0")/12),0))) -> 0 | I40: =('Team & Salaries'!$D12*I102)*((1+'Team & Salaries'!$Q12)^(ROUNDDOWN((COUNTIF($E40:G40,">0")/12),0))) -> 0 | J40: =('Team & Salaries'!$D12*J102)*((1+'Team & Salaries'!$Q12)^(ROUNDDOWN((COUNTIF($E40:H40,">0")/12),0))) -> 0 | K40: =('Team & Salaries'!$D12*K102)*((1+'Team & Salaries'!$Q12)^(ROUNDDOWN((COUNTIF($E40:I40,">0")/12),0))) -> 0 | L40: =('Team & Salaries'!$D12*L102)*((1+'Team & Salaries'!$Q12)^(ROUNDDOWN((COUNTIF($E40:J40,">0")/12),0))) -> 0 | M40: =('Team & Salaries'!$D12*M102)*((1+'Team & Salaries'!$Q12)^(ROUNDDOWN((COUNTIF($E40:K40,">0")/12),0))) -> 0 | N40: =('Team & Salaries'!$D12*N102)*((1+'Team & Salaries'!$Q12)^(ROUNDDOWN((COUNTIF($E40:L40,">0")/12),0))) -> 0 | O40: =('Team & Salaries'!$D12*O102)*((1+'Team & Salaries'!$Q12)^(ROUNDDOWN((COUNTIF($E40:M40,">0")/12),0))) -> 0 | ... DI40: =('Team & Salaries'!$D12*DI102)*((1+'Team & Salaries'!$Q12)^(ROUNDDOWN((COUNTIF($E40:DG40,">0")/12),0))) -> 5849.6238
A41: =A103 -> CMO 2 | D41: ='Team & Salaries'!B13 -> Ops | E41: =Settings!$C$6 -> USD | F41: ='Team & Salaries'!$D18*F103 -> 0 | G41: =('Team & Salaries'!$D13*G103)*((1+'Team & Salaries'!$Q13)^(ROUNDDOWN((COUNTIF(E41:$E41,">0")/12),0))) -> 0 | H41: =('Team & Salaries'!$D13*H103)*((1+'Team & Salaries'!$Q13)^(ROUNDDOWN((COUNTIF($E41:F41,">0")/12),0))) -> 0 | I41: =('Team & Salaries'!$D13*I103)*((1+'Team & Salaries'!$Q13)^(ROUNDDOWN((COUNTIF($E41:G41,">0")/12),0))) -> 0 | J41: =('Team & Salaries'!$D13*J103)*((1+'Team & Salaries'!$Q13)^(ROUNDDOWN((COUNTIF($E41:H41,">0")/12),0))) -> 0 | K41: =('Team & Salaries'!$D13*K103)*((1+'Team & Salaries'!$Q13)^(ROUNDDOWN((COUNTIF($E41:I41,">0")/12),0))) -> 0 | L41: =('Team & Salaries'!$D13*L103)*((1+'Team & Salaries'!$Q13)^(ROUNDDOWN((COUNTIF($E41:J41,">0")/12),0))) -> 0 | M41: =('Team & Salaries'!$D13*M103)*((1+'Team & Salaries'!$Q13)^(ROUNDDOWN((COUNTIF($E41:K41,">0")/12),0))) -> 0 | N41: =('Team & Salaries'!$D13*N103)*((1+'Team & Salaries'!$Q13)^(ROUNDDOWN((COUNTIF($E41:L41,">0")/12),0))) -> 0 | O41: =('Team & Salaries'!$D13*O103)*((1+'Team & Salaries'!$Q13)^(ROUNDDOWN((COUNTIF($E41:M41,">0")/12),0))) -> 0 | ... DI41: =('Team & Salaries'!$D13*DI103)*((1+'Team & Salaries'!$Q13)^(ROUNDDOWN((COUNTIF($E41:DG41,">0")/12),0))) -> 5849.6238
A44: =A106 -> Product
A45: =A107 -> CTO | D45: ='Team & Salaries'!B17 -> Prod | E45: =Settings!$C$6 -> USD | F45: ='Team & Salaries'!$D17*F107 -> 2291.6667 | G45: ='Team & Salaries'!$D17*G107 -> 2291.6667 | H45: ='Team & Salaries'!$D17*H107 -> 2291.6667 | I45: ='Team & Salaries'!$D17*I107 -> 2291.6667 | J45: ='Team & Salaries'!$D17*J107 -> 2291.6667 | K45: ='Team & Salaries'!$D17*K107 -> 2291.6667 | L45: ='Team & Salaries'!$D17*L107 -> 2291.6667 | M45: ='Team & Salaries'!$D17*M107 -> 2291.6667 | ... DI45: ='Team & Salaries'!$D17*DI107 -> 2291.6667
A46: =A108 -> 3D Design | D46: ='Team & Salaries'!B18 -> Prod | E46: =Settings!$C$6 -> USD | F46: ='Team & Salaries'!$D18*F108 -> 0 | G46: ='Team & Salaries'!$D18*G108 -> 0 | H46: ='Team & Salaries'!$D18*H108 -> 0 | I46: ='Team & Salaries'!$D18*I108 -> 0 | J46: ='Team & Salaries'!$D18*J108 -> 0 | K46: ='Team & Salaries'!$D18*K108 -> 0 | L46: ='Team & Salaries'!$D18*L108 -> 2291.6667 | M46: ='Team & Salaries'!$D18*M108 -> 2291.6667 | ... DI46: ='Team & Salaries'!$D18*DI108 -> 2291.6667
A47: =A109 -> 3D Design | D47: ='Team & Salaries'!B19 -> Prod | E47: =Settings!$C$6 -> USD | F47: ='Team & Salaries'!$D19*F109 -> 0 | G47: ='Team & Salaries'!$D19*G109 -> 0 | H47: ='Team & Salaries'!$D19*H109 -> 0 | I47: ='Team & Salaries'!$D19*I109 -> 0 | J47: ='Team & Salaries'!$D19*J109 -> 0 | K47: ='Team & Salaries'!$D19*K109 -> 0 | L47: ='Team & Salaries'!$D19*L109 -> 0 | M47: ='Team & Salaries'!$D19*M109 -> 0 | ... DI47: ='Team & Salaries'!$D19*DI109 -> 2291.6667
A48: =A110 -> 3D Design | D48: ='Team & Salaries'!B20 -> Prod | E48: =Settings!$C$6 -> USD | F48: ='Team & Salaries'!$D20*F110 -> 0 | G48: ='Team & Salaries'!$D20*G110 -> 0 | H48: ='Team & Salaries'!$D20*H110 -> 0 | I48: ='Team & Salaries'!$D20*I110 -> 0 | J48: ='Team & Salaries'!$D20*J110 -> 0 | K48: ='Team & Salaries'!$D20*K110 -> 0 | L48: ='Team & Salaries'!$D20*L110 -> 0 | M48: ='Team & Salaries'!$D20*M110 -> 0 | ... DI48: ='Team & Salaries'!$D20*DI110 -> 2291.6667
A49: =A111 -> 3D Design | D49: ='Team & Salaries'!B21 -> Prod | E49: =Settings!$C$6 -> USD | F49: ='Team & Salaries'!$D21*F111 -> 0 | G49: ='Team & Salaries'!$D21*G111 -> 0 | H49: ='Team & Salaries'!$D21*H111 -> 0 | I49: ='Team & Salaries'!$D21*I111 -> 0 | J49: ='Team & Salaries'!$D21*J111 -> 0 | K49: ='Team & Salaries'!$D21*K111 -> 0 | L49: ='Team & Salaries'!$D21*L111 -> 0 | M49: ='Team & Salaries'!$D21*M111 -> 0 | ... DI49: ='Team & Salaries'!$D21*DI111 -> 6875
A50: =A112 -> 3D Design | D50: ='Team & Salaries'!B22 -> Prod | E50: =Settings!$C$6 -> USD | F50: ='Team & Salaries'!$D22*F112 -> 0 | G50: ='Team & Salaries'!$D22*G112 -> 0 | H50: ='Team & Salaries'!$D22*H112 -> 0 | I50: ='Team & Salaries'!$D22*I112 -> 0 | J50: ='Team & Salaries'!$D22*J112 -> 0 | K50: ='Team & Salaries'!$D22*K112 -> 0 | L50: ='Team & Salaries'!$D22*L112 -> 0 | M50: ='Team & Salaries'!$D22*M112 -> 0 | ... DI50: ='Team & Salaries'!$D22*DI112 -> 6875
A51: =A113 -> Mobile Dev | D51: ='Team & Salaries'!B23 -> Prod | E51: =Settings!$C$6 -> USD | F51: ='Team & Salaries'!$D23*F113 -> 0 | G51: ='Team & Salaries'!$D23*G113 -> 0 | H51: ='Team & Salaries'!$D23*H113 -> 0 | I51: ='Team & Salaries'!$D23*I113 -> 0 | J51: ='Team & Salaries'!$D23*J113 -> 0 | K51: ='Team & Salaries'!$D23*K113 -> 0 | L51: ='Team & Salaries'!$D23*L113 -> 0 | M51: ='Team & Salaries'!$D23*M113 -> 0 | ... DI51: ='Team & Salaries'!$D23*DI113 -> 6875
A52: =A114 -> Mobile Dev | D52: ='Team & Salaries'!B24 -> Prod | E52: =Settings!$C$6 -> USD | F52: ='Team & Salaries'!$D24*F114 -> 0 | G52: ='Team & Salaries'!$D24*G114 -> 0 | H52: ='Team & Salaries'!$D24*H114 -> 0 | I52: ='Team & Salaries'!$D24*I114 -> 2291.6667 | J52: ='Team & Salaries'!$D24*J114 -> 2291.6667 | K52: ='Team & Salaries'!$D24*K114 -> 2291.6667 | L52: ='Team & Salaries'!$D24*L114 -> 2291.6667 | M52: ='Team & Salaries'!$D24*M114 -> 2291.6667 | ... DI52: ='Team & Salaries'!$D24*DI114 -> 2291.6667
A53: =A115 -> Mobile Dev | D53: ='Team & Salaries'!B25 -> Prod | E53: =Settings!$C$6 -> USD | F53: ='Team & Salaries'!$D25*F115 -> 0 | G53: ='Team & Salaries'!$D25*G115 -> 0 | H53: ='Team & Salaries'!$D25*H115 -> 0 | I53: ='Team & Salaries'!$D25*I115 -> 2291.6667 | J53: ='Team & Salaries'!$D25*J115 -> 2291.6667 | K53: ='Team & Salaries'!$D25*K115 -> 2291.6667 | L53: ='Team & Salaries'!$D25*L115 -> 2291.6667 | M53: ='Team & Salaries'!$D25*M115 -> 2291.6667 | ... DI53: ='Team & Salaries'!$D25*DI115 -> 2291.6667
A54: =A116 -> Mobile Dev | D54: ='Team & Salaries'!B26 -> Prod | E54: =Settings!$C$6 -> USD | F54: ='Team & Salaries'!$D26*F116 -> 0 | G54: ='Team & Salaries'!$D26*G116 -> 0 | H54: ='Team & Salaries'!$D26*H116 -> 0 | I54: ='Team & Salaries'!$D26*I116 -> 0 | J54: ='Team & Salaries'!$D26*J116 -> 0 | K54: ='Team & Salaries'!$D26*K116 -> 0 | L54: ='Team & Salaries'!$D26*L116 -> 0 | M54: ='Team & Salaries'!$D26*M116 -> 0 | ... DI54: ='Team & Salaries'!$D26*DI116 -> 2291.6667
A55: =A117 -> Mobile Dev | D55: ='Team & Salaries'!B27 -> Prod | E55: =Settings!$C$6 -> USD | F55: ='Team & Salaries'!$D27*F117 -> 0 | G55: ='Team & Salaries'!$D27*G117 -> 0 | H55: ='Team & Salaries'!$D27*H117 -> 0 | I55: ='Team & Salaries'!$D27*I117 -> 0 | J55: ='Team & Salaries'!$D27*J117 -> 0 | K55: ='Team & Salaries'!$D27*K117 -> 0 | L55: ='Team & Salaries'!$D27*L117 -> 0 | M55: ='Team & Salaries'!$D27*M117 -> 0 | ... DI55: ='Team & Salaries'!$D27*DI117 -> 2291.6667
A56: =A118 -> Mobile Dev | D56: ='Team & Salaries'!B28 -> Prod | E56: =Settings!$C$6 -> USD | F56: ='Team & Salaries'!$D28*F118 -> 0 | G56: ='Team & Salaries'!$D28*G118 -> 0 | H56: ='Team & Salaries'!$D28*H118 -> 0 | I56: ='Team & Salaries'!$D28*I118 -> 0 | J56: ='Team & Salaries'!$D28*J118 -> 0 | K56: ='Team & Salaries'!$D28*K118 -> 0 | L56: ='Team & Salaries'!$D28*L118 -> 0 | M56: ='Team & Salaries'!$D28*M118 -> 0 | ... DI56: ='Team & Salaries'!$D28*DI118 -> 2291.6667
... A70: =A132 -> VR Dev 4 | D70: ='Team & Salaries'!B42 -> Prod | E70: =Settings!$C$6 -> USD | F70: ='Team & Salaries'!$D42*F132 -> 0 | G70: ='Team & Salaries'!$D42*G132 -> 0 | H70: ='Team & Salaries'!$D42*H132 -> 0 | I70: ='Team & Salaries'!$D42*I132 -> 0 | J70: ='Team & Salaries'!$D42*J132 -> 0 | K70: ='Team & Salaries'!$D42*K132 -> 0 | L70: ='Team & Salaries'!$D42*L132 -> 0 | M70: ='Team & Salaries'!$D42*M132 -> 0 | ... DI70: ='Team & Salaries'!$D42*DI132 -> 5500
A72: =A134 -> Marketing & Sales
A73: =A135 -> CMO | D73: ='Team & Salaries'!B46 -> Growth | E73: =Settings!$C$6 -> USD | F73: =('Team & Salaries'!$D46*F135)*((1+'Team & Salaries'!$Q46)^(ROUNDDOWN((COUNTIF(D73:$E73,">0")/12),0))) -> 0 | G73: =('Team & Salaries'!$D46*G135)*((1+'Team & Salaries'!$Q46)^(ROUNDDOWN((COUNTIF(E73:$E73,">0")/12),0))) -> 0 | H73: =('Team & Salaries'!$D46*H135)*((1+'Team & Salaries'!$Q46)^(ROUNDDOWN((COUNTIF($E73:F73,">0")/12),0))) -> 0 | I73: =('Team & Salaries'!$D46*I135)*((1+'Team & Salaries'!$Q46)^(ROUNDDOWN((COUNTIF($E73:G73,">0")/12),0))) -> 0 | J73: =('Team & Salaries'!$D46*J135)*((1+'Team & Salaries'!$Q46)^(ROUNDDOWN((COUNTIF($E73:H73,">0")/12),0))) -> 0 | K73: =('Team & Salaries'!$D46*K135)*((1+'Team & Salaries'!$Q46)^(ROUNDDOWN((COUNTIF($E73:I73,">0")/12),0))) -> 0 | L73: =('Team & Salaries'!$D46*L135)*((1+'Team & Salaries'!$Q46)^(ROUNDDOWN((COUNTIF($E73:J73,">0")/12),0))) -> 0 | M73: =('Team & Salaries'!$D46*M135)*((1+'Team & Salaries'!$Q46)^(ROUNDDOWN((COUNTIF($E73:K73,">0")/12),0))) -> 0 | N73: =('Team & Salaries'!$D46*N135)*((1+'Team & Salaries'!$Q46)^(ROUNDDOWN((COUNTIF($E73:L73,">0")/12),0))) -> 0 | O73: =('Team & Salaries'!$D46*O135)*((1+'Team & Salaries'!$Q46)^(ROUNDDOWN((COUNTIF($E73:M73,">0")/12),0))) -> 0 | ... DI73: =('Team & Salaries'!$D46*DI135)*((1+'Team & Salaries'!$Q46)^(ROUNDDOWN((COUNTIF($E73:DG73,">0")/12),0))) -> 2736.3698
A74: =A136 -> Digital Marketer | D74: ='Team & Salaries'!B47 -> Growth | E74: =Settings!$C$6 -> USD | F74: =('Team & Salaries'!$D47*F136)*((1+'Team & Salaries'!$Q47)^(ROUNDDOWN((COUNTIF(D74:$E74,">0")/12),0))) -> 0 | G74: =('Team & Salaries'!$D47*G136)*((1+'Team & Salaries'!$Q47)^(ROUNDDOWN((COUNTIF(E74:$E74,">0")/12),0))) -> 0 | H74: =('Team & Salaries'!$D47*H136)*((1+'Team & Salaries'!$Q47)^(ROUNDDOWN((COUNTIF($E74:F74,">0")/12),0))) -> 0 | I74: =('Team & Salaries'!$D47*I136)*((1+'Team & Salaries'!$Q47)^(ROUNDDOWN((COUNTIF($E74:G74,">0")/12),0))) -> 0 | J74: =('Team & Salaries'!$D47*J136)*((1+'Team & Salaries'!$Q47)^(ROUNDDOWN((COUNTIF($E74:H74,">0")/12),0))) -> 0 | K74: =('Team & Salaries'!$D47*K136)*((1+'Team & Salaries'!$Q47)^(ROUNDDOWN((COUNTIF($E74:I74,">0")/12),0))) -> 0 | L74: =('Team & Salaries'!$D47*L136)*((1+'Team & Salaries'!$Q47)^(ROUNDDOWN((COUNTIF($E74:J74,">0")/12),0))) -> 0 | M74: =('Team & Salaries'!$D47*M136)*((1+'Team & Salaries'!$Q47)^(ROUNDDOWN((COUNTIF($E74:K74,">0")/12),0))) -> 0 | N74: =('Team & Salaries'!$D47*N136)*((1+'Team & Salaries'!$Q47)^(ROUNDDOWN((COUNTIF($E74:L74,">0")/12),0))) -> 0 | O74: =('Team & Salaries'!$D47*O136)*((1+'Team & Salaries'!$Q47)^(ROUNDDOWN((COUNTIF($E74:M74,">0")/12),0))) -> 0 | ... DI74: =('Team & Salaries'!$D47*DI136)*((1+'Team & Salaries'!$Q47)^(ROUNDDOWN((COUNTIF($E74:DG74,">0")/12),0))) -> 2736.3698
A75: =A137 -> Digital Marketer | D75: ='Team & Salaries'!B48 -> Growth | E75: =Settings!$C$6 -> USD | F75: =('Team & Salaries'!$D48*F137)*((1+'Team & Salaries'!$Q48)^(ROUNDDOWN((COUNTIF(D75:$E75,">0")/12),0))) -> 0 | G75: =('Team & Salaries'!$D48*G137)*((1+'Team & Salaries'!$Q48)^(ROUNDDOWN((COUNTIF(E75:$E75,">0")/12),0))) -> 0 | H75: =('Team & Salaries'!$D48*H137)*((1+'Team & Salaries'!$Q48)^(ROUNDDOWN((COUNTIF($E75:F75,">0")/12),0))) -> 0 | I75: =('Team & Salaries'!$D48*I137)*((1+'Team & Salaries'!$Q48)^(ROUNDDOWN((COUNTIF($E75:G75,">0")/12),0))) -> 0 | J75: =('Team & Salaries'!$D48*J137)*((1+'Team & Salaries'!$Q48)^(ROUNDDOWN((COUNTIF($E75:H75,">0")/12),0))) -> 0 | K75: =('Team & Salaries'!$D48*K137)*((1+'Team & Salaries'!$Q48)^(ROUNDDOWN((COUNTIF($E75:I75,">0")/12),0))) -> 0 | L75: =('Team & Salaries'!$D48*L137)*((1+'Team & Salaries'!$Q48)^(ROUNDDOWN((COUNTIF($E75:J75,">0")/12),0))) -> 0 | M75: =('Team & Salaries'!$D48*M137)*((1+'Team & Salaries'!$Q48)^(ROUNDDOWN((COUNTIF($E75:K75,">0")/12),0))) -> 0 | N75: =('Team & Salaries'!$D48*N137)*((1+'Team & Salaries'!$Q48)^(ROUNDDOWN((COUNTIF($E75:L75,">0")/12),0))) -> 0 | O75: =('Team & Salaries'!$D48*O137)*((1+'Team & Salaries'!$Q48)^(ROUNDDOWN((COUNTIF($E75:M75,">0")/12),0))) -> 0 | ... DI75: =('Team & Salaries'!$D48*DI137)*((1+'Team & Salaries'!$Q48)^(ROUNDDOWN((COUNTIF($E75:DG75,">0")/12),0))) -> 2736.3698
A76: =A138 -> Digital Marketer | D76: ='Team & Salaries'!B49 -> Growth | E76: =Settings!$C$6 -> USD | F76: =('Team & Salaries'!$D49*F138)*((1+'Team & Salaries'!$Q49)^(ROUNDDOWN((COUNTIF(D76:$E76,">0")/12),0))) -> 0 | G76: =('Team & Salaries'!$D49*G138)*((1+'Team & Salaries'!$Q49)^(ROUNDDOWN((COUNTIF(E76:$E76,">0")/12),0))) -> 0 | H76: =('Team & Salaries'!$D49*H138)*((1+'Team & Salaries'!$Q49)^(ROUNDDOWN((COUNTIF($E76:F76,">0")/12),0))) -> 0 | I76: =('Team & Salaries'!$D49*I138)*((1+'Team & Salaries'!$Q49)^(ROUNDDOWN((COUNTIF($E76:G76,">0")/12),0))) -> 0 | J76: =('Team & Salaries'!$D49*J138)*((1+'Team & Salaries'!$Q49)^(ROUNDDOWN((COUNTIF($E76:H76,">0")/12),0))) -> 0 | K76: =('Team & Salaries'!$D49*K138)*((1+'Team & Salaries'!$Q49)^(ROUNDDOWN((COUNTIF($E76:I76,">0")/12),0))) -> 0 | L76: =('Team & Salaries'!$D49*L138)*((1+'Team & Salaries'!$Q49)^(ROUNDDOWN((COUNTIF($E76:J76,">0")/12),0))) -> 0 | M76: =('Team & Salaries'!$D49*M138)*((1+'Team & Salaries'!$Q49)^(ROUNDDOWN((COUNTIF($E76:K76,">0")/12),0))) -> 0 | N76: =('Team & Salaries'!$D49*N138)*((1+'Team & Salaries'!$Q49)^(ROUNDDOWN((COUNTIF($E76:L76,">0")/12),0))) -> 0 | O76: =('Team & Salaries'!$D49*O138)*((1+'Team & Salaries'!$Q49)^(ROUNDDOWN((COUNTIF($E76:M76,">0")/12),0))) -> 0 | ... DI76: =('Team & Salaries'!$D49*DI138)*((1+'Team & Salaries'!$Q49)^(ROUNDDOWN((COUNTIF($E76:DG76,">0")/12),0))) -> 2736.3698
A77: =A139 -> Digital Marketer | D77: ='Team & Salaries'!B50 -> Growth | E77: =Settings!$C$6 -> USD | F77: =('Team & Salaries'!$D50*F139)*((1+'Team & Salaries'!$Q50)^(ROUNDDOWN((COUNTIF(D77:$E77,">0")/12),0))) -> 0 | G77: =('Team & Salaries'!$D50*G139)*((1+'Team & Salaries'!$Q50)^(ROUNDDOWN((COUNTIF(E77:$E77,">0")/12),0))) -> 0 | H77: =('Team & Salaries'!$D50*H139)*((1+'Team & Salaries'!$Q50)^(ROUNDDOWN((COUNTIF($E77:F77,">0")/12),0))) -> 0 | I77: =('Team & Salaries'!$D50*I139)*((1+'Team & Salaries'!$Q50)^(ROUNDDOWN((COUNTIF($E77:G77,">0")/12),0))) -> 0 | J77: =('Team & Salaries'!$D50*J139)*((1+'Team & Salaries'!$Q50)^(ROUNDDOWN((COUNTIF($E77:H77,">0")/12),0))) -> 0 | K77: =('Team & Salaries'!$D50*K139)*((1+'Team & Salaries'!$Q50)^(ROUNDDOWN((COUNTIF($E77:I77,">0")/12),0))) -> 0 | L77: =('Team & Salaries'!$D50*L139)*((1+'Team & Salaries'!$Q50)^(ROUNDDOWN((COUNTIF($E77:J77,">0")/12),0))) -> 0 | M77: =('Team & Salaries'!$D50*M139)*((1+'Team & Salaries'!$Q50)^(ROUNDDOWN((COUNTIF($E77:K77,">0")/12),0))) -> 0 | N77: =('Team & Salaries'!$D50*N139)*((1+'Team & Salaries'!$Q50)^(ROUNDDOWN((COUNTIF($E77:L77,">0")/12),0))) -> 0 | O77: =('Team & Salaries'!$D50*O139)*((1+'Team & Salaries'!$Q50)^(ROUNDDOWN((COUNTIF($E77:M77,">0")/12),0))) -> 0 | ... DI77: =('Team & Salaries'!$D50*DI139)*((1+'Team & Salaries'!$Q50)^(ROUNDDOWN((COUNTIF($E77:DG77,">0")/12),0))) -> 3505.8325
A78: =A140 -> Sales & Maketing | D78: ='Team & Salaries'!B51 -> Growth | E78: =Settings!$C$6 -> USD | F78: =('Team & Salaries'!$D51*F140)*((1+'Team & Salaries'!$Q51)^(ROUNDDOWN((COUNTIF(D78:$E78,">0")/12),0))) -> 0 | G78: =('Team & Salaries'!$D51*G140)*((1+'Team & Salaries'!$Q51)^(ROUNDDOWN((COUNTIF(E78:$E78,">0")/12),0))) -> 0 | H78: =('Team & Salaries'!$D51*H140)*((1+'Team & Salaries'!$Q51)^(ROUNDDOWN((COUNTIF($E78:F78,">0")/12),0))) -> 0 | I78: =('Team & Salaries'!$D51*I140)*((1+'Team & Salaries'!$Q51)^(ROUNDDOWN((COUNTIF($E78:G78,">0")/12),0))) -> 0 | J78: =('Team & Salaries'!$D51*J140)*((1+'Team & Salaries'!$Q51)^(ROUNDDOWN((COUNTIF($E78:H78,">0")/12),0))) -> 0 | K78: =('Team & Salaries'!$D51*K140)*((1+'Team & Salaries'!$Q51)^(ROUNDDOWN((COUNTIF($E78:I78,">0")/12),0))) -> 0 | L78: =('Team & Salaries'!$D51*L140)*((1+'Team & Salaries'!$Q51)^(ROUNDDOWN((COUNTIF($E78:J78,">0")/12),0))) -> 0 | M78: =('Team & Salaries'!$D51*M140)*((1+'Team & Salaries'!$Q51)^(ROUNDDOWN((COUNTIF($E78:K78,">0")/12),0))) -> 0 | N78: =('Team & Salaries'!$D51*N140)*((1+'Team & Salaries'!$Q51)^(ROUNDDOWN((COUNTIF($E78:L78,">0")/12),0))) -> 0 | O78: =('Team & Salaries'!$D51*O140)*((1+'Team & Salaries'!$Q51)^(ROUNDDOWN((COUNTIF($E78:M78,">0")/12),0))) -> 0 | ... DI78: =('Team & Salaries'!$D51*DI140)*((1+'Team & Salaries'!$Q51)^(ROUNDDOWN((COUNTIF($E78:DG78,">0")/12),0))) -> 3719.3377
A79: =A141 -> Sales & Maketing | D79: ='Team & Salaries'!B52 -> Growth | E79: =Settings!$C$6 -> USD | F79: =('Team & Salaries'!$D52*F141)*((1+'Team & Salaries'!$Q52)^(ROUNDDOWN((COUNTIF(D79:$E79,">0")/12),0))) -> 0 | G79: =('Team & Salaries'!$D52*G141)*((1+'Team & Salaries'!$Q52)^(ROUNDDOWN((COUNTIF(E79:$E79,">0")/12),0))) -> 0 | H79: =('Team & Salaries'!$D52*H141)*((1+'Team & Salaries'!$Q52)^(ROUNDDOWN((COUNTIF($E79:F79,">0")/12),0))) -> 0 | I79: =('Team & Salaries'!$D52*I141)*((1+'Team & Salaries'!$Q52)^(ROUNDDOWN((COUNTIF($E79:G79,">0")/12),0))) -> 0 | J79: =('Team & Salaries'!$D52*J141)*((1+'Team & Salaries'!$Q52)^(ROUNDDOWN((COUNTIF($E79:H79,">0")/12),0))) -> 0 | K79: =('Team & Salaries'!$D52*K141)*((1+'Team & Salaries'!$Q52)^(ROUNDDOWN((COUNTIF($E79:I79,">0")/12),0))) -> 0 | L79: =('Team & Salaries'!$D52*L141)*((1+'Team & Salaries'!$Q52)^(ROUNDDOWN((COUNTIF($E79:J79,">0")/12),0))) -> 0 | M79: =('Team & Salaries'!$D52*M141)*((1+'Team & Salaries'!$Q52)^(ROUNDDOWN((COUNTIF($E79:K79,">0")/12),0))) -> 0 | N79: =('Team & Salaries'!$D52*N141)*((1+'Team & Salaries'!$Q52)^(ROUNDDOWN((COUNTIF($E79:L79,">0")/12),0))) -> 0 | O79: =('Team & Salaries'!$D52*O141)*((1+'Team & Salaries'!$Q52)^(ROUNDDOWN((COUNTIF($E79:M79,">0")/12),0))) -> 0 | ... DI79: =('Team & Salaries'!$D52*DI141)*((1+'Team & Salaries'!$Q52)^(ROUNDDOWN((COUNTIF($E79:DG79,">0")/12),0))) -> 3719.3377
A80: =A142 -> Sales & Maketing | D80: ='Team & Salaries'!B53 -> Growth | E80: =Settings!$C$6 -> USD | F80: =('Team & Salaries'!$D53*F142)*((1+'Team & Salaries'!$Q53)^(ROUNDDOWN((COUNTIF(D80:$E80,">0")/12),0))) -> 0 | G80: =('Team & Salaries'!$D53*G142)*((1+'Team & Salaries'!$Q53)^(ROUNDDOWN((COUNTIF(E80:$E80,">0")/12),0))) -> 0 | H80: =('Team & Salaries'!$D53*H142)*((1+'Team & Salaries'!$Q53)^(ROUNDDOWN((COUNTIF($E80:F80,">0")/12),0))) -> 0 | I80: =('Team & Salaries'!$D53*I142)*((1+'Team & Salaries'!$Q53)^(ROUNDDOWN((COUNTIF($E80:G80,">0")/12),0))) -> 0 | J80: =('Team & Salaries'!$D53*J142)*((1+'Team & Salaries'!$Q53)^(ROUNDDOWN((COUNTIF($E80:H80,">0")/12),0))) -> 0 | K80: =('Team & Salaries'!$D53*K142)*((1+'Team & Salaries'!$Q53)^(ROUNDDOWN((COUNTIF($E80:I80,">0")/12),0))) -> 0 | L80: =('Team & Salaries'!$D53*L142)*((1+'Team & Salaries'!$Q53)^(ROUNDDOWN((COUNTIF($E80:J80,">0")/12),0))) -> 0 | M80: =('Team & Salaries'!$D53*M142)*((1+'Team & Salaries'!$Q53)^(ROUNDDOWN((COUNTIF($E80:K80,">0")/12),0))) -> 0 | N80: =('Team & Salaries'!$D53*N142)*((1+'Team & Salaries'!$Q53)^(ROUNDDOWN((COUNTIF($E80:L80,">0")/12),0))) -> 0 | O80: =('Team & Salaries'!$D53*O142)*((1+'Team & Salaries'!$Q53)^(ROUNDDOWN((COUNTIF($E80:M80,">0")/12),0))) -> 0 | ... DI80: =('Team & Salaries'!$D53*DI142)*((1+'Team & Salaries'!$Q53)^(ROUNDDOWN((COUNTIF($E80:DG80,">0")/12),0))) -> 3611.0074
D81: ='Team & Salaries'!B54 -> Growth | E81: =Settings!$C$6 -> USD | F81: =('Team & Salaries'!$D54*F143)*((1+'Team & Salaries'!$Q54)^(ROUNDDOWN((COUNTIF(D81:$E81,">0")/12),0))) -> 0 | G81: =('Team & Salaries'!$D54*G143)*((1+'Team & Salaries'!$Q54)^(ROUNDDOWN((COUNTIF(E81:$E81,">0")/12),0))) -> 0 | H81: =('Team & Salaries'!$D54*H143)*((1+'Team & Salaries'!$Q54)^(ROUNDDOWN((COUNTIF($E81:F81,">0")/12),0))) -> 0 | I81: =('Team & Salaries'!$D54*I143)*((1+'Team & Salaries'!$Q54)^(ROUNDDOWN((COUNTIF($E81:G81,">0")/12),0))) -> 0 | J81: =('Team & Salaries'!$D54*J143)*((1+'Team & Salaries'!$Q54)^(ROUNDDOWN((COUNTIF($E81:H81,">0")/12),0))) -> 0 | K81: =('Team & Salaries'!$D54*K143)*((1+'Team & Salaries'!$Q54)^(ROUNDDOWN((COUNTIF($E81:I81,">0")/12),0))) -> 0 | L81: =('Team & Salaries'!$D54*L143)*((1+'Team & Salaries'!$Q54)^(ROUNDDOWN((COUNTIF($E81:J81,">0")/12),0))) -> 0 | M81: =('Team & Salaries'!$D54*M143)*((1+'Team & Salaries'!$Q54)^(ROUNDDOWN((COUNTIF($E81:K81,">0")/12),0))) -> 0 | N81: =('Team & Salaries'!$D54*N143)*((1+'Team & Salaries'!$Q54)^(ROUNDDOWN((COUNTIF($E81:L81,">0")/12),0))) -> 0 | O81: =('Team & Salaries'!$D54*O143)*((1+'Team & Salaries'!$Q54)^(ROUNDDOWN((COUNTIF($E81:M81,">0")/12),0))) -> 0 | ... DI81: =('Team & Salaries'!$D54*DI143)*((1+'Team & Salaries'!$Q54)^(ROUNDDOWN((COUNTIF($E81:DG81,">0")/12),0))) -> 0
A83: =A148 -> Junior Customer Support | D83: ='Team & Salaries'!B61 -> Ops | E83: =Settings!$C$6 -> USD | F83: =('Team & Salaries'!$D60*F146) -> 0 | G83: =('Team & Salaries'!$D61*G146)*((1+'Team & Salaries'!$Q61)^(ROUNDDOWN((COUNTIF($F83:F83,">0")/12),0))) -> 0 | H83: =('Team & Salaries'!$D61*H146)*((1+'Team & Salaries'!$Q61)^(ROUNDDOWN((COUNTIF($F83:G83,">0")/12),0))) -> 0 | I83: =('Team & Salaries'!$D61*I146)*((1+'Team & Salaries'!$Q61)^(ROUNDDOWN((COUNTIF($F83:H83,">0")/12),0))) -> 0 | J83: =('Team & Salaries'!$D61*J146)*((1+'Team & Salaries'!$Q61)^(ROUNDDOWN((COUNTIF($F83:I83,">0")/12),0))) -> 0 | K83: =('Team & Salaries'!$D61*K146)*((1+'Team & Salaries'!$Q61)^(ROUNDDOWN((COUNTIF($F83:J83,">0")/12),0))) -> 0 | L83: =('Team & Salaries'!$D61*L146)*((1+'Team & Salaries'!$Q61)^(ROUNDDOWN((COUNTIF($F83:K83,">0")/12),0))) -> 0 | M83: =('Team & Salaries'!$D61*M146)*((1+'Team & Salaries'!$Q61)^(ROUNDDOWN((COUNTIF($F83:L83,">0")/12),0))) -> 0 | N83: =('Team & Salaries'!$D61*N146)*((1+'Team & Salaries'!$Q61)^(ROUNDDOWN((COUNTIF($F83:M83,">0")/12),0))) -> 0 | ... DI83: =('Team & Salaries'!$D61*DI146)*((1+'Team & Salaries'!$Q61)^(ROUNDDOWN((COUNTIF($F83:DH83,">0")/12),0))) -> 2736.3698
A84: =A149 -> Customer Rep 1 | D84: ='Team & Salaries'!B62 -> Ops | E84: =Settings!$C$6 -> USD | F84: =('Team & Salaries'!$D61*F147) -> 0 | G84: =('Team & Salaries'!$D62*G147)*((1+'Team & Salaries'!$Q62)^(ROUNDDOWN((COUNTIF($F84:F84,">0")/12),0))) -> 0 | H84: =('Team & Salaries'!$D62*H147)*((1+'Team & Salaries'!$Q62)^(ROUNDDOWN((COUNTIF($F84:G84,">0")/12),0))) -> 0 | I84: =('Team & Salaries'!$D62*I147)*((1+'Team & Salaries'!$Q62)^(ROUNDDOWN((COUNTIF($F84:H84,">0")/12),0))) -> 0 | J84: =('Team & Salaries'!$D62*J147)*((1+'Team & Salaries'!$Q62)^(ROUNDDOWN((COUNTIF($F84:I84,">0")/12),0))) -> 0 | K84: =('Team & Salaries'!$D62*K147)*((1+'Team & Salaries'!$Q62)^(ROUNDDOWN((COUNTIF($F84:J84,">0")/12),0))) -> 0 | L84: =('Team & Salaries'!$D62*L147)*((1+'Team & Salaries'!$Q62)^(ROUNDDOWN((COUNTIF($F84:K84,">0")/12),0))) -> 0 | M84: =('Team & Salaries'!$D62*M147)*((1+'Team & Salaries'!$Q62)^(ROUNDDOWN((COUNTIF($F84:L84,">0")/12),0))) -> 0 | N84: =('Team & Salaries'!$D62*N147)*((1+'Team & Salaries'!$Q62)^(ROUNDDOWN((COUNTIF($F84:M84,">0")/12),0))) -> 0 | ... DI84: =('Team & Salaries'!$D62*DI147)*((1+'Team & Salaries'!$Q62)^(ROUNDDOWN((COUNTIF($F84:DH84,">0")/12),0))) -> 2736.3698
A85: =A150 -> Customer Rep 2 | D85: ='Team & Salaries'!B63 -> Ops | E85: =Settings!$C$6 -> USD | F85: =('Team & Salaries'!$D62*F148) -> 0 | G85: =('Team & Salaries'!$D63*G148)*((1+'Team & Salaries'!$Q63)^(ROUNDDOWN((COUNTIF($F85:F85,">0")/12),0))) -> 0 | H85: =('Team & Salaries'!$D63*H148)*((1+'Team & Salaries'!$Q63)^(ROUNDDOWN((COUNTIF($F85:G85,">0")/12),0))) -> 0 | I85: =('Team & Salaries'!$D63*I148)*((1+'Team & Salaries'!$Q63)^(ROUNDDOWN((COUNTIF($F85:H85,">0")/12),0))) -> 0 | J85: =('Team & Salaries'!$D63*J148)*((1+'Team & Salaries'!$Q63)^(ROUNDDOWN((COUNTIF($F85:I85,">0")/12),0))) -> 0 | K85: =('Team & Salaries'!$D63*K148)*((1+'Team & Salaries'!$Q63)^(ROUNDDOWN((COUNTIF($F85:J85,">0")/12),0))) -> 0 | L85: =('Team & Salaries'!$D63*L148)*((1+'Team & Salaries'!$Q63)^(ROUNDDOWN((COUNTIF($F85:K85,">0")/12),0))) -> 0 | M85: =('Team & Salaries'!$D63*M148)*((1+'Team & Salaries'!$Q63)^(ROUNDDOWN((COUNTIF($F85:L85,">0")/12),0))) -> 0 | N85: =('Team & Salaries'!$D63*N148)*((1+'Team & Salaries'!$Q63)^(ROUNDDOWN((COUNTIF($F85:M85,">0")/12),0))) -> 0 | ... DI85: =('Team & Salaries'!$D63*DI148)*((1+'Team & Salaries'!$Q63)^(ROUNDDOWN((COUNTIF($F85:DH85,">0")/12),0))) -> 3283.6438
A86: =A151 -> Customer Rep 3 | D86: ='Team & Salaries'!B64 -> Ops | E86: =Settings!$C$6 -> USD | F86: =('Team & Salaries'!$D63*F149) -> 0 | G86: =('Team & Salaries'!$D64*G149)*((1+'Team & Salaries'!$Q64)^(ROUNDDOWN((COUNTIF($F86:F86,">0")/12),0))) -> 0 | H86: =('Team & Salaries'!$D64*H149)*((1+'Team & Salaries'!$Q64)^(ROUNDDOWN((COUNTIF($F86:G86,">0")/12),0))) -> 0 | I86: =('Team & Salaries'!$D64*I149)*((1+'Team & Salaries'!$Q64)^(ROUNDDOWN((COUNTIF($F86:H86,">0")/12),0))) -> 0 | J86: =('Team & Salaries'!$D64*J149)*((1+'Team & Salaries'!$Q64)^(ROUNDDOWN((COUNTIF($F86:I86,">0")/12),0))) -> 0 | K86: =('Team & Salaries'!$D64*K149)*((1+'Team & Salaries'!$Q64)^(ROUNDDOWN((COUNTIF($F86:J86,">0")/12),0))) -> 0 | L86: =('Team & Salaries'!$D64*L149)*((1+'Team & Salaries'!$Q64)^(ROUNDDOWN((COUNTIF($F86:K86,">0")/12),0))) -> 0 | M86: =('Team & Salaries'!$D64*M149)*((1+'Team & Salaries'!$Q64)^(ROUNDDOWN((COUNTIF($F86:L86,">0")/12),0))) -> 0 | N86: =('Team & Salaries'!$D64*N149)*((1+'Team & Salaries'!$Q64)^(ROUNDDOWN((COUNTIF($F86:M86,">0")/12),0))) -> 0 | ... DI86: =('Team & Salaries'!$D64*DI149)*((1+'Team & Salaries'!$Q64)^(ROUNDDOWN((COUNTIF($F86:DH86,">0")/12),0))) -> 3188.0037
A87: =A152 -> Other 4 | D87: ='Team & Salaries'!B65 -> Ops | E87: =Settings!$C$6 -> USD | F87: =('Team & Salaries'!$D64*F150) -> 0 | G87: =('Team & Salaries'!$D65*G150)*((1+'Team & Salaries'!$Q65)^(ROUNDDOWN((COUNTIF($F87:F87,">0")/12),0))) -> 0 | H87: =('Team & Salaries'!$D65*H150)*((1+'Team & Salaries'!$Q65)^(ROUNDDOWN((COUNTIF($F87:G87,">0")/12),0))) -> 0 | I87: =('Team & Salaries'!$D65*I150)*((1+'Team & Salaries'!$Q65)^(ROUNDDOWN((COUNTIF($F87:H87,">0")/12),0))) -> 0 | J87: =('Team & Salaries'!$D65*J150)*((1+'Team & Salaries'!$Q65)^(ROUNDDOWN((COUNTIF($F87:I87,">0")/12),0))) -> 0 | K87: =('Team & Salaries'!$D65*K150)*((1+'Team & Salaries'!$Q65)^(ROUNDDOWN((COUNTIF($F87:J87,">0")/12),0))) -> 0 | L87: =('Team & Salaries'!$D65*L150)*((1+'Team & Salaries'!$Q65)^(ROUNDDOWN((COUNTIF($F87:K87,">0")/12),0))) -> 0 | M87: =('Team & Salaries'!$D65*M150)*((1+'Team & Salaries'!$Q65)^(ROUNDDOWN((COUNTIF($F87:L87,">0")/12),0))) -> 0 | N87: =('Team & Salaries'!$D65*N150)*((1+'Team & Salaries'!$Q65)^(ROUNDDOWN((COUNTIF($F87:M87,">0")/12),0))) -> 0 | ... DI87: =('Team & Salaries'!$D65*DI150)*((1+'Team & Salaries'!$Q65)^(ROUNDDOWN((COUNTIF($F87:DH87,">0")/12),0))) -> 3095.1492
A88: =A153 -> Other 5 | D88: ='Team & Salaries'!B66 -> Ops | E88: =Settings!$C$6 -> USD | F88: =('Team & Salaries'!$D65*F151) -> 0 | G88: =('Team & Salaries'!$D66*G151)*((1+'Team & Salaries'!$Q66)^(ROUNDDOWN((COUNTIF($F88:F88,">0")/12),0))) -> 0 | H88: =('Team & Salaries'!$D66*H151)*((1+'Team & Salaries'!$Q66)^(ROUNDDOWN((COUNTIF($F88:G88,">0")/12),0))) -> 0 | I88: =('Team & Salaries'!$D66*I151)*((1+'Team & Salaries'!$Q66)^(ROUNDDOWN((COUNTIF($F88:H88,">0")/12),0))) -> 0 | J88: =('Team & Salaries'!$D66*J151)*((1+'Team & Salaries'!$Q66)^(ROUNDDOWN((COUNTIF($F88:I88,">0")/12),0))) -> 0 | K88: =('Team & Salaries'!$D66*K151)*((1+'Team & Salaries'!$Q66)^(ROUNDDOWN((COUNTIF($F88:J88,">0")/12),0))) -> 0 | L88: =('Team & Salaries'!$D66*L151)*((1+'Team & Salaries'!$Q66)^(ROUNDDOWN((COUNTIF($F88:K88,">0")/12),0))) -> 0 | M88: =('Team & Salaries'!$D66*M151)*((1+'Team & Salaries'!$Q66)^(ROUNDDOWN((COUNTIF($F88:L88,">0")/12),0))) -> 0 | N88: =('Team & Salaries'!$D66*N151)*((1+'Team & Salaries'!$Q66)^(ROUNDDOWN((COUNTIF($F88:M88,">0")/12),0))) -> 0 | ... DI88: =('Team & Salaries'!$D66*DI151)*((1+'Team & Salaries'!$Q66)^(ROUNDDOWN((COUNTIF($F88:DH88,">0")/12),0))) -> 2917.475
A89: Total Payroll | E89: =Settings!$C$6 -> USD | F89: =SUM(F34:F87) -> 11458.333 | G89: =SUM(G34:G87) -> 6875 | H89: =SUM(H34:H87) -> 6875 | I89: =SUM(I34:I87) -> 11458.333 | J89: =SUM(J34:J87) -> 11458.333 | K89: =SUM(K34:K87) -> 11458.333 | L89: =SUM(L34:L87) -> 13750 | M89: =SUM(M34:M87) -> 13750 | ... DI89: =SUM(DI34:DI87) -> 169176.13
Q90: =SUM(F89:Q89) -> 148958.33
A93: Headcount:
A95: ='Team & Salaries'!A5 -> Operations
