Workbook
Name Holidays: [2]Assumptions!$R$3:$R$36
Name Sales_BU: [3]Sales!$B$79:$B$90
Name Sales_Forecast: [3]Sales!$B$79:$O$90
Name Sales_Month: [3]Sales!$B$79:$O$79
Name valuevx: 42.314159

Sheet Cap Table
A1: VReeMind Inc. | B1: Expected Month: | C1: 0 | F1: Expected Month: | G1: =IF(ISTEXT('[1]Investment & Cash'!$D$10),'[1]Investment & Cash'!$D$10,"") -> Month 4 | J1: Expected Month: | K1: =IF(ISTEXT('[1]Investment & Cash'!$D$11),'[1]Investment & Cash'!$D$11,"") -> Month 13 | N1: Expected Month: | O1: =IF(ISTEXT('[1]Investment & Cash'!$D$12),'[1]Investment & Cash'!$D$12,"") -> Month 25 | R1: Expected Month: | S1: =IF(ISTEXT('[1]Investment & Cash'!$D$13),'[1]Investment & Cash'!$D$13,"") -> Month 37 | V1: Expected Month: | W1: =IF(ISTEXT('[1]Investment & Cash'!$D$14),'[1]Investment & Cash'!$D$14,"") -> Month 49 | Z1: Exit at Year: | AA1: 5
B3: Pre-Seed | F3: Seed | J3: Series A | N3: Series B | R3: Series C | V3: Series D | Z3: Exit
A4: Share price | C4: 0.1 | G4: 1 | K4: 1.5 | O4: 3 | S4: 10 | W4: 25 | AA4: Multiplier:
A5: Multipliers | G5: =G4/C4 -> 10 | K5: =K4/G4 -> 1.5 | O5: =O4/K4 -> 2 | S5: =S4/O4 -> 3.3333333 | W5: =W4/S4 -> 2.5 | AA5: 3
AA6: =W42*AA5 -> 681250000
B7: Net shares added this round | C7: Cumulative shareholding | D7: Ownership | F7: Net shares added this round | G7: Cumulative shareholding | H7: Ownership | J7: Net shares added this round | K7: Cumulative shareholding | L7: Ownership | N7: Net shares added this round | O7: Cumulative shareholding | P7: Ownership | R7: Net shares added this round | S7: Cumulative shareholding | T7: Ownership | V7: Net shares added this round | W7: Cumulative shareholding | X7: Ownership | AA7: Cumulative shareholding | AB7: Ownership | AF7: Founders Returns
AF8: Laurens
A9: Common stock | AD9: EBITDA | AF9: =AD11*0.25 -> 46099624
A10: Founder restricted stock | C10: =SUM(C11:C13) -> 1000000 | D10: =SUM(D11:D13) -> 1 | G10: =SUM(G11:G13) -> 1000000 | H10: =SUM(H11:H13) -> 0.74074074 | K10: =SUM(K11:K13) -> 4000000 | L10: =SUM(L11:L13) -> 0.66481994 | O10: =SUM(O11:O13) -> 5000000 | P10: =SUM(P11:P13) -> 0.61099796 | S10: =SUM(S11:S13) -> 5000000 | T10: =SUM(T11:T13) -> 0.57581574 | W10: =SUM(W11:W13) -> 5000000 | X10: =SUM(X11:X13) -> 0.55045872 | AA10: =SUM(AA11:AA13) -> 5000000 | AB10: =SUM(AB11:AB13) -> 0.55045872
A11: Founders | B11: 1000000 | C11: =B11 -> 1000000 | D11: =IFERROR(C11/C$38,0) -> 1 | F11: 0 | G11: =C11+F11 -> 1000000 | H11: =IFERROR(G11/G$38,0) -> 0.74074074 | J11: 1000000 | K11: =G11+J11 -> 2000000 | L11: =IFERROR(K11/K$38,0) -> 0.33240997 | N11: 1000000 | O11: =K11+N11 -> 3000000 | P11: =IFERROR(O11/O$38,0) -> 0.36659878 | R11: 0 | S11: =O11+R11 -> 3000000 | T11: =IFERROR(S11/S$38,0) -> 0.34548944 | V11: 0 | W11: =S11+V11 -> 3000000 | X11: =IFERROR(W11/W$38,0) -> 0.33027523 | AA11: =W11 -> 3000000 | AB11: =X11 -> 0.33027523 | AD11: =SUM(AA$6/AA$38)*AA11 -> 1.843985e+08 | AF11: Aaron
A12: Senior Leadership Team | B12: 0 | C12: =B12 -> 0 | D12: =IFERROR(C12/C$38,0) -> 0 | F12: 0 | G12: =C12+F12 -> 0 | H12: =IFERROR(G12/G$38,0) -> 0 | J12: 2000000 | K12: =G12+J12 -> 2000000 | L12: =IFERROR(K12/K$38,0) -> 0.33240997 | N12: 0 | O12: =K12+N12 -> 2000000 | P12: =IFERROR(O12/O$38,0) -> 0.24439919 | R12: 0 | S12: =O12+R12 -> 2000000 | T12: =IFERROR(S12/S$38,0) -> 0.2303263 | V12: 0 | W12: =S12+V12 -> 2000000 | X12: =IFERROR(W12/W$38,0) -> 0.22018349 | AA12: =W12 -> 2000000 | AB12: =X12 -> 0.22018349 | AD12: =SUM(AA$6/AA$38)*AA12 -> 1.2293233e+08 | AF12: =AD11*0.25 -> 46099624
A13: IP license | B13: 0 | C13: =B13 -> 0 | D13: =IFERROR(C13/C$38,0) -> 0 | F13: 0 | G13: =C13+F13 -> 0 | H13: =IFERROR(G13/G$38,0) -> 0 | J13: 0 | K13: =G13+J13 -> 0 | L13: =IFERROR(K13/K$38,0) -> 0 | N13: 0 | O13: =K13+N13 -> 0 | P13: =IFERROR(O13/O$38,0) -> 0 | R13: 0 | S13: =O13+R13 -> 0 | T13: =IFERROR(S13/S$38,0) -> 0 | V13: 0 | W13: =S13+V13 -> 0 | X13: =IFERROR(W13/W$38,0) -> 0 | AA13: =W13 -> 0 | AB13: =X13 -> 0 | AD13: =SUM(AA$6/AA$38)*AA13 -> 0
A14: Option pool | C14: =SUM(C15:C17) -> 0 | D14: =IFERROR(C14/C$38,0) -> 0 | G14: =SUM(G15:G17) -> 0 | H14: =IFERROR(G14/G$38,0) -> 0 | K14: =SUM(K15:K17) -> 1000000 | L14: =IFERROR(K14/K$38,0) -> 0.16620499 | O14: =SUM(O15:O17) -> 1000000 | P14: =IFERROR(O14/O$38,0) -> 0.12219959 | S14: =SUM(S15:S17) -> 1000000 | T14: =IFERROR(S14/S$38,0) -> 0.11516315 | W14: =SUM(W15:W17) -> 1000000 | X14: =IFERROR(W14/W$38,0) -> 0.11009174 | AA14: =SUM(AA15:AA17) -> 3000000 | AB14: =IFERROR(AA14/AA$38,0) -> 0.27067669 | AF14: Scott
A15: Staff Stock Options | B15: 0 | C15: =B15 -> 0 | D15: =IFERROR(C15/C$38,0) -> 0 | F15: 0 | G15: =C15+F15 -> 0 | H15: =IFERROR(G15/G$38,0) -> 0 | J15: 1000000 | K15: =G15+J15 -> 1000000 | L15: =IFERROR(K15/K$38,0) -> 0.16620499 | N15: 1000000 | O15: =K15+N15 -> 2000000 | P15: =IFERROR(O15/O$38,0) -> 0.24439919 | R15: 0 | S15: =O15+R15 -> 2000000 | T15: =IFERROR(S15/S$38,0) -> 0.2303263 | V15: 0 | W15: =S15+V15 -> 2000000 | X15: =IFERROR(W15/W$38,0) -> 0.22018349 | AA15: =W15 -> 2000000 | AB15: =X15 -> 0.22018349 | AD15: =SUM(AA$6/AA$38)*AA15 -> 1.2293233e+08 | AF15: =AD11*0.25 -> 46099624
A16: Issued and outstanding | B16: 0 | C16: =B16 -> 0 | D16: =IFERROR(C16/C$38,0) -> 0 | F16: 0 | G16: =C16+F16 -> 0 | H16: =IFERROR(G16/G$38,0) -> 0 | J16: 0 | K16: =G16+J16 -> 0 | L16: =IFERROR(K16/K$38,0) -> 0 | N16: 0 | O16: =K16+N16 -> 0 | P16: =IFERROR(O16/O$38,0) -> 0 | R16: 0 | S16: =O16+R16 -> 0 | T16: =IFERROR(S16/S$38,0) -> 0 | V16: 0 | W16: =S16+V16 -> 0 | X16: =IFERROR(W16/W$38,0) -> 0 | AA16: =W16 -> 0 | AB16: =X16 -> 0 | AD16: =SUM(AA$6/AA$38)*AA16 -> 0
A17: Reserved | B17: 0 | C17: =B17 -> 0 | D17: =IFERROR(C17/C$38,0) -> 0 | F17: 0 | G17: =C17+F17 -> 0 | H17: =IFERROR(G17/G$38,0) -> 0 | J17: 0 | K17: =G17+J17 -> 0 | L17: =IFERROR(K17/K$38,0) -> 0 | N17: -1000000 | O17: =K17+N17 -> -1000000 | P17: =IFERROR(O17/O$38,0) -> -0.12219959 | R17: 0 | S17: =O17+R17 -> -1000000 | T17: =IFERROR(S17/S$38,0) -> -0.11516315 | V17: 0 | W17: =S17+V17 -> -1000000 | X17: =IFERROR(W17/W$38,0) -> -0.11009174 | AA17: =W17*-1 -> 1000000 | AB17: =X17*-1 -> 0.11009174 | AD17: =SUM(AA$6/AA$38)*AA17 -> 61466165 | AF17: Sam
A18: Total | B18: =SUM(B11:B13,B15:B17) -> 1000000 | C18: =C10+C14 -> 1000000 | D18: =D10+D14 -> 1 | F18: =SUM(F11:F13,F15:F17) -> 0 | G18: =G10+G14 -> 1000000 | H18: =H10+H14 -> 0.74074074 | J18: =SUM(J11:J13,J15:J17) -> 4000000 | K18: =K10+K14 -> 5000000 | L18: =L10+L14 -> 0.83102493 | N18: =SUM(N11:N13,N15:N17) -> 1000000 | O18: =O10+O14 -> 6000000 | P18: =P10+P14 -> 0.73319756 | R18: =SUM(R11:R13,R15:R17) -> 0 | S18: =S10+S14 -> 6000000 | T18: =T10+T14 -> 0.69097889 | V18: =SUM(V11:V13,V15:V17) -> 0 | W18: =W10+W14 -> 6000000 | X18: =X10+X14 -> 0.66055046 | Z18: TOTAL | AA18: =AA10+AA14 -> 8000000 | AB18: =AB10+AB14 -> 0.82113541 | AF18: =AD11*0.25 -> 46099624
A20: Preference Stock | B20: Investment in this round | C20: Cumulative shareholding | D20: Ownership | F20: Investment in this round | G20: Cumulative shareholding | H20: Ownership | J20: Investment in this round | K20: Cumulative shareholding | L20: Ownership | N20: Investment in this round | O20: Cumulative shareholding | P20: Ownership | R20: Investment in this round | S20: Cumulative shareholding | T20: Ownership | V20: Investment in this round | W20: Cumulative shareholding | X20: Ownership | AA20: Cumulative shareholding | AB20: Ownership | AF20: CAGR | AG20: ROI | AH20: ROI Multiplier
A21: Co-Founders (pre-seed) | B21: 50000 | C21: 0 | D21: =IFERROR(C21/C$38,0) -> 0 | F21: 0 | G21: =C21+F21/G$4 -> 0 | H21: =IFERROR(G21/G$38,0) -> 0 | J21: 0 | K21: =G21+J21/K$4 -> 0 | L21: =IFERROR(K21/K$38,0) -> 0 | N21: 0 | O21: =K21+N21/O$4 -> 0 | P21: =IFERROR(O21/O$38,0) -> 0 | R21: 0 | S21: =O21+R21/S$4 -> 0 | T21: =IFERROR(S21/S$38,0) -> 0 | V21: 0 | W21: =S21+V21/W$4 -> 0 | X21: =IFERROR(W21/W$38,0) -> 0 | AA21: =W21 -> 0 | AB21: =X21 -> 0 | AD21: =SUM(AA$6/AA$38)*AA21 -> 0
A22: Seed Investor | B22: 0 | C22: =B22/C$4 -> 0 | D22: =IFERROR(C22/C$38,0) -> 0 | F22: 350000 | G22: =C22+F22/G$4 -> 350000 | H22: =IFERROR(G22/G$38,0) -> 0.25925926 | J22: 0 | K22: =G22+J22/K$4 -> 350000 | L22: =IFERROR(K22/K$38,0) -> 0.058171745 | N22: 0 | O22: =K22+N22/O$4 -> 350000 | P22: =IFERROR(O22/O$38,0) -> 0.042769857 | R22: 0 | S22: =O22+R22/S$4 -> 350000 | T22: =IFERROR(S22/S$38,0) -> 0.040307102 | V22: 0 | W22: =S22+V22/W$4 -> 350000 | X22: =IFERROR(W22/W$38,0) -> 0.03853211 | AA22: =W22 -> 350000 | AB22: =X22 -> 0.03853211 | AD22: =SUM(AA$6/AA$38)*AA22 -> 21513158 | AF22: =_xlfn.RRI(5,F22,AD22) -> 1.2789103 | AG22: =SUM(AD22-F22)/F22 -> 60.466165 | AH22: =SUM(AD22/F22) -> 61.466165
A23: Series A | B23: 0 | C23: =B23/C$4 -> 0 | D23: =IFERROR(C23/C$38,0) -> 0 | F23: 0 | G23: =C23+F23/G$4 -> 0 | H23: =IFERROR(G23/G$38,0) -> 0 | J23: 1000000 | K23: =G23+J23/K$4 -> 666666.67 | L23: =IFERROR(K23/K$38,0) -> 0.11080332 | N23: 0 | O23: =K23+N23/O$4 -> 666666.67 | P23: =IFERROR(O23/O$38,0) -> 0.081466395 | R23: 0 | S23: =O23+R23/S$4 -> 666666.67 | T23: =IFERROR(S23/S$38,0) -> 0.076775432 | V23: 0 | W23: =S23+V23/W$4 -> 666666.67 | X23: =IFERROR(W23/W$38,0) -> 0.073394495 | AA23: =W23 -> 666666.67 | AB23: =X23 -> 0.073394495 | AD23: =SUM(AA$6/AA$38)*AA23 -> 40977444 | AF23: =_xlfn.RRI(4,J23,AD23) -> 1.5300914 | AG23: =SUM(AD23-J23)/J23 -> 39.977444 | AH23: =SUM(AD23/J23) -> 40.977444
A24: Series B | B24: 0 | C24: =B24/C$4 -> 0 | D24: =IFERROR(C24/C$38,0) -> 0 | F24: 0 | G24: =C24+F24/G$4 -> 0 | H24: =IFERROR(G24/G$38,0) -> 0 | J24: 0 | K24: =G24+J24/K$4 -> 0 | L24: =IFERROR(K24/K$38,0) -> 0 | N24: 3500000 | O24: =K24+N24/O$4 -> 1166666.7 | P24: =IFERROR(O24/O$38,0) -> 0.14256619 | R24: 0 | S24: =O24+R24/S$4 -> 1166666.7 | T24: =IFERROR(S24/S$38,0) -> 0.13435701 | V24: 0 | W24: =S24+V24/W$4 -> 1166666.7 | X24: =IFERROR(W24/W$38,0) -> 0.12844037 | AA24: =W24 -> 1166666.7 | AB24: =X24 -> 0.12844037 | AD24: =SUM(AA$6/AA$38)*AA24 -> 71710526 | AF24: =_xlfn.RRI(3,N24,AD24) -> 1.7363498 | AG24: =SUM(AD24-N24)/N24 -> 19.488722 | AH24: =SUM(AD24/N24) -> 20.488722
A25: Series C | B25: 0 | C25: =B25/C$4 -> 0 | D25: =IFERROR(C25/C$38,0) -> 0 | F25: 0 | G25: =C25+F25/G$4 -> 0 | H25: =IFERROR(G25/G$38,0) -> 0 | J25: 0 | K25: =G25+J25/K$4 -> 0 | L25: =IFERROR(K25/K$38,0) -> 0 | N25: 0 | O25: =K25+N25/O$4 -> 0 | P25: =IFERROR(O25/O$38,0) -> 0 | R25: 5000000 | S25: =O25+R25/S$4 -> 500000 | T25: =IFERROR(S25/S$38,0) -> 0.057581574 | V25: 0 | W25: =S25+V25/W$4 -> 500000 | X25: =IFERROR(W25/W$38,0) -> 0.055045872 | AA25: =W25 -> 500000 | AB25: =X25 -> 0.055045872 | AD25: =SUM(AA$6/AA$38)*AA25 -> 30733083 | AF25: =_xlfn.RRI(2,R25,AD25) -> 1.4792371 | AG25: =SUM(AD25-R25)/R25 -> 5.1466165 | AH25: =SUM(AD25/R25) -> 6.1466165
A26: Series D | B26: 0 | C26: =B26/C$4 -> 0 | D26: =IFERROR(C26/C$38,0) -> 0 | F26: 0 | G26: =C26+F26/G$4 -> 0 | H26: =IFERROR(G26/G$38,0) -> 0 | J26: 0 | K26: =G26+J26/K$4 -> 0 | L26: =IFERROR(K26/K$38,0) -> 0 | N26: 0 | O26: =K26+N26/O$4 -> 0 | P26: =IFERROR(O26/O$38,0) -> 0 | R26: 0 | S26: =O26+R26/S$4 -> 0 | T26: =IFERROR(S26/S$38,0) -> 0 | V26: 10000000 | W26: =S26+V26/W$4 -> 400000 | X26: =IFERROR(W26/W$38,0) -> 0.044036697 | AA26: =W26 -> 400000 | AB26: =X26 -> 0.044036697 | AD26: =SUM(AA$6/AA$38)*AA26 -> 24586466 | AF26: =_xlfn.RRI(1,V26,AD26) -> 1.4586466 | AG26: =SUM(AD26-V26)/V26 -> 1.4586466 | AH26: =SUM(AD26/V26) -> 2.4586466
A27: Investor 7 | B27: 0 | C27: =B27/C$4 -> 0 | D27: =IFERROR(C27/C$38,0) -> 0 | F27: 0 | G27: =C27+F27/G$4 -> 0 | H27: =IFERROR(G27/G$38,0) -> 0 | J27: 0 | K27: =G27+J27/K$4 -> 0 | L27: =IFERROR(K27/K$38,0) -> 0 | N27: 0 | O27: =K27+N27/O$4 -> 0 | P27: =IFERROR(O27/O$38,0) -> 0 | R27: 0 | S27: =O27+R27/S$4 -> 0 | T27: =IFERROR(S27/S$38,0) -> 0 | V27: 0 | W27: =S27+V27/W$4 -> 0 | X27: =IFERROR(W27/W$38,0) -> 0 | AA27: =W27 -> 0 | AB27: =X27 -> 0 | AD27: =SUM(AA$6/AA$38)*AA27 -> 0 | AF27: =AVERAGE(AF22:AF26) -> 1.496647 | AG27: =AVERAGE(AG22:AG26) -> 25.307519 | AH27: =AVERAGE(AH22:AH26) -> 26.307519
A28: Investor 8 | B28: 0 | C28: =B28/C$4 -> 0 | D28: =IFERROR(C28/C$38,0) -> 0 | F28: 0 | G28: =C28+F28/G$4 -> 0 | H28: =IFERROR(G28/G$38,0) -> 0 | J28: 0 | K28: =G28+J28/K$4 -> 0 | L28: =IFERROR(K28/K$38,0) -> 0 | N28: 0 | O28: =K28+N28/O$4 -> 0 | P28: =IFERROR(O28/O$38,0) -> 0 | R28: 0 | S28: =O28+R28/S$4 -> 0 | T28: =IFERROR(S28/S$38,0) -> 0 | V28: 0 | W28: =S28+V28/W$4 -> 0 | X28: =IFERROR(W28/W$38,0) -> 0 | AA28: =W28 -> 0 | AB28: =X28 -> 0 | AD28: =SUM(AA$6/AA$38)*AA28 -> 0
A29: Investor 9 | B29: 0 | C29: =B29/C$4 -> 0 | D29: =IFERROR(C29/C$38,0) -> 0 | F29: 0 | G29: =C29+F29/G$4 -> 0 | H29: =IFERROR(G29/G$38,0) -> 0 | J29: 0 | K29: =G29+J29/K$4 -> 0 | L29: =IFERROR(K29/K$38,0) -> 0 | N29: 0 | O29: =K29+N29/O$4 -> 0 | P29: =IFERROR(O29/O$38,0) -> 0 | R29: 0 | S29: =O29+R29/S$4 -> 0 | T29: =IFERROR(S29/S$38,0) -> 0 | V29: 0 | W29: =S29+V29/W$4 -> 0 | X29: =IFERROR(W29/W$38,0) -> 0 | AA29: =W29 -> 0 | AB29: =X29 -> 0 | AD29: =SUM(AA$6/AA$38)*AA29 -> 0
A30: Investor 10 | B30: 0 | C30: =B30/C$4 -> 0 | D30: =IFERROR(C30/C$38,0) -> 0 | F30: 0 | G30: =C30+F30/G$4 -> 0 | H30: =IFERROR(G30/G$38,0) -> 0 | J30: 0 | K30: =G30+J30/K$4 -> 0 | L30: =IFERROR(K30/K$38,0) -> 0 | N30: 0 | O30: =K30+N30/O$4 -> 0 | P30: =IFERROR(O30/O$38,0) -> 0 | R30: 0 | S30: =O30+R30/S$4 -> 0 | T30: =IFERROR(S30/S$38,0) -> 0 | V30: 0 | W30: =S30+V30/W$4 -> 0 | X30: =IFERROR(W30/W$38,0) -> 0 | AA30: =W30 -> 0 | AB30: =X30 -> 0 | AD30: =SUM(AA$6/AA$38)*AA30 -> 0
A31: Investor 11 | B31: 0 | C31: =B31/C$4 -> 0 | D31: =IFERROR(C31/C$38,0) -> 0 | F31: 0 | G31: =C31+F31/G$4 -> 0 | H31: =IFERROR(G31/G$38,0) -> 0 | J31: 0 | K31: =G31+J31/K$4 -> 0 | L31: =IFERROR(K31/K$38,0) -> 0 | N31: 0 | O31: =K31+N31/O$4 -> 0 | P31: =IFERROR(O31/O$38,0) -> 0 | R31: 0 | S31: =O31+R31/S$4 -> 0 | T31: =IFERROR(S31/S$38,0) -> 0 | V31: 0 | W31: =S31+V31/W$4 -> 0 | X31: =IFERROR(W31/W$38,0) -> 0 | AA31: =W31 -> 0 | AB31: =X31 -> 0 | AD31: =SUM(AA$6/AA$38)*AA31 -> 0
A32: Investor 12 | B32: 0 | C32: =B32/C$4 -> 0 | D32: =IFERROR(C32/C$38,0) -> 0 | F32: 0 | G32: =C32+F32/G$4 -> 0 | H32: =IFERROR(G32/G$38,0) -> 0 | J32: 0 | K32: =G32+J32/K$4 -> 0 | L32: =IFERROR(K32/K$38,0) -> 0 | N32: 0 | O32: =K32+N32/O$4 -> 0 | P32: =IFERROR(O32/O$38,0) -> 0 | R32: 0 | S32: =O32+R32/S$4 -> 0 | T32: =IFERROR(S32/S$38,0) -> 0 | V32: 0 | W32: =S32+V32/W$4 -> 0 | X32: =IFERROR(W32/W$38,0) -> 0 | AA32: =W32 -> 0 | AB32: =X32 -> 0 | AD32: =SUM(AA$6/AA$38)*AA32 -> 0
A33: Investor 13 | B33: 0 | C33: =B33/C$4 -> 0 | D33: =IFERROR(C33/C$38,0) -> 0 | F33: 0 | G33: =C33+F33/G$4 -> 0 | H33: =IFERROR(G33/G$38,0) -> 0 | J33: 0 | K33: =G33+J33/K$4 -> 0 | L33: =IFERROR(K33/K$38,0) -> 0 | N33: 0 | O33: =K33+N33/O$4 -> 0 | P33: =IFERROR(O33/O$38,0) -> 0 | R33: 0 | S33: =O33+R33/S$4 -> 0 | T33: =IFERROR(S33/S$38,0) -> 0 | V33: 0 | W33: =S33+V33/W$4 -> 0 | X33: =IFERROR(W33/W$38,0) -> 0 | AA33: =W33 -> 0 | AB33: =X33 -> 0 | AD33: =SUM(AA$6/AA$38)*AA33 -> 0
A34: Investor 14 | B34: 0 | C34: =B34/C$4 -> 0 | D34: =IFERROR(C34/C$38,0) -> 0 | F34: 0 | G34: =C34+F34/G$4 -> 0 | H34: =IFERROR(G34/G$38,0) -> 0 | J34: 0 | K34: =G34+J34/K$4 -> 0 | L34: =IFERROR(K34/K$38,0) -> 0 | N34: 0 | O34: =K34+N34/O$4 -> 0 | P34: =IFERROR(O34/O$38,0) -> 0 | R34: 0 | S34: =O34+R34/S$4 -> 0 | T34: =IFERROR(S34/S$38,0) -> 0 | V34: 0 | W34: =S34+V34/W$4 -> 0 | X34: =IFERROR(W34/W$38,0) -> 0 | AA34: =W34 -> 0 | AB34: =X34 -> 0 | AD34: =SUM(AA$6/AA$38)*AA34 -> 0
A35: Investor 15 | B35: 0 | C35: =B35/C$4 -> 0 | D35: =IFERROR(C35/C$38,0) -> 0 | F35: 0 | G35: =C35+F35/G$4 -> 0 | H35: =IFERROR(G35/G$38,0) -> 0 | J35: 0 | K35: =G35+J35/K$4 -> 0 | L35: =IFERROR(K35/K$38,0) -> 0 | N35: 0 | O35: =K35+N35/O$4 -> 0 | P35: =IFERROR(O35/O$38,0) -> 0 | R35: 0 | S35: =O35+R35/S$4 -> 0 | T35: =IFERROR(S35/S$38,0) -> 0 | V35: 0 | W35: =S35+V35/W$4 -> 0 | X35: =IFERROR(W35/W$38,0) -> 0 | AA35: =W35 -> 0 | AB35: =X35 -> 0 | AD35: =SUM(AA$6/AA$38)*AA35 -> 0
A36: Total | B36: =SUM(B21:B35) -> 50000 | C36: =SUM(C21:C35) -> 0 | D36: =SUM(D21:D35) -> 0 | F36: =SUM(F21:F35) -> 350000 | G36: =SUM(G21:G35) -> 350000 | H36: =SUM(H21:H35) -> 0.25925926 | J36: =SUM(J21:J35) -> 1000000 | K36: =SUM(K21:K35) -> 1016666.7 | L36: =SUM(L21:L35) -> 0.16897507 | N36: =SUM(N21:N35) -> 3500000 | O36: =SUM(O21:O35) -> 2183333.3 | P36: =SUM(P21:P35) -> 0.26680244 | R36: =SUM(R21:R35) -> 5000000 | S36: =SUM(S21:S35) -> 2683333.3 | T36: =SUM(T21:T35) -> 0.30902111 | V36: =SUM(V21:V35) -> 10000000 | W36: =SUM(W21:W35) -> 3083333.3 | X36: =SUM(X21:X35) -> 0.33944954 | AA36: =SUM(AA21:AA35) -> 3083333.3 | AB36: =SUM(AB21:AB35) -> 0.33944954
A38: Total allocated shares | C38: =C18+C36 -> 1000000 | D38: =D18+D36 -> 1 | G38: =G18+G36 -> 1350000 | H38: =H18+H36 -> 1 | K38: =K18+K36 -> 6016666.7 | L38: =L18+L36 -> 1 | O38: =O18+O36 -> 8183333.3 | P38: =IFERROR(P18+P36,0) -> 1 | S38: =S18+S36 -> 8683333.3 | T38: =IFERROR(T18+T36,0) -> 1 | W38: =W18+W36 -> 9083333.3 | X38: =IFERROR(X18+X36,0) -> 1 | Z38: TOTAL | AA38: =AA18+AA36 -> 11083333 | AB38: =IFERROR(AB18+AB36,0) -> 1.1605849
A40: Pre-money valuation | C40: =C4*C18 -> 100000 | G40: =IF((G18+C36)*G4=0,C42,(G18+C36)*G4) -> 1000000 | K40: =(K18+G36)*K4 -> 8025000 | O40: =(O18+K36)*O4 -> 21050000 | S40: =(S18+O36)*S4 -> 81833333 | W40: =(W18+S36)*W4 -> 2.1708333e+08
A42: Post-money valuation | C42: =C38*C4 -> 100000 | G42: =G38*G4 -> 1350000 | K42: =K38*K4 -> 9025000 | O42: =O38*O4 -> 24550000 | S42: =S38*S4 -> 86833333 | W42: =W38*W4 -> 2.2708333e+08
A44: Difference | C44: =SUM(C42-C40) -> 0 | G44: =SUM(G42-G40) -> 350000 | K44: =SUM(K42-K40) -> 1000000 | O44: =SUM(O42-O40) -> 3500000 | S44: =SUM(S42-S40) -> 5000000 | W44: =SUM(W42-W40) -> 10000000

Sheet ROI Analysis
A1: Original | B1: Average | C1: Bin | D1: Random | E1: Norm Dist | F1: Histogram | G1: Histogram | P1: CAGR | Q1: Probability Distribution
A2: =P2 -> 1.2789103 | B2: =AVERAGE(A2:A6) -> 1.496647 | C2: =$B$2-3*$B4 -> 1.0043078 | D2: 0.9418396 | E2: =_xlfn.NORM.DIST(D2,$B$2,$B$4,FALSE) -> 0.0080176748 | F2: Bin | G2: Frequency | H2: Bin | I2: Frequency | P2: ='Cap Table'!AF22 -> 1.2789103 | Q2: =_xlfn.NORM.DIST(P2,$N$6,$N$7,0) -> 0.71513141
A3: =P3 -> 1.4586466 | B3: STDEV | C3: =C2+$B$4 -> 1.1684209 | D3: 0.99879718 | E3: =_xlfn.NORM.DIST(D3,$B$2,$B$4,FALSE) -> 0.024403283 | F3: 1.0043078 | G3: 2 | H3: 1.0043078 | I3: 0 | P3: ='Cap Table'!AF26 -> 1.4586466 | Q3: =_xlfn.NORM.DIST(P3,$N$6,$N$7,0) -> 3.0180939
A4: =P4 -> 1.4792371 | B4: =STDEV(A2:A6) -> 0.16411308 | C4: =C3+$B$4 -> 1.332534 | D4: 1.0148217 | E4: =_xlfn.NORM.DIST(D4,$B$2,$B$4,FALSE) -> 0.032660264 | F4: 1.1684209 | G4: 40 | H4: 1.1684209 | I4: 0 | P4: ='Cap Table'!AF25 -> 1.4792371 | Q4: =_xlfn.NORM.DIST(P4,$N$6,$N$7,0) -> 3.1279138
A5: =P5 -> 1.5300914 | C5: =C4+$B$4 -> 1.496647 | D5: 1.0222489 | E5: =_xlfn.NORM.DIST(D5,$B$2,$B$4,FALSE) -> 0.037263156 | F5: 1.332534 | G5: 265 | H5: 1.332534 | I5: 1 | P5: ='Cap Table'!AF23 -> 1.5300914 | Q5: =_xlfn.NORM.DIST(P5,$N$6,$N$7,0) -> 3.0490264
A6: =P6 -> 1.7363498 | C6: =C5+$B$4 -> 1.6607601 | D6: 1.056119 | E6: =_xlfn.NORM.DIST(D6,$B$2,$B$4,FALSE) -> 0.066240596 | F6: 1.496647 | G6: 696 | H6: 1.496647 | I6: 2 | M6: Mean | N6: ='Cap Table'!AF27 -> 1.496647 | P6: ='Cap Table'!AF24 -> 1.7363498 | Q6: =_xlfn.NORM.DIST(P6,$N$6,$N$7,0) -> 0.52201558
C7: =C6+$B$4 -> 1.8248732 | D7: 1.0745018 | E7: =_xlfn.NORM.DIST(D7,$B$2,$B$4,FALSE) -> 0.088916429 | F7: 1.6607601 | G7: 666 | H7: 1.6607601 | I7: 1 | M7: Std Dev | N7: =_xlfn.STDEV.P('ROI Analysis'!AR22,'ROI Analysis'!AR23,'Cap Table'!AF24,'Cap Table'!AF25,'Cap Table'!AF26) -> 0.1263373
C8: =C7+$B$4 -> 1.9889863 | D8: 1.0755765 | E8: =_xlfn.NORM.DIST(D8,$B$2,$B$4,FALSE) -> 0.090424904 | F8: 1.8248732 | G8: 274 | H8: 1.8248732 | I8: 1
D9: 1.0803707 | E9: =_xlfn.NORM.DIST(D9,$B$2,$B$4,FALSE) -> 0.097421381 | F9: 1.9889863 | G9: 49 | H9: 1.9889863 | I9: 0
D10: 1.0881322 | E10: =_xlfn.NORM.DIST(D10,$B$2,$B$4,FALSE) -> 0.1097153 | F10: More | G10: 8 | H10: More | I10: 0
D11: 1.0948071 | E11: =_xlfn.NORM.DIST(D11,$B$2,$B$4,FALSE) -> 0.12130464
D12: 1.0979117 | E12: =_xlfn.NORM.DIST(D12,$B$2,$B$4,FALSE) -> 0.12703296
D13: 1.1006342 | E13: =_xlfn.NORM.DIST(D13,$B$2,$B$4,FALSE) -> 0.1322395
D14: 1.1025448 | E14: =_xlfn.NORM.DIST(D14,$B$2,$B$4,FALSE) -> 0.13599777
D15: 1.1059927 | E15: =_xlfn.NORM.DIST(D15,$B$2,$B$4,FALSE) -> 0.14300359
D16: 1.1107541 | E16: =_xlfn.NORM.DIST(D16,$B$2,$B$4,FALSE) -> 0.15316427
D17: 1.1128138 | E17: =_xlfn.NORM.DIST(D17,$B$2,$B$4,FALSE) -> 0.15773944
D18: 1.1259248 | E18: =_xlfn.NORM.DIST(D18,$B$2,$B$4,FALSE) -> 0.1895405
D19: 1.1303399 | E19: =_xlfn.NORM.DIST(D19,$B$2,$B$4,FALSE) -> 0.20134359
D20: 1.1309728 | E20: =_xlfn.NORM.DIST(D20,$B$2,$B$4,FALSE) -> 0.20308259
D21: 1.134355 | E21: =_xlfn.NORM.DIST(D21,$B$2,$B$4,FALSE) -> 0.21258063
D22: 1.1355461 | E22: =_xlfn.NORM.DIST(D22,$B$2,$B$4,FALSE) -> 0.21600835
... D2001: 2.0926454 | E2001: =_xlfn.NORM.DIST(D2001,$B$2,$B$4,FALSE) -> 0.0033255648
