Workbook

Sheet User model
A1: Year | B1: Assumptions | D1: 1 | E1: 2 | F1: 3 | G1: 4 | H1: 5
A2: Total App store Page Views | B2: Assumed 18.52% conversion rate of health & fitness apps on app store https://splitmetrics.com/blog/good-app-store-conversion-rate/ | C2: 0.1852 | D2: =(D3/$C$2)*100% -> 1906198.7 | E2: =(E3/$C$2)*100% -> 1783299.5 | F2: =(F3/$C$2)*100% -> 3336648 | G2: =(G3/$C$2)*100% -> 6243045.6 | H2: =(H3/$C$2)*100% -> 11681070
A3: Total Downloads | B3: Assumed 97% unpaid users - headspace 1m paid users out of 31m users in 2018 - see K29 https://www.cnbc.com/2018/09/02/companies-are-turning-to-headspace-to-help-their-workers-meditate.html | D3: =(D4/$K$29)*100% -> 353028 | E3: =(E4/$K$29)*100% -> 330267.07 | F3: =(F4/$K$29)*100% -> 617947.22 | G3: =(G4/$K$29)*100% -> 1156212.1 | H3: =(H4/$K$29)*100% -> 2163334.1
A4: Total PayingUsers | B4: Assumed C2% of Headspace Yr1 Users | C4: 0.5 | D4: =C4*D28 -> 11388 | E4: =D4*K4 -> 10653.776 | F4: =E4*K5 -> 19933.781 | G4: =F4*K5 -> 37297.163 | H4: =G4*K5 -> 69784.972 | J4: Yr 1-2 CAGR | K4: =D30*L4 -> 0.93552655 | L4: 0.5 | M4: Assumed L2% of Headspace CAGR Yr 1-3
A5: Total Revs | D5: =SUM(D9,D13,D18) -> 3141721.4 | E5: =SUM(E9,E13,E18) -> 3450545.1 | F5: =SUM(F9,F13,F18) -> 7412974.5 | G5: =SUM(G9,G13,G18) -> 14317635 | H5: =SUM(H9,H13,H18) -> 30641186 | J5: Yr 3-6 CAGR | K5: =D30 -> 1.8710531
D6: 750 | E6: 1750 | F6: 2000 | G6: 3000 | H6: 4500
A7: Tier 1 % of Users | B7: 100% - Tier 2 - Tier 3 | D7: =1-D11-D16 -> 0.45 | E7: =1-E11-E16 -> 0.35 | F7: =1-F11-F16 -> 0.25 | G7: =1-G11-G16 -> 0.2 | H7: =1-H11-H16 -> 0.09 | I7: Access to 1 course (6 lessons) access
A8: No of Users | B8: % of Tier Users x Total Paying Users for this year | D8: =D7*D$4 -> 5124.6 | E8: =E7*E$4 -> 3728.8217 | F8: =F7*F$4 -> 4983.4453 | G8: =G7*G$4 -> 7459.4326 | H8: =H7*H$4 -> 6280.6475 | I8: (Free online community)
A9: Revenues | C9: 119.88 | D9: =D8*$C9 -> 614337.05 | E9: =E8*$C9 -> 447011.15 | F9: =F8*$C9 -> 597415.42 | G9: =G8*$C9 -> 894236.78 | H9: =H8*$C9 -> 752924.02
A11: Tier 2 % of users | B11: Assumed most attractive 'middle version' (manual input) | D11: 0.5 | E11: 0.55 | F11: 0.6 | G11: 0.65 | H11: 0.7 | I11: Access 1 courses + 2x betterhelp checkins
A12: No of Users | B12: % of Tier Users x Total Paying Users for this year | D12: =D11*D$4 -> 5694 | E12: =E11*E$4 -> 5859.577 | F12: =F11*F$4 -> 11960.269 | G12: =G11*G$4 -> 24243.156 | H12: =H11*H$4 -> 48849.481 | I12: (AI Therapist)
A13: Revenues | C13: 359.88 | D13: =D12*$C13 -> 2049156.7 | E13: =E12*$C13 -> 2108744.6 | F13: =F12*$C13 -> 4304261.5 | G13: =G12*$C13 -> 8724627 | H13: =H12*$C13 -> 17579951 | I13: (Free online community)
A15: Tier 3
A16: Users % | B16: Manual input | D16: 0.05 | E16: 0.1 | F16: 0.15 | G16: 0.15 | H16: 0.21 | I16: Access 1 courses + 6x betterhelp checkins
A17: No of Users | B17: % of Tier Users x Total Paying Users for this year | D17: =D16*D$4 -> 569.4 | E17: =E16*E$4 -> 1065.3776 | F17: =F16*F$4 -> 2990.0672 | G17: =G16*G$4 -> 5594.5744 | H17: =H16*H$4 -> 14654.844 | I17: (AI Therapist)
A18: Revenues | C18: 839.88 | D18: =D17*$C18 -> 478227.67 | E18: =E17*$C18 -> 894789.37 | F18: =F17*$C18 -> 2511297.6 | G18: =G17*$C18 -> 4698771.2 | H18: =H17*$C18 -> 12308311 | I18: (Free online community)
A20: Average Revenue per User Per Year | B20: Total Revenue this year / Total Users this year | D20: =D5/D4 -> 275.88 | E20: =E5/E4 -> 323.88 | F20: =F5/F4 -> 371.88 | G20: =G5/G4 -> 383.88 | H20: =H5/H4 -> 439.08
A21: Average Revenue per User Per Month | B21: Total Revenue this year / Total Users this year / 12 months | D21: =D20/12 -> 22.99 | E21: =E20/12 -> 26.99 | F21: =F20/12 -> 30.99 | G21: =G20/12 -> 31.99 | H21: =H20/12 -> 36.59
C24: Check totals | D24: =IF(SUM(D17,D12,D8)=D4,"OK","CHECK") -> OK | E24: =IF(SUM(E17,E12,E8)=E4,"OK","CHECK") -> OK | F24: =IF(SUM(F17,F12,F8)=F4,"OK","CHECK") -> OK | G24: =IF(SUM(G17,G12,G8)=G4,"OK","CHECK") -> OK | H24: =IF(SUM(H17,H12,H8)=H4,"OK","CHECK") -> OK
A26: Learning from Headspace User Growth
A27: https://www.headspace.com/1million/subscribers | D27: 2012 | E27: 2013 | F27: 2014 | G27: 2015 | H27: 2016 | I27: 2017 | J27: 2018 | K27: % of paying users:
A28: 300 downloads first day in June 2012; 1m subscribers - June 2018 | C28: Users | D28: =(312*20%)*365 -> 22776 | E28: =D28*$D$30 -> 42615.105 | F28: =E28*$D$30 -> 79735.125 | G28: =F28*$D$30 -> 149188.65 | H28: =G28*$D$30 -> 279139.89 | I28: =H28*$D$30 -> 522285.55 | J28: 1000000
B29: Note - key driver - headspace 312 downloads day 1. TBD how many year 1 - which has dramatic impact on CAGR. | C29: Total Users | D29: =(D28/$K$29)*100% -> 706056 | E29: =(E28/$K$29)*100% -> 1321068.3 | F29: =(F28/$K$29)*100% -> 2471788.9 | G29: =(G28/$K$29)*100% -> 4624848.2 | H29: =(H28/$K$29)*100% -> 8653336.5 | I29: =(I28/$K$29)*100% -> 16190852 | J29: 31000000 | K29: =J28/J29 -> 0.032258065
B30: Assumed 312 downloads day 1. Assumes 20% of day 1 downloads daily for year 1. | C30: CAGR | D30: =((J28-D28)/D28)^(1/6) -> 1.8710531
E31: =D28/E28 -> 0.53445838 | F31: =E28/F28 -> 0.53445838 | G31: =F28/G28 -> 0.53445838 | H31: =G28/H28 -> 0.53445838 | I31: =H28/I28 -> 0.53445838 | J31: =I28/J28 -> 0.52228555
A32: Headspace | B32: Calm | C32: Betterhelp
D33: Betterhelp Expenses
C34: # Weeks/Sessions | D34: =D6 -> 750 | E34: =E6 -> 1750 | F34: =F6 -> 2000 | G34: 3250 | H34: 5000
B35: Tier 2 | C35: 3 | D35: =D11*D34 -> 375 | E35: =E11*E34 -> 962.5 | F35: =F11*F34 -> 1200 | G35: =G11*G34 -> 2112.5 | H35: =H11*H34 -> 3500
B36: Tier 3 | C36: 12 | D36: =D16*D34 -> 37.5 | E36: =E16*E34 -> 175 | F36: =F16*F34 -> 300 | G36: =G16*G34 -> 487.5 | H36: =H16*H34 -> 1050
D37: =SUM(D35:D36) -> 412.5 | E37: =SUM(E35:E36) -> 1137.5 | F37: =SUM(F35:F36) -> 1500 | G37: =SUM(G35:G36) -> 2600 | H37: =SUM(H35:H36) -> 4550
C38: 50 | D38: =D37*$C$38 -> 20625 | E38: =E37*$C$38 -> 56875 | F38: =F37*$C$38 -> 75000 | G38: =G37*$C$38 -> 130000 | H38: =H37*$C$38 -> 227500
A41: Market share estimates
A42: Target market size (people with phobia we will tackle and have a smartphone) | B42: 18000000
A43: People that received mental health services | B43: =B42*42.6% -> 7668000 | D43: https://www.nimh.nih.gov/health/statistics/mental-illness.shtml 2017 - 42.6% of people with mental health issues received mental health services
A44: People that will seek a digital treatment | B44: =B43*$C44 -> 4907520 | C44: 0.64 | D44: Proxy - 64% of US track their health metrics using digital https://www.ortholive.com/blog/32-statistics-on-mhealth/
A45: People that seek a digital treatment that choose VReeMind | B45: =B44*$C45 -> 711590.4 | C45: =29%/2 -> 0.145 | D45: Assumed 50% of Headspace market share (50% x 29% headspace market shared). 29% based on $56m revenue in 2019 in a $195m revenue industry https://techcrunch.com/2020/01/30/top-10-meditation-apps-pulled-in-195m-in-2019-up-52-from-2018/
A46: Representative market share | B46: =B45/B42 -> 0.0395328

Sheet Pricing tiers
B3: Tier 0 - Freemium | E3: Tier 1 - Silver | H3: Tier 2 - Gold | K3: Tier 3 - Platinum
A4: Features | B4: Access to all courses (1 level) | E4: Access to 1 course (12 levels) | H4: Access to all courses (12 levels) | K4: Access to all courses (12 levels)
B5: (Free online community) | E5: (Free online community) | H5: (Free online community) | K5: (Free online community)
H6: AI Therapist Freya | K6: AI Therapist Freya
H7: Betterhelp therapist for 3 weeks worth 60 USD/week (start, mid and end of therapy) | K7: Betterhelp therapist for 12 weeks worth 60 USD/week (1 week per month)
A9: Betterhelp value | H9: Number of weeks | I9: 3 | K9: Number of weeks | L9: 12
H10: Normal price Betterhelp | I10: 60 | K10: Normal price Betterhelp | L10: =I10 -> 60
H11: Value to customer | I11: =I9*I10 -> 180 | K11: Value to customer | L11: =L9*L10 -> 720
A13: Price | B13: Annual | C13: =C14*12 -> 0 | E13: Annual | F13: =F14*12 -> 119.88 | H13: Annual | I13: =I14*12 -> 359.88 | K13: Annual | L13: =L14*12 -> 839.88
B14: Monthly installments | C14: 0 | E14: Monthly installments | F14: 9.99 | H14: Monthly installments | I14: 29.99 | K14: Monthly installments | L14: 69.99
E15: *Monthly price is what we show in our offer - like Headspace and Calm do - but we charge full amount
A16: Betterhelp costs | H16: Cost per week to us | I16: 45 | K16: Cost per week to us | L16: =I16 -> 45
H17: Costs to us | I17: =I9*I16 -> 135 | K17: Costs to us | L17: =L9*L16 -> 540
A19: Gross Margin | C19: =C13-C17 -> 0 | F19: =F13-F17 -> 119.88 | I19: =I13-I17 -> 224.88 | L19: =L13-L17 -> 299.88
A21: Features | H21: Tier 2 | K21: Tier 3
H22: Access to all courses (12 levels) | K22: Access to all courses (12 levels)
H23: (Free online community) | K23: (Free online community)
H24: Betterhelp therapist for 2 sessions (beginning & end) | K24: Betterhelp therapist for 4 sessions (quarterly)
H25: * REMOVED AI Therapist | K25: AI Therapist Freya
A27: Betterhelp value | H27: Number of sessions | I27: 2 | K27: Number of sessions | L27: 4
A29: Price | B29: Annual | C29: =C30*12 -> 0 | E29: Annual | F29: 120 | H29: Annual | I29: 300 | K29: Annual | L29: 600
B30: Monthly installments | C30: 0 | E30: Monthly installments | F30: =F29/10 -> 12 | H30: Monthly installments | I30: =I29/10 -> 30 | K30: Monthly installments | L30: =L29/10 -> 60
E31: *Monthly installments divided by 10 - charge more per month than annual
A32: Betterhelp costs | H32: Cost per session | I32: 45 | K32: Cost per session | L32: =I32 -> 45
H33: Costs to us | I33: =I27*I32 -> 90 | K33: Costs to us | L33: =L32*4 -> 180
A35: Gross Margin - Annual Subscription | C35: =C29-C33 -> 0 | F35: =F29-F33 -> 120 | I35: =I29-I33 -> 210 | L35: =L29-L33 -> 420

Sheet Competitive prices
B2: Headspace | N2: Betterhelp
N4: With BetterHelp you can have professional counseling for only €60 per week, charged every 4 weeks. Unlike traditional in-office therapy which can cost €125-€200 for a single session, your BetterHelp membership includes unlimited text, video, audio messaging as well as weekly live sessions. The subscription is billed and renewed every 4 weeks. It includes both the use of the secured site and the counseling service itself.
N6: Traditional in-office therapy
N8: Which can cost €125-€200 for a single session
N9: NEED A SOLID SOURCE FOR THIS!
B18: Calm | N18: Limbix
B32: Price comparison - https://www.priceintelligently.com/blog/headspace-calm-pricing

Sheet Pricing tiers VISUAL
C3: Tier 0 - Freemium | E3: Tier 1 - Silver | G3: Tier 2 - Gold | I3: Tier 3 - Platinum
A4: Features
A5: Phobia courses | C5: All courses, first level only | E5: 1 full course (12 levels) | G5: All full courses (12 levels) | I5: All full courses (12 levels)
A6: Community | C6: Full access | E6: Full access | G6: Full access | I6: Full access
A7: AI Therapist Freya | C7: Try-out, 1 level only | E7: Try-out, 1 level only | G7: Full use | I7: Full use
A8: Betterhelp therapist | C8: Not included, optional in-app purchase | E8: Not included, optional in-app purchase | G8: 3 sessions of 1 full week (start, mid- and end of therapy) | I8: 12 sessions of 1 full week (i.e. monthly)
A10: Monthly fee | C10: ='Pricing tiers'!C13 -> 0 | E10: ='Pricing tiers'!F14 -> 9.99 | G10: ='Pricing tiers'!I14 -> 29.99 | I10: ='Pricing tiers'!L14 -> 69.99
A11: Annual fee | C11: ='Pricing tiers'!C14 -> 0 | E11: ='Pricing tiers'!F13 -> 119.88 | G11: ='Pricing tiers'!I13 -> 359.88 | I11: ='Pricing tiers'!L13 -> 839.88
